Workbook

Sheet Caratula
A1: Junio - 2026
A4: º
A26: *Observación: En base a los datos del sistema SOFIA proveído por la Dirección Nacional de Aduanas.
A27: Uso exclusivo de las empresas asociadas de CADAM
A28: Elaborado por el departamento de estadística - CADAM

Sheet Indice
A1: =UPPER("Cuadro") -> CUADRO | B1: DESCRIPCIÓN | C1: PÁGINA
A2: Cuadro 1 | B2: Parque Automotor : vehículos y camiones 0km, mensual 2014 y anual 1998-2026 | C2: 1
A3: Cuadro 2 | B3: Importación de vehículos por tipo,variacion 2022-2026 | C3: 2
A4: Cuadro 3 | B4: Importación de vehículos por tipo y mes, 2026 | C4: 3
A5: Cuadro 4 | B5: Importación de vehículos variación mensual, 2025-2026 | C5: 4
A6: Cuadro 5 | B6: Importación de vehículos por marca y mes, 2026 | C6: 5
A7: Cuadro 6 | B7: Importación de vehículos por pais de procedencia y mes, 2026 | C7: 6
A8: Cuadro 7 | B8: Importación de vehículos por Marca y empresa, 2026 | C8: 7
A9: Cuadro 8 | B9: Importación de vehículos por modelo, por mes y valor Cif U$S de importación, 2026 | C9: 8
A10: Cuadro 9 | B10: Importación de vehículos por tipo, 2026 | C10: 9
A11: Cuadro 10 | B11: Importaciones por tipos de vehículos y tipos de combustibles, por mes, 2026 | C11: 10
A12: Cuadro 11 | B12: Importación de vehículos por tipo y mes. Serie 2008-2026 | C12: 11
A13: Cuadro 12 | B13: Importación de vehículos 0km y usados por año, 1998-2026 | C13: 12
... A30: Cuadro 29 | B30: Importación de vehículos 0Km por marca 2003-2024 | C30: 29

Sheet Resumen
A1: Valor CIF de importaciones de automotores, en millones de U$S, por año, 2010-2025 | U1: Valor CIF de importación de automotores, en millones de U$S. 2025- 2026
A2: Total | B2: 2010 | C2: 2011 | D2: 2012 | E2: 2013 | F2: 2014 | G2: 2015 | H2: 2016 | I2: 2017 | J2: 2018 | K2: 2019 | L2: 2020 | M2: 2021 | N2: 2022 | O2: 2023 | P2: 2024 | Q2: 2025 | R2: Var.% 2025/2024 | U2: Total | V2: Jun 2025 | W2: Jun 2026 | X2: Var. %
A3: Vehículos 0km | B3: 315.699 | C3: 470.889 | D3: 486.904 | E3: 478.969 | F3: 530.901 | G3: 448 | H3: 382.577 | I3: 493.28079 | J3: 621.22749 | K3: 467.39855 | L3: 361.98061 | M3: 490.10006 | N3: 628.17492 | O3: 620.92963 | P3: 747.42954 | Q3: 750.46409 | R3: =+Q3/P3-1 -> 0.0040599791 | U3: Vehículos 0km | V3: 352.22159 | W3: 492.43829 | X3: =+W3/V3-1 -> 0.39809228 | Z3: =+Y3/1000000 -> 0
A4: Camiones 0km | B4: 49.845 | C4: 56.693 | D4: 63.913 | E4: 56.581 | F4: 55.937 | G4: 98.9 | H4: 61.22 | I4: 66.73418 | J4: 66.73418 | K4: 58.353199 | L4: 36.112935 | M4: 45.208219 | N4: 43.467873 | O4: 56.169802 | P4: 57.089428 | Q4: 77.838796 | R4: =+Q4/P4-1 -> 0.36345377 | U4: Camiones 0km | V4: 34.367659 | W4: 35.561022 | X4: =+W4/V4-1 -> 0.034723437 | Z4: =+Y4/1000000 -> 0
A5: Tractores | B5: 67.092 | C5: 111.452 | D5: 49.084 | R5: =+D5/C5-1 -> -0.55959516 | U5: Tractores | X5: =+W5/V5-1 -> #DIV/0!
A6: Cosechadoras | B6: 52.196 | C6: 108.802 | D6: 42.098 | R6: =+D6/C6-1 -> -0.61307697 | U6: Cosechadoras | X6: =+W6/V6-1 -> #DIV/0!
A7: Pulverizadoras | B7: 7.885 | C7: 46.227 | D7: 16.101 | R7: =+D7/C7-1 -> -0.65169706 | U7: Pulverizadoras | X7: =+W7/V7-1 -> #DIV/0!
A8: Maq. Viales e industriales | B8: 24.5775 | C8: 39.0646 | D8: 39.037 | R8: =+D8/C8-1 -> -0.00070652202 | U8: Maq. Viales e industriales | X8: =+W8/V8-1 -> #DIV/0!
A9: Total | B9: =SUM(B3:B8) -> 517.2945 | C9: =SUM(C3:C8) -> 833.1276 | D9: =SUM(D3:D8) -> 697.137 | E9: =SUM(E3:E8) -> 535.55 | F9: =SUM(F3:F8) -> 586.838 | G9: =SUM(G3:G8) -> 546.9 | H9: =SUM(H3:H8) -> 443.797 | I9: =SUM(I3:I8) -> 560.01497 | ... O9: =SUM(O3:O8) -> 677.09944 | P9: =SUM(P3:P4) -> 804.51897 | Q9: =SUM(Q3:Q4) -> 828.30288 | R9: =+Q9/P9-1 -> 0.029562903 | U9: Total | V9: =SUM(V3:V8) -> 386.58925 | W9: =SUM(W3:W8) -> 527.99931 | X9: =+W9/V9-1 -> 0.36578891
A10: Elaboracion: CADAM. Fuente: Penta Transaction. | U10: Elaboracion: CADAM. Fuente: Penta Transaction.
A12: Importación de automotores, en unidades, por año, 2010-2025 | U12: Importación de automotores, en unidades, 2025-2026
A13: Total | B13: 2010 | C13: 2011 | D13: 2012 | E13: 2013 | F13: 2014 | G13: 2015 | H13: 2016 | I13: 2017 | J13: 2018 | K13: 2019 | L13: 2020 | M13: 2021 | N13: 2022 | O13: 2023 | P13: 2024 | Q13: 2025 | R13: Var.% 2025/2024 | U13: Total | V13: Jun 2025 | W13: Jun 2026 | X13: Var. %
A14: Vehículos 0km | B14: 20215 | C14: 29392 | D14: 28887 | E14: 28190 | F14: 30691 | G14: 24559 | H14: 20802 | I14: 27851 | J14: 35890 | K14: 28437 | L14: 22000 | M14: 27910 | N14: 34185 | O14: 29720 | P14: 34705 | Q14: 38611 | R14: =+Q14/P14-1 -> 0.11254862 | U14: Vehículos 0km | V14: 16850 | W14: 24047 | X14: =+W14/V14-1 -> 0.42712166
A15: Camiones 0km | B15: 1814 | C15: 2415 | D15: 2715 | E15: 2930 | F15: 3470 | G15: 3786 | H15: 2017 | I15: 2510 | J15: 2509 | K15: 2298 | L15: 1479 | M15: 1821 | N15: 1563 | O15: 1677 | P15: 2013 | Q15: 2341 | R15: =+Q15/P15-1 -> 0.16294088 | U15: Camiones 0km | V15: 939 | W15: 1298 | X15: =+W15/V15-1 -> 0.38232162
A16: Tractores | B16: 1854 | C16: 2963 | D16: 1235 | R16: =+J16/H16-1 -> #DIV/0! | U16: Tractores | X16: =+W16/V16-1 -> #DIV/0!
A17: Cosechadoras | B17: 435 | C17: 720 | D17: 420 | R17: =+J17/H17-1 -> #DIV/0! | U17: Cosechadoras | X17: =+W17/V17-1 -> #DIV/0!
A18: Pulverizadoras | B18: 131 | C18: 371 | D18: 119 | R18: =+J18/H18-1 -> #DIV/0! | U18: Pulverizadoras | X18: =+W18/V18-1 -> #DIV/0!
A19: Maq. Viales e industriales | B19: 312 | C19: 802 | D19: 676 | R19: =+J19/H19-1 -> #DIV/0! | U19: Maq. Viales e industriales | X19: =+W19/V19-1 -> #DIV/0!
A20: Total Vehiculos y Camiones | B20: =+B14+B15 -> 22029 | C20: =+C14+C15 -> 31807 | D20: =+D14+D15 -> 31602 | E20: =SUM(E14:E19) -> 31120 | F20: =SUM(F14:F19) -> 34161 | G20: =SUM(G14:G19) -> 28345 | H20: =SUM(H14:H19) -> 22819 | I20: =+I14+I15 -> 30361 | J20: =+J14+J15 -> 38399 | K20: =SUM(K14:K19) -> 30735 | L20: =SUM(L14:L19) -> 23479 | M20: =SUM(M14:M19) -> 29731 | N20: =SUM(N14:N19) -> 35748 | O20: =SUM(O14:O19) -> 31397 | P20: =SUM(P14:P15) -> 36718 | Q20: =SUM(Q14:Q15) -> 40952 | R20: =+Q20/P20-1 -> 0.11531129 | U20: Total | V20: =SUM(V14:V19) -> 17789 | W20: =SUM(W14:W19) -> 25345 | X20: =+W20/V20-1 -> 0.42475687
A21: Elaboracion: CADAM. Fuente: DNA | U21: Elaboración: CADAM. Fuente: DNA

Sheet 1
A1: Parque Automotor : vehículos y camiones 0km, mensual 2020 y anual 1998-2026
A3: Cuadro 1: Importaciones de automoviles y camiones 0km, mensual 2026
A4: Año | B4: Vehículos | C4: Var % | D4: Camiones | E4: Var % | F4: Total | G4: Var %
A5: Enero | B5: 3205 | D5: 182 | F5: =+B5+D5 -> 3387
A6: Febrero | B6: 3319 | C6: =+B6/B5-1 -> 0.035569423 | D6: 198 | E6: =+D6/D5-1 -> 0.087912088 | F6: =+B6+D6 -> 3517 | G6: =+F6/F5-1 -> 0.038382049
A7: Marzo | B7: 4038 | C7: =+B7/B6-1 -> 0.21663152 | D7: 214 | E7: =+D7/D6-1 -> 0.080808081 | F7: =+B7+D7 -> 4252 | G7: =+F7/F6-1 -> 0.20898493
A8: Abril | B8: 4624 | C8: =+B8/B7-1 -> 0.14512135 | D8: 290 | E8: =+D8/D7-1 -> 0.35514019 | F8: =+B8+D8 -> 4914 | G8: =+F8/F7-1 -> 0.15569144
A9: Mayo | B9: 4341 | C9: =+B9/B8-1 -> -0.061202422 | D9: 206 | E9: =+D9/D8-1 -> -0.28965517 | F9: =+B9+D9 -> 4547 | G9: =+F9/F8-1 -> -0.074684575
A10: Junio | B10: 4520 | C10: =+B10/B9-1 -> 0.041234739 | D10: 208 | E10: =+D10/D9-1 -> 0.0097087379 | F10: =+B10+D10 -> 4728 | G10: =+F10/F9-1 -> 0.039806466
A11: Julio | C11: =+B11/B10-1 -> -1 | E11: =+D11/D10-1 -> -1 | F11: =+B11+D11 -> 0 | G11: =+F11/F10-1 -> -1
A12: Agosto | C12: =+B12/B11-1 -> #DIV/0! | E12: =+D12/D11-1 -> #DIV/0! | F12: =+B12+D12 -> 0 | G12: =+F12/F11-1 -> #DIV/0!
A13: Septiembre | C13: =+B13/B12-1 -> #DIV/0! | E13: =+D13/D12-1 -> #DIV/0! | F13: =+B13+D13 -> 0 | G13: =+F13/F12-1 -> #DIV/0!
A14: Octubre | C14: =+B14/B13-1 -> #DIV/0! | E14: =+D14/D13-1 -> #DIV/0! | F14: =+B14+D14 -> 0 | G14: =+F14/F13-1 -> #DIV/0!
A15: Noviembre | C15: =+B15/B14-1 -> #DIV/0! | E15: =+D15/D14-1 -> #DIV/0! | F15: =+B15+D15 -> 0 | G15: =+F15/F14-1 -> #DIV/0!
A16: Diciembre | C16: =+B16/B15-1 -> #DIV/0! | E16: =+D16/D15-1 -> #DIV/0! | F16: =+B16+D16 -> 0 | G16: =+F16/F15-1 -> #DIV/0!
A17: Total | B17: =SUM(B5:B16) -> 24047 | D17: =SUM(D5:D16) -> 1298 | F17: =SUM(F5:F16) -> 25345
A18: Fuente: CADAM
A20: Cuadro 1A:Importaciones de vehículos y camiones 0km, 1998-2026
A21: Año | B21: Vehículos | C21: Var % | D21: Camiones | E21: Var % | F21: Total | G21: Var %
A23: 1998 | B23: 15259 | D23: 1152 | F23: =+B23+D23 -> 16411
A24: 1999 | B24: 9666 | C24: =+B24/B23-1 -> -0.36653778 | D24: 887 | E24: =+D24/D23-1 -> -0.23003472 | F24: =+B24+D24 -> 10553 | G24: =+F24/F23-1 -> -0.3569557
A25: 2000 | B25: 6780 | C25: =+B25/B24-1 -> -0.29857232 | D25: 524 | E25: =+D25/D24-1 -> -0.40924464 | F25: =+B25+D25 -> 7304 | G25: =+F25/F24-1 -> -0.30787454
A26: 2001 | B26: 6559 | C26: =+B26/B25-1 -> -0.03259587 | D26: 427 | E26: =+D26/D25-1 -> -0.1851145 | F26: =+B26+D26 -> 6986 | G26: =+F26/F25-1 -> -0.043537788
A27: 2002 | B27: 2842 | C27: =+B27/B26-1 -> -0.56670224 | D27: 192 | E27: =+D27/D26-1 -> -0.55035129 | F27: =+B27+D27 -> 3034 | G27: =+F27/F26-1 -> -0.56570283
A28: 2003 | B28: 3209 | C28: =+B28/B27-1 -> 0.12913441 | D28: 53 | E28: =+D28/D27-1 -> -0.72395833 | F28: =+B28+D28 -> 3262 | G28: =+F28/F27-1 -> 0.075148319
A29: 2004 | B29: 5720 | C29: =+B29/B28-1 -> 0.78248676 | D29: 234 | E29: =+D29/D28-1 -> 3.4150943 | F29: =+B29+D29 -> 5954 | G29: =+F29/F28-1 -> 0.82526058
A30: 2005 | B30: 6710 | C30: =+B30/B29-1 -> 0.17307692 | D30: 399 | E30: =+D30/D29-1 -> 0.70512821 | F30: =+B30+D30 -> 7109 | G30: =+F30/F29-1 -> 0.19398724
A31: 2006 | B31: 8417 | C31: =+B31/B30-1 -> 0.25439642 | D31: 566 | E31: =+D31/D30-1 -> 0.41854637 | F31: =+B31+D31 -> 8983 | G31: =+F31/F30-1 -> 0.26360951
A32: 2007 | B32: 11898 | C32: =+B32/B31-1 -> 0.41356778 | D32: 1007 | E32: =+D32/D31-1 -> 0.77915194 | F32: =+B32+D32 -> 12905 | G32: =+F32/F31-1 -> 0.43660247
A33: 2008 | B33: 20266 | C33: =+B33/B32-1 -> 0.70331148 | D33: 2048 | E33: =+D33/D32-1 -> 1.0337637 | F33: =+B33+D33 -> 22314 | G33: =+F33/F32-1 -> 0.72909725
A34: 2009 | B34: 12160 | C34: =+B34/B33-1 -> -0.39998026 | D34: 1570 | E34: =+D34/D33-1 -> -0.23339844 | F34: =+B34+D34 -> 13730 | G34: =+F34/F33-1 -> -0.38469123
A35: 2010 | B35: 20215 | C35: =+B35/B34-1 -> 0.66241776 | D35: 1814 | E35: =+D35/D34-1 -> 0.15541401 | F35: =+B35+D35 -> 22029 | G35: =+F35/F34-1 -> 0.60444283
... A43: 2018 | B43: 35890 | C43: =+B43/B42-1 -> 0.28864314 | D43: 2509 | E43: =+D43/D42-1 -> -0.00039840637 | F43: =+B43+D43 -> 38399 | G43: =+F43/F42-1 -> 0.26474754
A44: 2019 | B44: 28437 | C44: =+B44/B43-1 -> -0.2076623 | D44: 2298 | E44: -0.08409725 | F44: 30735 | G44: =+F44/F43-1 -> -0.19958853
A45: 2020 | B45: 22000 | C45: =+B45/B44-1 -> -0.22636002 | D45: 1479 | E45: =+D45/D44-1 -> -0.35639687 | F45: =+B45+D45 -> 23479 | G45: =+F45/F44-1 -> -0.23608264
A46: 2021 | B46: 27910 | C46: =+B46/B45-1 -> 0.26863636 | D46: 1821 | E46: =+D46/D45-1 -> 0.23123732 | F46: =+B46+D46 -> 29731 | G46: =+F46/F45-1 -> 0.26628051
A47: 2022 | B47: 34185 | C47: =+B47/B46-1 -> 0.22482981 | D47: 1563 | E47: =+D47/D46-1 -> -0.1416804 | F47: =+B47+D47 -> 35748 | G47: =+F47/F46-1 -> 0.20238135
A48: 2023 | B48: 29720 | C48: =+B48/B47-1 -> -0.13061284 | D48: 1677 | E48: =+D48/D47-1 -> 0.07293666 | F48: =+B48+D48 -> 31397 | G48: =+F48/F47-1 -> -0.1217131
A49: 2024 | B49: 34705 | C49: =+B49/B48-1 -> 0.16773217 | D49: 2013 | E49: =+D49/D48-1 -> 0.20035778 | F49: =+B49+D49 -> 36718 | G49: =+F49/F48-1 -> 0.16947479
A50: 2025 | B50: 38611 | C50: =+B50/B49-1 -> 0.11254862 | D50: 2341 | E50: =+D50/D49-1 -> 0.16294088 | F50: =+B50+D50 -> 40952 | G50: =+F50/F49-1 -> 0.11531129
A51: Fuente: CADAM

Sheet 2
A1: Cuadro 2: Importación de automotores por tipo,variacion 2025 - 2026
A2: Tipo | B2: 46143 | C2: 46174 | D2: Var % | E2: 45809 | F2: 46174 | G2: Var % | H2: Acum 2025 | I2: Acum 2026 | J2: Acum Var % | K2: En %
B3: (a) | C3: ( b) | D3: (b)/(a) | E3: ('c) | F3: ( d) | G3: (d)/('c) | H3: (e) | I3: (f) | J3: (f)/('e) | K3: Junio
A4: Automóvil | B4: 555 | C4: 744 | D4: =+C4/B4-1 -> 0.34054054 | E4: 492 | F4: 744 | G4: =+F4/E4-1 -> 0.51219512 | H4: 2977 | I4: 2980 | J4: =+I4/H4-1 -> 0.0010077259 | K4: =+I4/I9 -> 0.12392398
A5: Furgón | B5: 31 | C5: 121 | D5: =+C5/B5-1 -> 2.9032258 | E5: 141 | F5: 121 | G5: =+F5/E5-1 -> -0.14184397 | H5: 388 | I5: 426 | J5: =+I5/H5-1 -> 0.097938144 | K5: =+I5/I9 -> 0.017715308
A6: Minibus | B6: 10 | C6: 10 | D6: =+C6/B6-1 -> 0 | E6: 13 | F6: 10 | G6: =+F6/E6-1 -> -0.23076923 | H6: 196 | I6: 141 | J6: =+I6/H6-1 -> -0.28061224 | K6: =+I6/I9 -> 0.0058635173
A7: Pick Up | B7: 1157 | C7: 733 | D7: =+C7/B7-1 -> -0.366465 | E7: 740 | F7: 733 | G7: =+F7/E7-1 -> -0.0094594595 | H7: 3792 | I7: 5315 | J7: =+I7/H7-1 -> 0.40163502 | K7: =+I7/I9 -> 0.22102549
A8: SUV | B8: 2588 | C8: 2912 | D8: =+C8/B8-1 -> 0.1251932 | E8: 1968 | F8: 2912 | G8: =+F8/E8-1 -> 0.4796748 | H8: 9497 | I8: 15185 | J8: =+I8/H8-1 -> 0.59892598 | K8: =+I8/I9 -> 0.6314717
A9: Total vehículos | B9: =SUM(B4:B8) -> 4341 | C9: =SUM(C4:C8) -> 4520 | D9: =+C9/B9-1 -> 0.041234739 | E9: =SUM(E4:E8) -> 3354 | F9: =SUM(F4:F8) -> 4520 | G9: =+F9/E9-1 -> 0.3476446 | H9: =SUM(H4:H8) -> 16850 | I9: =SUM(I4:I8) -> 24047 | J9: =+I9/H9-1 -> 0.42712166 | K9: =+I9/I9 -> 1
A10: Camión | B10: 169 | C10: 198 | D10: =+C10/B10-1 -> 0.17159763 | E10: 140 | F10: 198 | G10: =+F10/E10-1 -> 0.41428571 | H10: 882 | I10: 1226 | J10: =+I10/H10-1 -> 0.39002268 | K10: =+I10/I12 -> 0.94453005
A11: Omnibus | B11: 37 | C11: 10 | D11: =+C11/B11-1 -> -0.72972973 | E11: 3 | F11: 10 | G11: =+F11/E11-1 -> 2.3333333 | H11: 57 | I11: 72 | J11: =+I11/H11-1 -> 0.26315789 | K11: =+I11/I12 -> 0.055469954
A12: Total camiones | B12: =SUM(B10:B11) -> 206 | C12: =SUM(C10:C11) -> 208 | D12: =+C12/B12-1 -> 0.0097087379 | E12: =SUM(E10:E11) -> 143 | F12: =+F10+F11 -> 208 | G12: =+F12/E12-1 -> 0.45454545 | H12: =SUM(H10:H11) -> 939 | I12: =SUM(I10:I11) -> 1298 | J12: =+I12/H12-1 -> 0.38232162 | K12: =+I12/I12 -> 1
A13: Fuente: CADAM

Sheet 3
A1: Cuadro 3: Importación de vehículos por tipo y mes, 2026 | Q1: Cuadro 3 A: Importación de vehículos por tipo, 2011- 2026
A2: Tipo de vehículos | B2: Ene | C2: Feb | D2: Mar | E2: Abr | F2: May | G2: Jun | H2: Jul | I2: Ago | J2: Sep | K2: Oct | L2: Nov | M2: Dic | N2: Total | O2: % | Q2: Tipo de vehículos | R2: 2011 | T2: 2012 | V2: 2013 | X2: 2014 | Z2: 2015 | AB2: 2016 | AD2: 2017 | AF2: 2018 | AH2: 2019 | AJ2: 2020 | AL2: 2021 | AN2: 2022 | AP2: 2023 | AR2: 2024 | AT2: 2025 | AV2: 2026
A3: Automóvil | B3: 437 | C3: 371 | D3: 419 | E3: 454 | F3: 555 | G3: 744 | N3: =SUM(B3:M3) -> 2980 | O3: =+N3/$N$8 -> 0.12392398 | R3: Unidades | S3: En % | T3: Unidades | U3: En % | V3: Unidades | W3: En % | X3: Unidades | Y3: En % | Z3: Unidades | AA3: En % | AB3: Unidades | AC3: En % | AD3: Unidades | AE3: En % | AF3: Unidades | AG3: En % | AH3: Unidades | AI3: En % | AJ3: Unidades | AK3: En % | AL3: Unidades | AM3: En % | AN3: Unidades | AO3: En % | AP3: Unidades | AQ3: En % | AR3: Unidades | AS3: En % | AT3: Unidades | AU3: En % | AV3: Unidades | AW3: En %
A4: Furgón | B4: 63 | C4: 48 | D4: 34 | E4: 129 | F4: 31 | G4: 121 | N4: =SUM(B4:M4) -> 426 | O4: =+N4/$N$8 -> 0.017715308 | Q4: Automóvil | R4: 11732 | S4: =+R4/$R$9 -> 0.39915623 | T4: 10977 | U4: =+T4/$T$9 -> 0.37999792 | V4: 12740 | W4: =+V4/$V$9 -> 0.45193331 | X4: 13747 | Y4: =+X4/X9 -> 0.44791633 | Z4: 9108 | AA4: =+Z4/Z9 -> 0.37086201 | AB4: 8053 | AC4: =+AB4/AB9 -> 0.38712624 | AD4: 10886 | AE4: =+AD4/AD9 -> 0.39086568 | AF4: 15256 | AG4: =+AF4/$AF$9 -> 0.42507662 | AH4: 12974 | AI4: 0.45623659 | AJ4: 10827 | AK4: =+AJ4/AJ9 -> 0.49213636 | AL4: 10890 | AM4: =+AL4/AL9 -> 0.39018273 | AN4: 9379 | AO4: =+AN4/$AN$9 -> 0.2743601 | AP4: 6056 | AQ4: =+AP4/$AP$9 -> 0.20376851 | AR4: 6059 | AS4: =+AR4/$AR$9 -> 0.17458579 | AT4: 5134 | AU4: =+AT4/$AT$9 -> 0.16370651 | AV4: =+N3 -> 2980 | AW4: =+AV4/AV9 -> 0.12392398
A5: Minibus | B5: 46 | C5: 26 | D5: 35 | E5: 14 | F5: 10 | G5: 10 | N5: =SUM(B5:M5) -> 141 | O5: =+N5/$N$8 -> 0.0058635173 | Q5: Furgón | R5: 668 | S5: =+R5/$R$9 -> 0.022727273 | T5: 681 | U5: =+T5/$T$9 -> 0.023574618 | V5: 670 | W5: =+V5/$V$9 -> 0.023767293 | X5: 389 | Y5: =+X5/X9 -> 0.012674725 | Z5: 587 | AA5: =+Z5/Z9 -> 0.023901625 | AB5: 215 | AC5: =+AB5/AB9 -> 0.010335545 | AD5: 388 | AE5: =+AD5/AD9 -> 0.013931277 | AF5: 368 | AG5: =+AF5/$AF$9 -> 0.010253553 | AH5: 411 | AI5: 0.014453001 | AJ5: 188 | AK5: =+AJ5/AJ9 -> 0.0085454545 | AL5: 316 | AM5: =+AL5/AL9 -> 0.011322107 | AN5: 417 | AO5: =+AN5/$AN$9 -> 0.012198333 | AP5: 480 | AQ5: =+AP5/$AP$9 -> 0.01615074 | AR5: 529 | AS5: =+AR5/$AR$9 -> 0.01524276 | AT5: 679 | AU5: =+AT5/$AT$9 -> 0.021651095 | AV5: =+N4 -> 426 | AW5: =+AV5/AV9 -> 0.017715308
A6: Pick Up | B6: 557 | C6: 627 | D6: 938 | E6: 1303 | F6: 1157 | G6: 733 | N6: =SUM(B6:M6) -> 5315 | O6: =+N6/$N$8 -> 0.22102549 | Q6: Minibus | R6: 286 | S6: =+R6/$R$9 -> 0.0097305389 | T6: 365 | U6: =+T6/$T$9 -> 0.012635442 | V6: 398 | W6: =+V6/$V$9 -> 0.014118482 | X6: 408 | Y6: =+X6/X9 -> 0.013293799 | Z6: 285 | AA6: =+Z6/Z9 -> 0.011604707 | AB6: 163 | AC6: =+AB6/AB9 -> 0.007835785 | AD6: 197 | AE6: =+AD6/AD9 -> 0.0070733546 | AF6: 163 | AG6: =+AF6/$AF$9 -> 0.0045416551 | AH6: 177 | AI6: 0.0062242853 | AJ6: 106 | AK6: =+AJ6/AJ9 -> 0.0048181818 | AL6: 124 | AM6: =+AL6/AL9 -> 0.004442852 | AN6: 271 | AO6: =+AN6/$AN$9 -> 0.0079274536 | AP6: 251 | AQ6: =+AP6/$AP$9 -> 0.0084454913 | AR6: 373 | AS6: =+AR6/$AR$9 -> 0.010747731 | AT6: 277 | AU6: =+AT6/$AT$9 -> 0.0088326265 | AV6: =+N5 -> 141 | AW6: =+AV6/AV9 -> 0.0058635173
A7: SUV | B7: 2102 | C7: 2247 | D7: 2612 | E7: 2724 | F7: 2588 | G7: 2912 | N7: =SUM(B7:M7) -> 15185 | O7: =+N7/$N$8 -> 0.6314717 | Q7: Pick Up | R7: 10326 | S7: =+R7/$R$9 -> 0.35132009 | T7: 10303 | U7: =+T7/$T$9 -> 0.35666563 | V7: 8759 | W7: =+V7/$V$9 -> 0.31071302 | X7: 8557 | Y7: =+X7/X9 -> 0.27881138 | Z7: 7465 | AA7: =+Z7/Z9 -> 0.30396189 | AB7: 5823 | AC7: =+AB7/AB9 -> 0.27992501 | AD7: 8478 | AE7: =+AD7/AD9 -> 0.30440559 | AF7: 9645 | AG7: =+AF7/$AF$9 -> 0.26873781 | AH7: 6167 | AI7: 0.21686535 | AJ7: 4440 | AK7: =+AJ7/AJ9 -> 0.20181818 | AL7: 7737 | AM7: =+AL7/AL9 -> 0.27721247 | AN7: 7997 | AO7: =+AN7/$AN$9 -> 0.23393301 | AP7: 8292 | AQ7: =+AP7/$AP$9 -> 0.27900404 | AR7: 9267 | AS7: =+AR7/$AR$9 -> 0.26702204 | AT7: 7317 | AU7: =+AT7/$AR$9 -> 0.21083417 | AV7: =+N6 -> 5315 | AW7: =+AV7/AV9 -> 0.22102549
A8: Total vehículos | B8: =SUM(B3:B7) -> 3205 | C8: =SUM(C3:C7) -> 3319 | D8: =SUM(D3:D7) -> 4038 | E8: =SUM(E3:E7) -> 4624 | F8: =SUM(F3:F7) -> 4341 | G8: =SUM(G3:G7) -> 4520 | H8: =SUM(H3:H7) -> 0 | I8: =SUM(I3:I7) -> 0 | ... N8: =SUM(N3:N7) -> 24047 | O8: =+N8/$N$8 -> 1 | Q8: SUV | R8: 6380 | S8: =+R8/$R$9 -> 0.21706587 | T8: 6561 | U8: =+T8/$T$9 -> 0.22712639 | V8: 5623 | W8: =+V8/$V$9 -> 0.1994679 | X8: 7590 | Y8: =+X8/X9 -> 0.24730377 | Z8: 7114 | AA8: =+Z8/Z9 -> 0.28966977 | AB8: 6548 | AC8: =+AB8/AB9 -> 0.31477743 | AD8: 7902 | AE8: =+AD8/AD9 -> 0.2837241 | AF8: 10458 | AG8: =+AF8/$AF$9 -> 0.29139036 | AH8: 8708 | AI8: 0.30622077 | AJ8: 6439 | AK8: =+AJ8/AJ9 -> 0.29268182 | AL8: 8843 | AM8: =+AL8/AL9 -> 0.31683984 | AN8: 16121 | AO8: =+AN8/$AN$9 -> 0.4715811 | AP8: 14641 | AQ8: =+AP8/$AP$9 -> 0.49263122 | AR8: 18477 | AS8: =+AR8/$AR$9 -> 0.53240167 | AT8: 17954 | AU8: =+AT8/$AR$9 -> 0.5173318 | AV8: =+N7 -> 15185 | AW8: =+AV8/AV9 -> 0.6314717
A9: Crec, % mes | C9: =+C8/B8-1 -> 0.035569423 | D9: =+D8/C8-1 -> 0.21663152 | E9: =+E8/D8-1 -> 0.14512135 | F9: =+F8/E8-1 -> -0.061202422 | G9: =+G8/F8-1 -> 0.041234739 | H9: =+H8/G8-1 -> -1 | I9: =+I8/H8-1 -> #DIV/0! | J9: =+J8/I8-1 -> #DIV/0! | ... M9: =+M8/L8-1 -> #DIV/0! | Q9: Total | R9: =SUM(R4:R8) -> 29392 | S9: =SUM(S4:S8) -> 1 | T9: =SUM(T4:T8) -> 28887 | U9: =SUM(U4:U8) -> 1 | V9: =SUM(V4:V8) -> 28190 | W9: =SUM(W4:W8) -> 1 | X9: =SUM(X4:X8) -> 30691 | Y9: =SUM(Y4:Y8) -> 1 | ... AN9: =SUM(AN4:AN8) -> 34185 | AO9: =+AN9/$AN$9 -> 1 | AP9: =SUM(AP4:AP8) -> 29720 | AQ9: =+AP9/$AP$9 -> 1 | AR9: =SUM(AR4:AR8) -> 34705 | AS9: =+AR9/$AR$9 -> 1 | AT9: =SUM(AT4:AT8) -> 31361 | AV9: =SUM(AV4:AV8) -> 24047 | AW9: =SUM(AW4:AW8) -> 1
A10: Fuente: CADAM | Q10: Fuente: CADAM

Sheet 4
A1: Cuadro 4: Importación de vehículos variación mensual, 2025-2026 | P1: Cuadro 16: Importación de camiones, variación mensual, 2019-2020 | W1: Variación mensual autos y camiones 2020
A2: MESES | B2: 2025 | C2: Var. % 2025 | D2: 2026 | E2: Var. % 2026 | F2: Var. % 2026/2025 | P2: Meses | Q2: 2019 | R2: var. % 2019 | S2: 2020 | T2: var. % 2020 | U2: Var % 2020/2019 | W2: Meses | X2: 2019 | Y2: var. % 2019 | Z2: 2020 | AA2: var. % 2020
A4: Ene | B4: 2649 | C4: - | D4: 3205 | F4: =+D4/B4-1 -> 0.20989052 | P4: Ene | Q4: 274 | R4: - | S4: 253 | T4: - | U4: =+S4/Q4-1 -> -0.076642336 | W4: Ene | X4: =+B4+Q4 -> 2923 | Z4: =+D4+S4 -> 3458
A5: Feb | B5: 2457 | C5: =+B5/B4-1 -> -0.072480181 | D5: 3319 | E5: =+D5/D4-1 -> 0.035569423 | F5: =+D5/B5-1 -> 0.35083435 | P5: Feb | Q5: 242 | R5: =+Q5/Q4-1 -> -0.11678832 | S5: 190 | T5: =+S5/S4-1 -> -0.24901186 | U5: =+S5/Q5-1 -> -0.21487603 | W5: Feb | X5: =+B5+Q5 -> 2699 | Y5: =+X5/X4-1 -> -0.076633596 | Z5: =+D5+S5 -> 3509 | AA5: =+Z5/Z4-1 -> 0.014748409
A6: Mar | B6: 2913 | C6: =+B6/B5-1 -> 0.18559219 | D6: 4038 | E6: =+D6/D5-1 -> 0.21663152 | F6: =+D6/B6-1 -> 0.38619979 | P6: Mar | Q6: 313 | R6: =+Q6/Q5-1 -> 0.29338843 | S6: 93 | T6: =+S6/S5-1 -> -0.51052632 | U6: =+S6/Q6-1 -> -0.7028754 | W6: Mar | X6: =+B6+Q6 -> 3226 | Y6: =+X6/X5-1 -> 0.1952575 | Z6: =+D6+S6 -> 4131 | AA6: =+Z6/Z5-1 -> 0.17725848
A7: Abr | B7: 2537 | C7: =+B7/B6-1 -> -0.12907655 | D7: 4624 | E7: =+D7/D6-1 -> 0.14512135 | F7: =+D7/B7-1 -> 0.82262515 | P7: Abr | Q7: 233 | R7: =+Q7/Q6-1 -> -0.25559105 | T7: =+S7/S6-1 -> -1 | U7: =+S7/Q7-1 -> -1 | W7: Total | X7: =SUM(X4:X6) -> 8848 | Z7: =SUM(Z4:Z6) -> 11098
A8: May | B8: 2940 | C8: =+B8/B7-1 -> 0.15884903 | D8: 4341 | E8: =+D8/D7-1 -> -0.061202422 | F8: =+D8/B8-1 -> 0.47653061 | P8: May | Q8: 153 | R8: =+Q8/Q7-1 -> -0.34334764 | T8: =+S8/S7-1 -> #DIV/0! | U8: =+S8/Q8-1 -> -1 | Z8: =+Z7/X7-1 -> 0.25429476
A9: Jun | B9: 3354 | C9: =+B9/B8-1 -> 0.14081633 | D9: 4520 | E9: =+D9/D8-1 -> 0.041234739 | F9: =+D9/B9-1 -> 0.3476446 | P9: Jun | Q9: 96 | R9: =+Q9/Q8-1 -> -0.37254902 | T9: =+S9/S8-1 -> #DIV/0! | U9: =+S9/Q9-1 -> -1
A10: Jul | B10: 3480 | C10: =+B10/B9-1 -> 0.037567084 | E10: =+D10/D9-1 -> -1 | F10: =+D10/B10-1 -> -1 | P10: Jul | Q10: 188 | R10: =+Q10/Q9-1 -> 0.95833333 | T10: =+S10/S9-1 -> #DIV/0! | U10: =+S10/Q10-1 -> -1
A11: Ago | B11: 3330 | C11: =+B11/B10-1 -> -0.043103448 | E11: =+D11/D10-1 -> #DIV/0! | F11: =+D11/B11-1 -> -1 | P11: Ago | Q11: 173 | R11: =+Q11/Q10-1 -> -0.079787234 | T11: =+S11/S10-1 -> #DIV/0! | U11: =+S11/Q11-1 -> -1
A12: Sep | B12: 3197 | C12: =+B12/B11-1 -> -0.03993994 | E12: =+D12/D11-1 -> #DIV/0! | F12: =+D12/B12-1 -> -1 | P12: Sep | Q12: 146 | R12: =+Q12/Q11-1 -> -0.15606936 | T12: =+S12/S11-1 -> #DIV/0! | U12: =+S12/Q12-1 -> -1
A13: Oct | B13: 4504 | C13: =+B13/B12-1 -> 0.40882077 | E13: =+D13/D12-1 -> #DIV/0! | F13: =+D13/B13-1 -> -1 | P13: Oct | Q13: 108 | R13: =+Q13/Q12-1 -> -0.26027397 | T13: =+S13/S12-1 -> #DIV/0! | U13: =+S13/Q13-1 -> -1
A14: Nov | B14: 3540 | C14: =+B14/B13-1 -> -0.21403197 | E14: =+D14/D13-1 -> #DIV/0! | F14: =+D14/B14-1 -> -1 | P14: Nov | Q14: 232 | R14: =+Q14/Q13-1 -> 1.1481481 | T14: =+S14/S13-1 -> #DIV/0! | U14: =+S14/Q14-1 -> -1
A15: Dic | B15: 3710 | C15: =+B15/B14-1 -> 0.048022599 | E15: =+D15/D14-1 -> #DIV/0! | F15: =+D15/B15-1 -> -1 | P15: Dic | Q15: 140 | R15: =+Q15/Q14-1 -> -0.39655172 | T15: =+S15/S14-1 -> #DIV/0! | U15: =+S15/Q15-1 -> -1
A16: Total | B16: =SUM(B4:B9) -> 16850 | C16: - | D16: =SUM(D4:D15) -> 24047 | E16: - | F16: =+D16/B16-1 -> 0.42712166 | P16: Total | Q16: =SUM(Q4:Q6) -> 829 | S16: =SUM(S4:S15) -> 536 | U16: =+S16/Q16-1 -> -0.35343788
A17: Fuente: CADAM
A34: Cuadro 4B: Importación de vehículos variación mensual, 2023-2024 | G34: Proyección | P34: Cuadro 4C: Importación de vehículos y camiones variación mensual, 2018-2019 | V34: Proyección
A35: MESES | B35: 2023 | C35: var. % 2023 | D35: 2024 | E35: var. % 2024 | F35: Var. % 2024/2023 | P35: MESES | Q35: 2018 | R35: var. % 2018 | S35: 2019 | T35: var. % 2019 | U35: Var. % 2019/2018
A37: Ene | B37: 1939 | C37: - | D37: 2037 | E37: - | F37: =+D37/B37-1 -> 0.050541516 | P37: Ene | Q37: =+B37+'16'!B44 -> 2043 | R37: - | S37: =+D37+'16'!D44 -> 2185 | T37: - | U37: =+S37/Q37-1 -> 0.069505629
A38: Feb | B38: 2451 | C38: =+B38/B37-1 -> 0.26405364 | E38: =+D38/D37-1 -> -1 | F38: =+D38/B38-1 -> -1 | P38: Feb | Q38: =+B38+'16'!B45 -> 2597 | R38: =+Q38/Q37-1 -> 0.27116985 | S38: =+D38+'16'!D45 -> 0 | T38: =+S38/S37-1 -> -1 | U38: =+S38/Q38-1 -> -1
A39: Mar | B39: 2752 | C39: =+B39/B38-1 -> 0.12280702 | E39: =+D39/D38-1 -> #DIV/0! | F39: =+D39/B39-1 -> -1 | P39: Mar | Q39: =+B39+'16'!B46 -> 2879 | R39: =+Q39/Q38-1 -> 0.10858683 | S39: =+D39+'16'!D46 -> 0 | T39: =+S39/S38-1 -> #DIV/0! | U39: =+S39/Q39-1 -> -1
A40: Abr | B40: 2336 | C40: =+B40/B39-1 -> -0.15116279 | E40: =+D40/D39-1 -> #DIV/0! | F40: =+D40/B40-1 -> -1 | P40: Abr | Q40: =+B40+'16'!B47 -> 2566 | R40: =+Q40/Q39-1 -> -0.1087183 | S40: =+D40+'16'!D47 -> 0 | T40: =+S40/S39-1 -> #DIV/0! | U40: =+S40/Q40-1 -> -1
A41: May | B41: 2590 | C41: =+B41/B40-1 -> 0.10873288 | E41: =+D41/D40-1 -> #DIV/0! | F41: =+D41/B41-1 -> -1 | P41: May | Q41: =+B41+'16'!B48 -> 2662 | R41: =+Q41/Q40-1 -> 0.037412315 | S41: =+D41+'16'!D48 -> 0 | T41: =+S41/S40-1 -> #DIV/0! | U41: =+S41/Q41-1 -> -1
A42: Jun | B42: 2496 | C42: =+B42/B41-1 -> -0.036293436 | E42: =+D42/D41-1 -> #DIV/0! | F42: =+D42/B42-1 -> -1 | P42: Jun | Q42: =+B42+'16'!B49 -> 2624 | R42: =+Q42/Q41-1 -> -0.014274981 | S42: =+D42+'16'!D49 -> 0 | T42: =+S42/S41-1 -> #DIV/0! | U42: =+S42/Q42-1 -> -1
A43: Jul | B43: 2619 | C43: =+B43/B42-1 -> 0.049278846 | E43: =+D43/D42-1 -> #DIV/0! | F43: =+D43/B43-1 -> -1 | P43: Jul | Q43: =+B43+'16'!B50 -> 2842 | R43: =+Q43/Q42-1 -> 0.083079268 | S43: =+D43+'16'!D50 -> 0 | T43: =+S43/S42-1 -> #DIV/0! | U43: =+S43/Q43-1 -> -1
A44: Ago | B44: 2707 | C44: =+B44/B43-1 -> 0.033600611 | E44: =+D44/D43-1 -> #DIV/0! | F44: =+D44/B44-1 -> -1 | P44: Ago | Q44: =+B44+'16'!B51 -> 2836 | R44: =+Q44/Q43-1 -> -0.0021111893 | S44: =+D44+'16'!D51 -> 0 | T44: =+S44/S43-1 -> #DIV/0! | U44: =+S44/Q44-1 -> -1
A45: Sep | B45: 2373 | C45: =+B45/B44-1 -> -0.12338382 | E45: =+D45/D44-1 -> #DIV/0! | F45: =+D45/B45-1 -> -1 | P45: Sep | Q45: =+B45+'16'!B52 -> 2522 | R45: =+Q45/Q44-1 -> -0.11071932 | S45: =+D45+'16'!D52 -> 0 | T45: =+S45/S44-1 -> #DIV/0! | U45: =+S45/Q45-1 -> -1
A46: Oct | B46: 2553 | C46: =+B46/B45-1 -> 0.07585335 | E46: =+D46/D45-1 -> #DIV/0! | F46: =+D46/B46-1 -> -1 | P46: Oct | Q46: =+B46+'16'!B53 -> 2685 | R46: =+Q46/Q45-1 -> 0.064631245 | S46: =+D46+'16'!D53 -> 0 | T46: =+S46/S45-1 -> #DIV/0! | U46: =+S46/Q46-1 -> -1
A47: Nov | B47: 2346 | C47: =+B47/B46-1 -> -0.081081081 | E47: =+D47/D46-1 -> #DIV/0! | F47: =+D47/B47-1 -> -1 | P47: Nov | Q47: =+B47+'16'!B54 -> 2613 | R47: =+Q47/Q46-1 -> -0.026815642 | S47: =+D47+'16'!D54 -> 0 | T47: =+S47/S46-1 -> #DIV/0! | U47: =+S47/Q47-1 -> -1
A48: Dic | B48: 2558 | C48: =+B48/B47-1 -> 0.090366581 | E48: =+D48/D47-1 -> #DIV/0! | F48: =+D48/B48-1 -> -1 | P48: Dic | Q48: =+B48+'16'!B55 -> 2672 | R48: =+Q48/Q47-1 -> 0.022579411 | S48: =+D48+'16'!D55 -> 0 | T48: =+S48/S47-1 -> #DIV/0! | U48: =+S48/Q48-1 -> -1
A49: Total | B49: =SUM(B37:B48) -> 29720 | C49: - | D49: =SUM(D37:D48) -> 2037 | E49: =+D49/B49-1 -> -0.9314603 | F49: =+D49/B49-1 -> -0.9314603 | P49: Total | Q49: =SUM(Q37:Q48) -> 31541 | R49: - | S49: =SUM(S37:S48) -> 2185 | T49: =+S49/Q49-1 -> -0.93072509 | U49: =+S49/Q49-1 -> -0.93072509
P53: 2020 | S53: 32000 | T53: =+S53/S49-1 -> 13.645309

Sheet 5
A1: Cuadro 5: Importación de vehículos por marca y mes, 2026
A2: MARCA | B2: Ene | C2: Feb | D2: Mar | E2: Abr | F2: May | G2: Jun | H2: Jul | I2: Ago | J2: Sep | K2: Oct | L2: Nov | M2: Dic | N2: Total | O2: % | Q2: MARCA | R2: Unidades | S2: % | T2: % Acum | V2: Grafico 5: Ranking de principales marcas importadas, 2026
A3: AION | B3: 4 | C3: 6 | D3: 0 | E3: 9 | F3: 0 | G3: 0 | N3: =SUM(B3:M3) -> 19 | O3: =+N3/$N$79 -> 0.00079011935 | Q3: TOYOTA | R3: 3237 | S3: =+R3/$R$79 -> 0.13461139 | T3: =+S3 -> 0.13461139
A4: ARCFOX | B4: 0 | C4: 0 | D4: 0 | E4: 0 | F4: 2 | G4: 0 | N4: =SUM(B4:M4) -> 2 | O4: =+N4/$N$79 -> 8.3170458e-05 | Q4: KIA | R4: 2394 | S4: =+R4/$R$79 -> 0.099555038 | T4: =+S4+T3 -> 0.23416642
A5: AUDI | B5: 21 | C5: 20 | D5: 19 | E5: 14 | F5: 13 | G5: 11 | N5: =SUM(B5:M5) -> 98 | O5: =+N5/$N$79 -> 0.0040753524 | Q5: HYUNDAI | R5: 2248 | S5: =+R5/$R$79 -> 0.093483595 | T5: =+S5+T4 -> 0.32765002
A6: AVATR | B6: 0 | C6: 0 | D6: 10 | E6: 7 | F6: 0 | G6: 4 | N6: =SUM(B6:M6) -> 21 | O6: =+N6/$N$79 -> 0.00087328981 | Q6: FIAT | R6: 2213 | S6: =+R6/$R$79 -> 0.092028112 | T6: =+S6+T5 -> 0.41967813
A7: BAIC | B7: 6 | C7: 24 | D7: 16 | E7: 0 | F7: 14 | G7: 14 | N7: =SUM(B7:M7) -> 74 | O7: =+N7/$N$79 -> 0.0030773069 | Q7: CHEVROLET | R7: 2144 | S7: =+R7/$R$79 -> 0.089158731 | T7: =+S7+T6 -> 0.50883686
A8: BAOJUN | B8: 0 | C8: 0 | D8: 0 | E8: 0 | F8: 3 | G8: 0 | N8: =SUM(B8:M8) -> 3 | O8: =+N8/$N$79 -> 0.00012475569 | Q8: VOLKSWAGEN | R8: 1461 | S8: =+R8/$R$79 -> 0.060756019 | T8: =+S8+T7 -> 0.56959288
A9: BMW | B9: 20 | C9: 37 | D9: 39 | E9: 50 | F9: 14 | G9: 33 | N9: =SUM(B9:M9) -> 193 | O9: =+N9/$N$79 -> 0.0080259492 | Q9: SUZUKI | R9: 1164 | S9: =+R9/$R$79 -> 0.048405206 | T9: =+S9+T8 -> 0.61799809
A10: BYD | B10: 11 | C10: 18 | D10: 124 | E10: 22 | F10: 100 | G10: 6 | N10: =SUM(B10:M10) -> 281 | O10: =+N10/$N$79 -> 0.011685449 | Q10: NISSAN | R10: 965 | S10: =+R10/$R$79 -> 0.040129746 | T10: =+S10+T9 -> 0.65812783
A11: CADILLAC | B11: 0 | C11: 0 | D11: 0 | E11: 1 | F11: 0 | G11: 0 | N11: =SUM(B11:M11) -> 1 | O11: =+N11/$N$79 -> 4.1585229e-05 | Q11: CHERY | R11: 882 | S11: =+R11/$R$79 -> 0.036678172 | T11: =+S11+T10 -> 0.694806
A12: CHANGAN | B12: 15 | C12: 71 | D12: 57 | E12: 39 | F12: 36 | G12: 9 | N12: =SUM(B12:M12) -> 227 | O12: =+N12/$N$79 -> 0.009439847 | Q12: GEELY | R12: 832 | S12: =+R12/$R$79 -> 0.03459891 | T12: =+S12+T11 -> 0.72940492
A13: CHERY | B13: 60 | C13: 238 | D13: 101 | E13: 319 | F13: 140 | G13: 24 | N13: =SUM(B13:M13) -> 882 | O13: =+N13/$N$79 -> 0.036678172 | Q13: JETOUR | R13: 583 | S13: =+R13/$R$79 -> 0.024244188 | T13: =+S13+T12 -> 0.7536491
A14: CHEVROLET | B14: 219 | C14: 221 | D14: 551 | E14: 236 | F14: 449 | G14: 468 | N14: =SUM(B14:M14) -> 2144 | O14: =+N14/$N$79 -> 0.089158731 | Q14: MG | R14: 558 | S14: =+R14/$R$79 -> 0.023204558 | T14: =+S14+T13 -> 0.77685366
A15: CITROEN | B15: 14 | C15: 9 | D15: 10 | E15: 16 | F15: 42 | G15: 0 | N15: =SUM(B15:M15) -> 91 | O15: =+N15/$N$79 -> 0.0037842558 | Q15: MAZDA | R15: 440 | S15: =+R15/$R$79 -> 0.018297501 | T15: =+S15+T14 -> 0.79515116
... A78: YUFENG | B78: 0 | C78: 0 | D78: 0 | E78: 0 | F78: 0 | G78: 2 | N78: =SUM(B78:M78) -> 2 | O78: =+N78/$N$79 -> 8.3170458e-05 | Q78: VOYAH DREAMER | R78: 1 | S78: =+R78/$R$79 -> 4.1585229e-05 | T78: =+S78+T77 -> 1
A79: Total | B79: =SUM(B3:B78) -> 3205 | C79: =SUM(C3:C78) -> 3319 | D79: =SUM(D3:D78) -> 4038 | E79: =SUM(E3:E78) -> 4624 | F79: =SUM(F3:F78) -> 4341 | G79: =SUM(G3:G78) -> 4520 | H79: =SUM(H3:H78) -> 0 | I79: =SUM(I3:I78) -> 0 | ... O79: =SUM(O3:O78) -> 1 | Q79: Total | R79: =SUM(R3:R78) -> 24047 | S79: =SUM(S3:S78) -> 1
A80: Fuente: CADAM | B80: 3205 | C80: 3319 | D80: 4038 | E80: 4624 | F80: 4341 | G80: 4520
A84: Cuadro 5A: Importación de vehículos por marca y mes | O84: Grafico 5A: Variación de importacipon de vehículos, por marca, 2026
A85: MARCAS | B85: 45809 | C85: 46174 | D85: Var % 2026/2025 | E85: Part. en total | F85: Var. Unid.
A86: TOYOTA | B86: 2151 | C86: 3237 | D86: =+C86/B86-1 -> 0.50488145 | E86: =+C86/$C$171 -> 0.13461139 | F86: =+C86-B86 -> 1086
A87: KIA | B87: 2295 | C87: 2394 | D87: =+C87/B87-1 -> 0.043137255 | E87: =+C87/$C$171 -> 0.099555038 | F87: =+C87-B87 -> 99
A88: HYUNDAI | B88: 1969 | C88: 2248 | D88: =+C88/B88-1 -> 0.14169629 | E88: =+C88/$C$171 -> 0.093483595 | F88: =+C88-B88 -> 279
A89: FIAT | B89: 1236 | C89: 2213 | D89: =+C89/B89-1 -> 0.79045307 | E89: =+C89/$C$171 -> 0.092028112 | F89: =+C89-B89 -> 977
A90: CHEVROLET | B90: 1242 | C90: 2144 | D90: =+C90/B90-1 -> 0.72624799 | E90: =+C90/$C$171 -> 0.089158731 | F90: =+C90-B90 -> 902
A91: VOLKSWAGEN | B91: 1166 | C91: 1461 | D91: =+C91/B91-1 -> 0.25300172 | E91: =+C91/$C$171 -> 0.060756019 | F91: =+C91-B91 -> 295
A92: SUZUKI | B92: 857 | C92: 1164 | D92: =+C92/B92-1 -> 0.35822637 | E92: =+C92/$C$171 -> 0.048405206 | F92: =+C92-B92 -> 307
A93: NISSAN | B93: 890 | C93: 965 | D93: =+C93/B93-1 -> 0.084269663 | E93: =+C93/$C$171 -> 0.040129746 | F93: =+C93-B93 -> 75
A94: CHERY | B94: 274 | C94: 882 | D94: =+C94/B94-1 -> 2.2189781 | E94: =+C94/$C$171 -> 0.036678172 | F94: =+C94-B94 -> 608
A95: GEELY | B95: 553 | C95: 832 | D95: =+C95/B95-1 -> 0.5045208 | E95: =+C95/$C$171 -> 0.03459891 | F95: =+C95-B95 -> 279
A96: JETOUR | B96: 281 | C96: 583 | D96: =+C96/B96-1 -> 1.0747331 | E96: =+C96/$C$171 -> 0.024244188 | F96: =+C96-B96 -> 302
A97: MG | B97: 131 | C97: 558 | D97: =+C97/B97-1 -> 3.259542 | E97: =+C97/$C$171 -> 0.023204558 | F97: =+C97-B97 -> 427
... A170: ZEEKR | B170: 9 | C170: 0 | D170: =+C170/B170-1 -> -1 | E170: =+C170/$C$171 -> 0 | F170: =+C170-B170 -> -9
A171: Total | B171: =SUM(B86:B170) -> 16850 | C171: =SUM(C86:C170) -> 24047 | D171: =+C171/B171-1 -> 0.42712166 | E171: =SUM(E86:E170) -> 1

Sheet 6
A1: Cuadro 6: Importación de vehículos por país de procedencia y mes, 2026
A2: Procedencia | B2: Ene | C2: Feb | D2: Mar | E2: Abr | F2: May | G2: Jun | H2: Jul | I2: Ago | J2: Set | K2: Oct | L2: Nov | M2: Dic | N2: Total | O2: % | Q2: Procedencia | R2: % | S2: % Acum | T2: Acum %
A3: ALEMANIA | B3: 41 | C3: 43 | D3: 59 | E3: 35 | F3: 23 | G3: 43 | N3: =SUM(B3:M3) -> 244 | O3: =+N3/$N$25 -> 0.010146796 | Q3: BRASIL | R3: 0.36179149 | S3: =+R3 -> 0.36179149 | T3: =+R3 -> 0.36179149
A4: ARGENTINA | B4: 110 | C4: 228 | D4: 273 | E4: 430 | F4: 465 | G4: 208 | N4: =SUM(B4:M4) -> 1714 | O4: =+N4/$N$25 -> 0.071277082 | Q4: CHINA | R4: 0.26531376 | S4: =+R4+S3 -> 0.62710525 | T4: =+R4+T3 -> 0.62710525
A5: AUSTRIA | B5: 1 | C5: 1 | D5: 0 | E5: 1 | F5: 1 | G5: 3 | N5: =SUM(B5:M5) -> 7 | O5: =+N5/$N$25 -> 0.0002910966 | Q5: ARGENTINA | R5: 0.071277082 | T5: =+R5+T4 -> 0.69838233
A6: BELGICA | B6: 0 | C6: 0 | D6: 2 | E6: 2 | F6: 0 | G6: 1 | N6: =SUM(B6:M6) -> 5 | O6: =+N6/$N$25 -> 0.00020792614 | Q6: INDIA | R6: 0.071069156 | T6: =+R6+T5 -> 0.76945149
A7: BRASIL | B7: 958 | C7: 1038 | D7: 1583 | E7: 1736 | F7: 1570 | G7: 1815 | N7: =SUM(B7:M7) -> 8700 | O7: =+N7/$N$25 -> 0.36179149 | Q7: COREA DEL SUR | R7: 0.059134196 | T7: =+R7+T6 -> 0.82858569
A8: CANADA | B8: 0 | C8: 2 | D8: 1 | E8: 0 | F8: 2 | G8: 1 | N8: =SUM(B8:M8) -> 6 | O8: =+N8/$N$25 -> 0.00024951137 | Q8: JAPON | R8: 0.042250593 | T8: =+R8+T7 -> 0.87083628
A9: CHINA | B9: 906 | C9: 965 | D9: 1211 | E9: 1356 | F9: 914 | G9: 1028 | N9: =SUM(B9:M9) -> 6380 | O9: =+N9/$N$25 -> 0.26531376 | Q9: INDONESIA | R9: 0.037676217 | S9: =+R9+S4 -> 0.66478147 | T9: =+R9+T8 -> 0.9085125
A10: COREA DEL SUR | B10: 240 | C10: 241 | D10: 271 | E10: 176 | F10: 265 | G10: 229 | N10: =SUM(B10:M10) -> 1422 | O10: =+N10/$N$25 -> 0.059134196 | Q10: TAILANDIA | R10: 0.029192831 | T10: =+R10+T9 -> 0.93770533
A11: EMIRATOS ARABES UNIDOS | B11: 2 | C11: 2 | D11: 0 | E11: 0 | F11: 0 | G11: 0 | N11: =SUM(B11:M11) -> 4 | O11: =+N11/$N$25 -> 0.00016634092 | Q11: MEXICO | R11: 0.02545016 | S11: =+R11+S9 -> 0.69023163 | T11: =+R11+T10 -> 0.96315549
A12: ESLOVAQUIA | B12: 6 | C12: 7 | D12: 9 | E12: 16 | F12: 3 | G12: 6 | N12: =SUM(B12:M12) -> 47 | O12: =+N12/$N$25 -> 0.0019545058 | Q12: EE.UU. | R12: 0.014305319 | T12: =+R12+T11 -> 0.97746081
A13: EE.UU. | B13: 65 | C13: 70 | D13: 60 | E13: 56 | F13: 40 | G13: 53 | N13: =SUM(B13:M13) -> 344 | O13: =+N13/$N$25 -> 0.014305319 | Q13: ALEMANIA | R13: 0.010146796 | S13: =+R13+S11 -> 0.70037843 | T13: =+R13+T12 -> 0.9876076
A14: FRANCIA | B14: 4 | C14: 3 | D14: 16 | E14: 3 | F14: 1 | G14: 0 | N14: =SUM(B14:M14) -> 27 | O14: =+N14/$N$25 -> 0.0011228012 | Q14: REINO UNIDO | R14: 0.0046159604 | S14: =+R14+S13 -> 0.70499439 | T14: =+R14+T13 -> 0.99222356
A15: HUNGRIA | B15: 6 | C15: 1 | D15: 1 | E15: 1 | F15: 0 | G15: 2 | N15: =SUM(B15:M15) -> 11 | O15: =+N15/$N$25 -> 0.00045743752 | Q15: SUECIA | R15: 0.0027446251 | S15: =+R15+S14 -> 0.70773901 | T15: =+R15+T14 -> 0.99496819
A16: INDIA | B16: 348 | C16: 163 | D16: 45 | E16: 281 | F16: 360 | G16: 512 | N16: =SUM(B16:M16) -> 1709 | O16: =+N16/$N$25 -> 0.071069156 | Q16: ESLOVAQUIA | R16: 0.0019545058 | S16: =+R16+S15 -> 0.70969352 | T16: =+R16+T15 -> 0.99692269
A17: INDONESIA | B17: 146 | C17: 141 | D17: 168 | E17: 58 | F17: 209 | G17: 184 | N17: =SUM(B17:M17) -> 906 | O17: =+N17/$N$25 -> 0.037676217 | Q17: FRANCIA | R17: 0.0011228012 | T17: =+R17+T16 -> 0.99804549
A18: ITALIA | B18: 0 | C18: 0 | D18: 0 | E18: 0 | F18: 1 | G18: 1 | N18: =SUM(B18:M18) -> 2 | O18: =+N18/$N$25 -> 8.3170458e-05 | Q18: SUDAFRICA | R18: 0.00049902275 | S18: =+R18+S16 -> 0.71019254 | T18: =+R18+T17 -> 0.99854452
A19: JAPON | B19: 175 | C19: 122 | D19: 99 | E19: 170 | F19: 289 | G19: 161 | N19: =SUM(B19:M19) -> 1016 | O19: =+N19/$N$25 -> 0.042250593 | Q19: HUNGRIA | R19: 0.00045743752 | S19: =+R19+S18 -> 0.71064998 | T19: =+R19+T18 -> 0.99900195
A20: MEXICO | B20: 32 | C20: 194 | D20: 116 | E20: 108 | F20: 80 | G20: 82 | N20: =SUM(B20:M20) -> 612 | O20: =+N20/$N$25 -> 0.02545016 | Q20: AUSTRIA | R20: 0.0002910966 | T20: =+R20+T19 -> 0.99929305
A21: REINO UNIDO | B21: 38 | C21: 1 | D21: 42 | E21: 5 | F21: 9 | G21: 16 | N21: =SUM(B21:M21) -> 111 | O21: =+N21/$N$25 -> 0.0046159604 | Q21: CANADA | R21: 0.00024951137 | S21: =+R21+S19 -> 0.71089949 | T21: =+R21+T20 -> 0.99954256
A22: SUDAFRICA | B22: 1 | C22: 1 | D22: 2 | E22: 7 | F22: 0 | G22: 1 | N22: =SUM(B22:M22) -> 12 | O22: =+N22/$N$25 -> 0.00049902275 | Q22: BELGICA | R22: 0.00020792614 | T22: =+R22+T21 -> 0.99975049
A23: SUECIA | B23: 12 | C23: 26 | D23: 11 | E23: 10 | F23: 0 | G23: 7 | N23: =SUM(B23:M23) -> 66 | O23: =+N23/$N$25 -> 0.0027446251 | Q23: EMIRATOS ARABES UNIDOS | R23: 0.00016634092 | S23: =+R23+S21 -> 0.71106583 | T23: =+R23+T22 -> 0.99991683
A24: TAILANDIA | B24: 114 | C24: 70 | D24: 69 | E24: 173 | F24: 109 | G24: 167 | N24: =SUM(B24:M24) -> 702 | O24: =+N24/$N$25 -> 0.029192831 | Q24: ITALIA | R24: 8.3170458e-05 | T24: =+R24+T23 -> 1
A25: Total | B25: =SUM(B3:B24) -> 3205 | C25: =SUM(C3:C24) -> 3319 | D25: =SUM(D3:D24) -> 4038 | E25: =SUM(E3:E24) -> 4624 | F25: =SUM(F3:F24) -> 4341 | G25: =SUM(G3:G24) -> 4520 | H25: =SUM(H3:H24) -> 0 | I25: =SUM(I3:I24) -> 0 | ... O25: =SUM(O3:O24) -> 1 | Q25: Total | R25: =SUM(R3:R24) -> 1
A26: Fuente: CADAM

Sheet 7
A1: Cuadro 7: Importación de vehículos por empresa y marca, 2024 | R1: *No se disponen datos del importador
A2: Empresa | B2: Marcas | C2: Ene | D2: Feb | E2: Mar | F2: Abr | G2: May | H2: Jun | I2: Jul | J2: Ago | K2: Sep | L2: Oct | M2: Nov | N2: Dic | O2: Total | P2: 0 Km, % del total | S2: Ranking
S3: Empresa | T3: Marca | V3: %
A4: Prestigio Automotores S.A. | B4: AUDI | O4: =SUM(C4:N4) -> 0 | P4: =+O4/$O$105 -> #DIV/0!
A5: Diesa S.A. | B5: AUDI | O5: =SUM(C5:N5) -> 0 | P5: =+O5/$O$105 -> #DIV/0!
A6: Imp. Casual | B6: AUDI | O6: =SUM(C6:N6) -> 0 | P6: =+O6/$O$105 -> #DIV/0!
A7: AMERICAN AUTOMOTORES S A | B7: AIGLE | O7: =SUM(C7:N7) -> 0 | P7: =+O7/$O$105 -> #DIV/0!
A8: Imp. Casual | B8: BAOJUN | O8: =SUM(C8:N8) -> 0 | P8: =+O8/$O$105 -> #DIV/0!
A9: CATHAY S.A. | B9: BAIC | O9: =SUM(C9:N9) -> 0 | P9: =+O9/$O$105 -> #DIV/0!
A10: Imp. Casual | B10: BEIJING | O10: =SUM(C10:N10) -> 0 | P10: =+O10/$O$105 -> #DIV/0!
A11: MERCOTEC S.A.E | B11: BESTUNE | O11: =SUM(C11:N11) -> 0 | P11: =+O11/$O$105 -> #DIV/0!
A12: Perfecta Automotores S.A. | B12: BMW | O12: =SUM(C12:N12) -> 0 | P12: =+O12/$O$105 -> #DIV/0!
A13: Chacomer Automotores S.A. | B13: BRILLIANCE | O13: =SUM(C13:N13) -> 0 | P13: =+O13/$O$105 -> #DIV/0!
A14: Diesa S.A. | B14: BYD | O14: =SUM(C14:N14) -> 0 | P14: =+O14/$O$105 -> #DIV/0!
A15: Imp. casual | B15: BYD | O15: =SUM(C15:N15) -> 0 | P15: =+O15/$O$105 -> #DIV/0!
... A41: Vicar S.A. | B41: HONDA | O41: =SUM(C41:N41) -> 0 | P41: =+O41/$O$105 -> #DIV/0!
A42: Automotor S.A. | B42: HYUNDAI | O42: =SUM(C42:N42) -> 0 | P42: =+O42/$O$105 -> #DIV/0! | Q42: =425-13 -> 412
A43: Automotor S.A. | B43: ISUZU | O43: =SUM(C43:N43) -> 0 | P43: =+O43/$O$105 -> #DIV/0!
A44: Rodomaq | B44: IVECO | O44: =SUM(C44:N44) -> 0 | P44: =+O44/$O$105 -> #DIV/0!
A45: SANTA ROSA PARAGUAY S.A. | B45: JAC | O45: =SUM(C45:N45) -> 0 | P45: =+O45/$O$105 -> #DIV/0!
A46: ACE SAC | B46: Jaguar | O46: =SUM(C46:N46) -> 0 | P46: =+O46/$O$105 -> #DIV/0!
A47: Garden Automotores S.A. | B47: JEEP | O47: =SUM(C47:N47) -> 0 | P47: =+O47/$O$105 -> #DIV/0!
A48: SANTA ROSA PARAGUAY S.A. | B48: JETOUR | O48: =SUM(C48:N48) -> 0 | P48: =+O48/$O$105 -> #DIV/0!
A49: TONINA S.A. | B49: JIANGSU | O49: =SUM(C49:N49) -> 0 | P49: =+O49/$O$105 -> #DIV/0!
A50: Chacomer Automotores S.A. | B50: Jim | O50: =SUM(C50:N50) -> 0 | P50: =+O50/$O$105 -> #DIV/0!
A51: Chacomer Automotores S.A. | B51: JMC | O51: =SUM(C51:N51) -> 0 | P51: =+O51/$O$105 -> #DIV/0!
A52: GOLDEN ARROW S.A. | B52: KAIYI | O52: =SUM(C52:N52) -> 0 | P52: =+O52/$O$105 -> #DIV/0!
A53: Imp. Casual | B53: KAIYUN | O53: =SUM(C53:N53) -> 0 | P53: =+O53/$O$105 -> #DIV/0!
A54: SANTA ROSA PARAGUAY S.A. | B54: KARRY | O54: =SUM(C54:N54) -> 0 | P54: =+O54/$O$105 -> #DIV/0!
... A88: Automotor S.A. | B88: RIDDARA | O88: =SUM(C88:N88) -> 0 | P88: =+O88/$O$105 -> #DIV/0!
A89: DOSZETAS SA | B89: SKODA | O89: =SUM(C89:N89) -> 0 | P89: =+O89/$O$105 -> #DIV/0! | S89: Total | U89: =SUM(U4:U88) -> 0 | V89: =SUM(V4:V88) -> 0
A90: Automotor S.A. | B90: SMART | O90: =SUM(C90:N90) -> 0 | P90: =+O90/$O$105 -> #DIV/0!
A91: CENSU S.A. | B91: SSANGYONG | O91: =SUM(C91:N91) -> 0 | P91: =+O91/$O$105 -> #DIV/0!
A92: Tokio Motors | B92: SUBARU | O92: =SUM(C92:N92) -> 0 | P92: =+O92/$O$105 -> #DIV/0!
A93: AMERICAN AUTOMOTORES S A | B93: SUNYU | O93: =SUM(C93:N93) -> 0 | P93: =+O93/$O$105 -> #DIV/0!
A94: Chacomer Automotores S.A. | B94: SUZUKI | O94: =SUM(C94:N94) -> 0 | P94: =+O94/$O$105 -> #DIV/0!
A95: AUTO LOGIC S.A. | B95: Tata | O95: =SUM(C95:N95) -> 0 | P95: =+O95/$O$105 -> #DIV/0!
A96: IVONNE MARGOTT BOSCH | B96: Tesla | O96: =SUM(C96:N96) -> 0 | P96: =+O96/$O$105 -> #DIV/0!
A97: Imp. Casual | B97: Tesla | O97: =SUM(C97:N97) -> 0 | P97: =+O97/$O$105 -> #DIV/0!
A98: Toyotoshi S.A. | B98: TOYOTA | O98: =SUM(C98:N98) -> 0 | P98: =+O98/$O$105 -> #DIV/0!
A99: MEYER DE LEON KATIA SOFIA | B99: UAZ | O99: =SUM(C99:N99) -> 0 | P99: =+O99/$O$105 -> #DIV/0!
A100: Garden Automotores S.A. | B100: VOLVO | O100: =SUM(C100:N100) -> 0 | P100: =+O100/$O$105 -> #DIV/0!
A101: Diesa S.A. | B101: VW | O101: =SUM(C101:N101) -> 0 | P101: =+O101/$O$105 -> #DIV/0!
... A104: Imp. Casual | B104: XIAOMI | O104: =SUM(C104:N104) -> 0 | P104: =+O104/$O$105 -> #DIV/0!
A105: Total | C105: =SUM(C4:C104) -> 0 | D105: =SUM(D4:D104) -> 0 | E105: =SUM(E4:E104) -> 0 | F105: =SUM(F4:F104) -> 0 | G105: =SUM(G4:G104) -> 0 | H105: =SUM(H4:H104) -> 0 | I105: =SUM(I4:I104) -> 0 | J105: =SUM(J4:J104) -> 0 | ... P105: =SUM(P4:P104) -> #DIV/0!
A106: Fuente: CADAM
A111: Cuadro 5 A: Importación de automotores CADAM - NO CADAM, 2024
C112: Ene | D112: Feb | E112: Mar | F112: Abr | G112: May | H112: Jun | I112: Jul | J112: Ago | K112: Sep | L112: Oct | M112: Nov | N112: Dic | O112: Total | P112: %
A113: CADAM | C113: =+C5+C12+C14+C18+C19+C20+C21+C22+C24+C26+C27+C31+C34+C35+C41+C42+C47+C48+C56+C58+C61+C62+C67+C68+C72+C76+C78+C82+C85+C87+C92+C98+C101 -> 0 | D113: =++D4+D5+D12+D14+D19+D20+D21+D22+D24+D26+D30+D31+D35+D41+D42+D43+D47+D48+D50+D54+D56+D58+D61+D62+D67+D68+D70+D72+D76+D78+D82+D85+D86+D87+D92+D98+D101 -> 0 | E113: =+E4+E5+E11+E12+E14+E19+E20+E21+E22+E24+E30+E31+E34+E35+E41+E42+E48+E50+E56+E58+E61+E62+E66+E68+E70+E72+E76+E78+E82+E86+E87+E92+E98+E101 -> 0 | F113: =+F4+F5+F12+F18+F19+F20+F21+F22+F24+F26+F30+F31+F34+F41+F42+F43+F47+F48+F50+F56+F58+F59+F61+F62+F68+F70+F72+F76+F78+F82+F84+F85+F86+F87+F89+F92+F98+F101 -> 0 | G113: =+G4+G5+G12+G18+G19+G20+G21+G22+G24+G30+G31+G33+G34+G35+G39+G41+G42+G43+G44+G47+G48+G56+G58+G59+G61+G62+G66+G67+G72+G76+G78+G82+G85+G86+G87+G92+G98+G100+G101 -> 0 | H113: =+H4+H5+H12+H14+H18+H19+H20+H21+H22+H24+H30+H31+H33+H34+H35+H39+H41+H42+H43+H47+H48+H56+H58+H61+H62+H67+H68+H70+H76+H78+H82+H85+H87+H92+H95+H98+H101 -> 0 | I113: =+I4+I5+I12+I14+I18+I19+I20+I21+I22+I24+I30+I31+I39+I41+I42+I44+I47+I48+I55+I56+I58+I61+I62+I67+I68+I70+I76+I78+I82+I85+I87+I92+I98+I94+I101 -> 0 | J113: =+J4+J5+J12+J14+J18+J19+J20+J21+J22+J24+J26+J27+J30+J31+J33+J35+J41+J42+J43+J47+J48+J56+J58+J61+J62+J67+J68+J69+J70+J76+J78+J82+J85+J86+J87+J92+J94+J98+J101 -> 0 | K113: =+K4+K5+K12+K14+K18+K19+K20+K21+K22+K24+K26+K27+K30+K31+K33+K35+K41+K42+K43+K47+K48+K56+K58+K61+K62+K67+K68+K69+K70+K76+K78+K82+K85+K86+K87+K92+K94+K98+K101 -> 0 | L113: =+L4+L5+L12+L14+L18+L19+L20+L21+L22+L24+L26+L27+L30+L31+L33+L35+L41+L42+L43+L47+L48+L56+L58+L61+L62+L67+L68+L69+L70+L76+L78+L82+L85+L86+L87+L92+L94+L98+L101 -> 0 | M113: =+M4+M5+M11+M12+M14+M19+M20+M21+M22+M24+M26+M27+M30+M31+M34+M35+M38+M39+M41+M42+M43+M44+M45+M47+M48+M50+M51+M56+M58+M61+M62+M66+M67+M68+M69+M70+M72+M76+M78+M82+M86+M87+M92+M94+M98+M100+M101 -> 0 | N113: =+N4+N5+N12+N14+N19+N20+N21+N22+N24+N26+N30+N31+N33+N34+N35+N38+N41+N42+N43+N45+N47+N48+N56+N58+N61+N62+N67+N69+N76+N78+N82+N85+N86+N87+N88+N92+N94+N98+N100+N101 -> 0 | O113: =SUM(C113:N113) -> 0 | P113: =+O113/O115 -> #DIV/0!
A114: No CADAM | C114: =+C105-C113 -> 0 | D114: =+D105-D113 -> 0 | E114: =+E105-E113 -> 0 | F114: =+F105-F113 -> 0 | G114: =+G105-G113 -> 0 | H114: =+H105-H113 -> 0 | I114: =+I105-I113 -> 0 | J114: =+J105-J113 -> 0 | ... N114: =+N105-N113 -> 0 | O114: =SUM(C114:N114) -> 0 | P114: =+O114/O115 -> #DIV/0!
A115: Total | C115: =SUM(C113:C114) -> 0 | D115: =SUM(D113:D114) -> 0 | E115: =SUM(E113:E114) -> 0 | F115: =SUM(F113:F114) -> 0 | G115: =SUM(G113:G114) -> 0 | H115: =SUM(H113:H114) -> 0 | I115: =SUM(I113:I114) -> 0 | J115: =SUM(J113:J114) -> 0 | K115: =SUM(K113:K114) -> 0 | L115: =+L113+L114 -> 0 | M115: =+M113+M114 -> 0 | N115: =+N113+N114 -> 0 | O115: =SUM(O113:O114) -> 0 | P115: =SUM(P113:P114) -> #DIV/0!
A116: Fuente: CADAM
A128: Cuadro 5 B: Importación de vehiculos y camiones CADAM - NO CADAM, 2011-2020, en %
B129: 2013 | C129: 2014 | D129: 2015 | E129: 2016 | F129: 2017 | G129: 2018 | H129: 2019 | I129: 2020
A130: CADAM | B130: 0.65327763 | C130: 0.66988671 | D130: 0.62889398 | E130: 0.92598273 | F130: 0.96535028 | G130: 0.96906169 | H130: 0.96798438 | I130: 0.97738405
A131: No CADAM | B131: 0.34672237 | C131: 0.33011329 | D131: 0.37110602 | E131: 0.074017266 | F131: 0.034649715 | G131: 0.030938306 | H131: 0.032015617 | I131: 0.022615955
A132: Total | B132: =SUM(B130:B131) -> 1 | C132: =SUM(C130:C131) -> 1 | D132: =SUM(D130:D131) -> 1 | E132: =SUM(E130:E131) -> 1 | F132: =SUM(F130:F131) -> 1 | G132: =SUM(G130:G131) -> 1 | H132: =SUM(H130:H131) -> 1 | I132: =SUM(I130:I131) -> 1

Sheet 8
R1: Valor CIF US$ | T1: Valor CIF US$ | V1: Valor CIF US$ | X1: Valor CIF US$ | Z1: Valor CIF US$ | AB1: Valor CIF US$ | AD1: Valor CIF US$ | AF1: Valor CIF US$ | AH1: Valor CIF US$ | AJ1: Valor CIF US$ | AL1: Valor CIF US$ | AN1: Valor CIF US$ | AR1: Reemplazar acumulado por mes
A2: Cuadro 8: Importación de vehículos por modelo, por mes y valor CIF de importación, 2026 | R2: 46023 | T2: 46054 | V2: 46082 | X2: 46113 | Z2: 46143 | AB2: 46174 | AD2: 46204 | AF2: 46235 | AH2: 46266 | AJ2: 45931 | AL2: 45962 | AN2: 45992 | AQ2: Cuadro 8A: Ranking de Importación de automotores por modelo, 2026
A3: Marca | B3: Modelo | C3: Tipo | D3: Ene | E3: Feb | F3: Mar | G3: Abr | H3: May | I3: Jun | J3: Jul | K3: Ago | L3: Sep | M3: Oct | N3: Nov | O3: Dic | P3: Total | Q3: % | R3: Max | S3: Min | T3: Max | U3: Min | V3: Max | W3: Min | X3: Max | Y3: Min | Z3: Max | AA3: Min | AB3: Max | AC3: Min | AD3: Max | AE3: Min | AF3: Max | AG3: Min | AH3: Max | AI3: Min | AJ3: Max | AK3: Min | AL3: Max | AM3: Min | AN3: Max | AO3: Min | AQ3: Ranking | AR3: Marca | AS3: Modelo | AT3: Tipo | AU3: Junio | AV3: %
A4: AIMA | B4: A08 | C4: Auto mediano B | D4: 0 | E4: 0 | F4: 0 | G4: 0 | H4: 0 | I4: 0 | J4: 0 | K4: 0 | L4: 0 | M4: 0 | N4: 0 | O4: 0 | P4: =SUM(D4:O4) -> 0 | Q4: =+P4/$P$766 -> 0 | R4: - | S4: - | AQ4: Toyota Hilux | AR4: TOYOTA | AS4: Hilux | AT4: Pick up mediano | AU4: 1138 | AV4: =+AU4/$AU$391 -> 0.047323991
A5: AION | B5: AHC7000BEVL0L | C5: Auto mediano C | D5: 4 | E5: 0 | F5: 0 | G5: 0 | H5: 0 | I5: 0 | J5: 0 | K5: 0 | L5: 0 | M5: 0 | N5: 0 | O5: 0 | P5: =SUM(D5:O5) -> 4 | Q5: =+P5/$P$766 -> 0.00016634092 | R5: 10720 | S5: 10720 | AQ5: Fiat Strada | AR5: FIAT | AS5: Strada | AT5: Pick up pequeño | AU5: 1034 | AV5: =+AU5/$AU$391 -> 0.042999127
A6: AION | B6: HIPER HT | C6: SUV mediano C | D6: 0 | E6: 0 | F6: 0 | G6: 0 | H6: 0 | I6: 0 | J6: 0 | K6: 0 | L6: 0 | M6: 0 | N6: 0 | O6: 0 | P6: =SUM(D6:O6) -> 0 | Q6: =+P6/$P$766 -> 0 | R6: - | S6: - | AQ6: Chevrolet S10 | AR6: CHEVROLET | AS6: S10 | AT6: Pick up mediano | AU6: 794 | AV6: =+AU6/$AU$391 -> 0.033018672
A7: AION | B7: M8 | C7: Minibus | D7: 0 | E7: 0 | F7: 0 | G7: 0 | H7: 0 | I7: 0 | J7: 0 | K7: 0 | L7: 0 | M7: 0 | N7: 0 | O7: 0 | P7: =SUM(D7:O7) -> 0 | Q7: =+P7/$P$766 -> 0 | R7: - | S7: - | AQ7: Hyundai Creta | AR7: HYUNDAI | AS7: Creta | AT7: SUV mediano B | AU7: 688 | AV7: =+AU7/$AU$391 -> 0.028610638
A8: AION | B8: RT | C8: Auto mediano C | D8: 0 | E8: 0 | F8: 0 | G8: 0 | H8: 0 | I8: 0 | J8: 0 | K8: 0 | L8: 0 | M8: 0 | N8: 0 | O8: 0 | P8: =SUM(D8:O8) -> 0 | Q8: =+P8/$P$766 -> 0 | R8: - | S8: - | AQ8: Kia Soluto | AR8: KIA | AS8: Soluto | AT8: auto mediano B | AU8: 648 | AV8: =+AU8/$AU$391 -> 0.026947228
A9: AION | B9: YPLUS | C9: SUV mediano C | D9: 0 | E9: 6 | F9: 0 | G9: 9 | H9: 0 | I9: 0 | J9: 0 | K9: 0 | L9: 0 | M9: 0 | N9: 0 | O9: 0 | P9: =SUM(D9:O9) -> 15 | Q9: =+P9/$P$766 -> 0.00062377843 | R9: - | S9: - | AQ9: Kia Sonet | AR9: KIA | AS9: Sonet | AT9: SUV Mediano B | AU9: 528 | AV9: =+AU9/$AU$391 -> 0.021957001
A10: ARCFOX | B10: S5 | C10: Auto grande D | D10: 0 | E10: 0 | F10: 0 | G10: 0 | H10: 1 | I10: 0 | J10: 0 | K10: 0 | L10: 0 | M10: 0 | N10: 0 | O10: 0 | P10: =SUM(D10:O10) -> 1 | Q10: =+P10/$P$766 -> 4.1585229e-05 | AQ10: Kia Sportage | AR10: KIA | AS10: Sportage | AT10: SUV mediano C | AU10: 508 | AV10: =+AU10/$AU$391 -> 0.021125296
A11: ARCFOX | B11: T5 | C11: SUV mediano B | D11: 0 | E11: 0 | F11: 0 | G11: 0 | H11: 1 | I11: 0 | J11: 0 | K11: 0 | L11: 0 | M11: 0 | N11: 0 | O11: 0 | P11: =SUM(D11:O11) -> 1 | Q11: =+P11/$P$766 -> 4.1585229e-05 | AQ11: Hyundai HB20 | AR11: HYUNDAI | AS11: HB20 | AT11: auto mediano B | AU11: 500 | AV11: =+AU11/$AU$391 -> 0.020792614
A12: AUDI | B12: A3 | C12: Auto mediano C | D12: 0 | E12: 0 | F12: 0 | G12: 1 | H12: 0 | I12: 0 | J12: 0 | K12: 0 | L12: 0 | M12: 0 | N12: 0 | O12: 0 | P12: =SUM(D12:O12) -> 1 | Q12: =+P12/$P$766 -> 4.1585229e-05 | R12: - | S12: - | AQ12: Suzuki Fronx | AR12: SUZUKI | AS12: Fronx | AT12: SUV mediano B | AU12: 500 | AV12: =+AU12/$AU$391 -> 0.020792614
A13: AUDI | B13: A4 | C13: Auto mediano C | D13: 1 | E13: 0 | F13: 0 | G13: 0 | H13: 0 | I13: 0 | J13: 0 | K13: 0 | L13: 0 | M13: 0 | N13: 0 | O13: 0 | P13: =SUM(D13:O13) -> 1 | Q13: =+P13/$P$766 -> 4.1585229e-05 | R13: - | S13: - | AQ13: Fiat Pulse | AR13: FIAT | AS13: Pulse | AT13: SUV mediano B | AU13: 488 | AV13: =+AU13/$AU$391 -> 0.020293592
A14: AUDI | B14: A5 | C14: Auto mediano C | D14: 0 | E14: 0 | F14: 1 | G14: 0 | H14: 0 | I14: 0 | J14: 0 | K14: 0 | L14: 0 | M14: 0 | N14: 0 | O14: 0 | P14: =SUM(D14:O14) -> 1 | Q14: =+P14/$P$766 -> 4.1585229e-05 | R14: - | S14: - | AQ14: Toyota Corolla Cross | AR14: TOYOTA | AS14: Corolla Cross | AT14: SUV mediano C | AU14: 441 | AV14: =+AU14/$AU$391 -> 0.018339086
A15: AUDI | B15: A6 | C15: Auto grande E | D15: 0 | E15: 0 | F15: 0 | G15: 0 | H15: 0 | I15: 0 | J15: 0 | K15: 0 | L15: 0 | M15: 0 | N15: 0 | O15: 0 | P15: =SUM(D15:O15) -> 0 | Q15: =+P15/$P$766 -> 0 | R15: - | S15: - | AQ15: MG ZS | AR15: MG | AS15: ZS | AT15: SUV grande D | AU15: 430 | AV15: =+AU15/$AU$391 -> 0.017881648
A16: AUDI | B16: A8 | C16: Auto grande F | D16: 1 | E16: 0 | F16: 0 | G16: 0 | H16: 0 | I16: 0 | J16: 0 | K16: 0 | L16: 0 | M16: 0 | N16: 0 | O16: 0 | P16: =SUM(D16:O16) -> 1 | Q16: =+P16/$P$766 -> 4.1585229e-05 | R16: - | S16: - | AQ16: Vw Saveiro | AR16: VW | AS16: Saveiro | AT16: Pick up pequeño | AU16: 408 | AV16: =+AU16/$AU$391 -> 0.016966773
A17: AUDI | B17: E5 | C17: Auto deportivo | D17: 0 | E17: 0 | F17: 2 | G17: 0 | H17: 0 | I17: 0 | J17: 0 | K17: 0 | L17: 0 | M17: 0 | N17: 0 | O17: 0 | P17: =SUM(D17:O17) -> 2 | Q17: =+P17/$P$766 -> 8.3170458e-05 | AQ17: Chevrolet Tracker | AR17: CHEVROLET | AS17: Tracker | AT17: SUV mediano B | AU17: 378 | AV17: =+AU17/$AU$391 -> 0.015719217
A18: AUDI | B18: E TRON GT RS | C18: Auto deportivo | D18: 0 | E18: 0 | F18: 0 | G18: 0 | H18: 0 | I18: 0 | J18: 0 | K18: 0 | L18: 0 | M18: 0 | N18: 0 | O18: 0 | P18: =SUM(D18:O18) -> 0 | Q18: =+P18/$P$766 -> 0 | R18: - | S18: - | AQ18: Chevrolet Onix | AR18: CHEVROLET | AS18: Onix | AT18: Auto mediano B | AU18: 364 | AV18: =+AU18/$AU$391 -> 0.015137023
A19: AUDI | B19: E-tron | C19: SUV grande D | D19: 0 | E19: 0 | F19: 0 | G19: 0 | H19: 0 | I19: 0 | J19: 0 | K19: 0 | L19: 0 | M19: 0 | N19: 0 | O19: 0 | P19: =SUM(D19:O19) -> 0 | Q19: =+P19/$P$766 -> 0 | R19: - | S19: - | AQ19: Geely Coolray | AR19: GEELY | AS19: Coolray | AT19: SUV mediano c | AU19: 353 | AV19: =+AU19/$AU$391 -> 0.014679586
A20: AUDI | B20: ETRON 50 | C20: SUV mediano C | D20: 0 | E20: 0 | F20: 0 | G20: 0 | H20: 0 | I20: 0 | J20: 0 | K20: 0 | L20: 0 | M20: 0 | N20: 0 | O20: 0 | P20: =SUM(D20:O20) -> 0 | Q20: =+P20/$P$766 -> 0 | R20: - | S20: - | AQ20: Nissan Kicks | AR20: NISSAN | AS20: Kicks | AT20: suv mediano B | AU20: 346 | AV20: =+AU20/$AU$391 -> 0.014388489
A21: AUDI | B21: ETRON 55 | C21: SUV mediano C | D21: 0 | E21: 0 | F21: 0 | G21: 0 | H21: 0 | I21: 0 | J21: 0 | K21: 0 | L21: 0 | M21: 0 | N21: 0 | O21: 0 | P21: =SUM(D21:O21) -> 0 | Q21: =+P21/$P$766 -> 0 | R21: - | S21: - | AQ21: Vw TERA | AR21: VW | AS21: TERA | AT21: SUV mediano B | AU21: 338 | AV21: =+AU21/$AU$391 -> 0.014055807
A22: AUDI | B22: ETRON GT RS | C22: Auto deportivo | D22: 0 | E22: 0 | F22: 0 | G22: 0 | H22: 0 | I22: 0 | J22: 0 | K22: 0 | L22: 0 | M22: 0 | N22: 0 | O22: 0 | P22: =SUM(D22:O22) -> 0 | Q22: =+P22/$P$766 -> 0 | R22: - | S22: - | AQ22: Fiat Fiorino | AR22: FIAT | AS22: Fiorino | AT22: Furgon Pequeño | AU22: 337 | AV22: =+AU22/$AU$391 -> 0.014014222
A23: AUDI | B23: Q2 | C23: SUV mediano C | D23: 1 | E23: 4 | F23: 0 | G23: 0 | H23: 3 | I23: 0 | J23: 0 | K23: 0 | L23: 0 | M23: 0 | N23: 0 | O23: 0 | P23: =SUM(D23:O23) -> 8 | Q23: =+P23/$P$766 -> 0.00033268183 | R23: - | S23: - | AQ23: Vw T-Cross | AR23: VW | AS23: T-Cross | AT23: SUV mediano B | AU23: 336 | AV23: =+AU23/$AU$391 -> 0.013972637
A24: AUDI | B24: Q3 | C24: SUV mediano C | D24: 0 | E24: 1 | F24: 12 | G24: 5 | H24: 2 | I24: 4 | J24: 0 | K24: 0 | L24: 0 | M24: 0 | N24: 0 | O24: 0 | P24: =SUM(D24:O24) -> 24 | Q24: =+P24/$P$766 -> 0.00099804549 | R24: - | S24: - | AQ24: Suzuki Jimny | AR24: SUZUKI | AS24: Jimny | AT24: SUV mediano B | AU24: 319 | AV24: =+AU24/$AU$391 -> 0.013265688
A25: AUDI | B25: Q4 | C25: SUV mediano C | D25: 1 | E25: 0 | F25: 1 | G25: 0 | H25: 0 | I25: 0 | J25: 0 | K25: 0 | L25: 0 | M25: 0 | N25: 0 | O25: 0 | P25: =SUM(D25:O25) -> 2 | Q25: =+P25/$P$766 -> 8.3170458e-05 | R25: - | S25: - | AR25: HYUNDAI | AS25: HB20S | AT25: auto mediano B | AU25: 310 | AV25: =+AU25/$AU$391 -> 0.012891421
A26: AUDI | B26: Q5 | C26: SUV mediano D | D26: 11 | E26: 9 | F26: 2 | G26: 1 | H26: 3 | I26: 1 | J26: 0 | K26: 0 | L26: 0 | M26: 0 | N26: 0 | O26: 0 | P26: =SUM(D26:O26) -> 27 | Q26: =+P26/$P$766 -> 0.0011228012 | R26: 46000 | S26: 35226.65 | AR26: GEELY | AS26: Emgrand | AT26: SUV grande D | AU26: 293 | AV26: =+AU26/$AU$391 -> 0.012184472
A27: AUDI | B27: Q6 | C27: SUV mediano D | D27: 0 | E27: 4 | F27: 0 | G27: 0 | H27: 3 | I27: 2 | J27: 0 | K27: 0 | L27: 0 | M27: 0 | N27: 0 | O27: 0 | P27: =SUM(D27:O27) -> 9 | Q27: =+P27/$P$766 -> 0.00037426706 | R27: - | S27: - | AR27: SUZUKI | AS27: VITARA ACROSS | AT27: SUV mediano B | AU27: 280 | AV27: =+AU27/$AU$391 -> 0.011643864
A28: AUDI | B28: Q7 | C28: SUV grande F | D28: 0 | E28: 2 | F28: 1 | G28: 3 | H28: 1 | I28: 2 | J28: 0 | K28: 0 | L28: 0 | M28: 0 | N28: 0 | O28: 0 | P28: =SUM(D28:O28) -> 9 | Q28: =+P28/$P$766 -> 0.00037426706 | R28: - | S28: - | AR28: TOYOTA | AS28: Yaris Cross | AT28: Auto mediano B | AU28: 276 | AV28: =+AU28/$AU$391 -> 0.011477523
A29: AUDI | B29: Q7 E-tron | C29: SUV grande D | D29: 0 | E29: 0 | F29: 0 | G29: 0 | H29: 0 | I29: 0 | J29: 0 | K29: 0 | L29: 0 | M29: 0 | N29: 0 | O29: 0 | P29: =SUM(D29:O29) -> 0 | Q29: =+P29/$P$766 -> 0 | R29: - | S29: - | AR29: HYUNDAI | AS29: Tucson | AT29: SUV mediano C | AU29: 269 | AV29: =+AU29/$AU$391 -> 0.011186427
A30: AUDI | B30: Q8 | C30: SUV grande F | D30: 5 | E30: 0 | F30: 0 | G30: 2 | H30: 1 | I30: 2 | J30: 0 | K30: 0 | L30: 0 | M30: 0 | N30: 0 | O30: 0 | P30: =SUM(D30:O30) -> 10 | Q30: =+P30/$P$766 -> 0.00041585229 | R30: 79181.86 | S30: 74230.69 | AR30: TOYOTA | AS30: Fortuner | AT30: SUV Grande D | AU30: 266 | AV30: =+AU30/$AU$391 -> 0.011061671
A31: AUDI | B31: Q8 ETRON | C31: SUV grande F | D31: 0 | E31: 0 | F31: 0 | G31: 0 | H31: 0 | I31: 0 | J31: 0 | K31: 0 | L31: 0 | M31: 0 | N31: 0 | O31: 0 | P31: =SUM(D31:O31) -> 0 | Q31: =+P31/$P$766 -> 0 | R31: - | S31: - | AR31: TOYOTA | AS31: Raize | AT31: SUV mediano B | AU31: 260 | AV31: =+AU31/$AU$391 -> 0.01081216
A32: AUDI | B32: R8 | C32: Auto deportivo | D32: 0 | E32: 0 | F32: 0 | G32: 0 | H32: 0 | I32: 0 | J32: 0 | K32: 0 | L32: 0 | M32: 0 | N32: 0 | O32: 0 | P32: =SUM(D32:O32) -> 0 | Q32: =+P32/$P$766 -> 0 | R32: - | S32: - | AR32: JEEP | AS32: Compass | AT32: SUV mediano C | AU32: 252 | AV32: =+AU32/$AU$391 -> 0.010479478
A33: AUDI | B33: RS6 | C33: Auto grande E | D33: 1 | E33: 0 | F33: 0 | G33: 1 | H33: 0 | I33: 0 | J33: 0 | K33: 0 | L33: 0 | M33: 0 | N33: 0 | O33: 0 | P33: =SUM(D33:O33) -> 2 | Q33: =+P33/$P$766 -> 8.3170458e-05 | R33: - | S33: - | AR33: ISUZU | AS33: D-MAX | AT33: Pick up mediano | AU33: 251 | AV33: =+AU33/$AU$391 -> 0.010437892
A34: AUDI | B34: RS Q3 | C34: SUV mediano C | D34: 0 | E34: 0 | F34: 0 | G34: 0 | H34: 0 | I34: 0 | J34: 0 | K34: 0 | L34: 0 | M34: 0 | N34: 0 | O34: 0 | P34: =SUM(D34:O34) -> 0 | Q34: =+P34/$P$766 -> 0 | R34: - | S34: - | AR34: KIA | AS34: Seltos | AT34: SUV Mediano B | AU34: 244 | AV34: =+AU34/$AU$391 -> 0.010146796
A35: AUDI | B35: RSQ8 | C35: SUV mediano C | D35: 0 | E35: 0 | F35: 0 | G35: 0 | H35: 0 | I35: 0 | J35: 0 | K35: 0 | L35: 0 | M35: 0 | N35: 0 | O35: 0 | P35: =SUM(D35:O35) -> 0 | Q35: =+P35/$P$766 -> 0 | R35: - | S35: - | AR35: NISSAN | AS35: KAIT | AT35: suv mediano B | AU35: 244 | AV35: =+AU35/$AU$391 -> 0.010146796
A36: AUDI | B36: SQ5 | C36: SUV mediano C | D36: 0 | E36: 0 | F36: 0 | G36: 1 | H36: 0 | I36: 0 | J36: 0 | K36: 0 | L36: 0 | M36: 0 | N36: 0 | O36: 0 | P36: =SUM(D36:O36) -> 1 | Q36: =+P36/$P$766 -> 4.1585229e-05 | R36: - | S36: - | AR36: CHERY | AS36: T7 | AT36: SUV mediano B | AU36: 243 | AV36: =+AU36/$AU$391 -> 0.010105211
A37: AVATR | B37: AVATR 11 | C37: SUV grande E | D37: 0 | E37: 0 | F37: 10 | G37: 0 | H37: 0 | I37: 0 | J37: 0 | K37: 0 | L37: 0 | M37: 0 | N37: 0 | O37: 0 | P37: =SUM(D37:O37) -> 10 | Q37: =+P37/$P$766 -> 0.00041585229 | AR37: CHERY | AS37: T4 | AT37: SUV mediano C | AU37: 234 | AV37: =+AU37/$AU$391 -> 0.0097309436
A38: AVATR | B38: 07 | C38: SUV mediano C | D38: 0 | E38: 0 | F38: 0 | G38: 7 | H38: 0 | I38: 4 | J38: 0 | K38: 0 | L38: 0 | M38: 0 | N38: 0 | O38: 0 | P38: =SUM(D38:O38) -> 11 | Q38: =+P38/$P$766 -> 0.00045743752 | AR38: HYUNDAI | AS38: NEW GRAND I10 | AT38: auto mediano B | AU38: 231 | AV38: =+AU38/$AU$391 -> 0.0096061879
A39: BAIC | B39: BJ30 | C39: SUV mediano C | D39: 0 | E39: 13 | F39: 4 | G39: 0 | H39: 0 | I39: 14 | J39: 0 | K39: 0 | L39: 0 | M39: 0 | N39: 0 | O39: 0 | P39: =SUM(D39:O39) -> 31 | Q39: =+P39/$P$766 -> 0.0012891421 | R39: - | S39: - | AR39: CHEVROLET | AS39: Montana | AT39: Pick up pequeño | AU39: 205 | AV39: =+AU39/$AU$391 -> 0.0085249719
A40: BAIC | B40: BJ40 | C40: SUV mediano C | D40: 0 | E40: 0 | F40: 0 | G40: 0 | H40: 0 | I40: 0 | J40: 0 | K40: 0 | L40: 0 | M40: 0 | N40: 0 | O40: 0 | P40: =SUM(D40:O40) -> 0 | Q40: =+P40/$P$766 -> 0 | R40: - | S40: - | AQ40: Toyota RAV4 | AR40: NISSAN | AS40: Frontier | AT40: Pick up mediano | AU40: 200 | AV40: =+AU40/$AU$391 -> 0.0083170458
A41: BAIC | B41: BJ60 | C41: SUV mediano C | D41: 0 | E41: 4 | F41: 6 | G41: 0 | H41: 2 | I41: 0 | J41: 0 | K41: 0 | L41: 0 | M41: 0 | N41: 0 | O41: 0 | P41: =SUM(D41:O41) -> 12 | Q41: =+P41/$P$766 -> 0.00049902275 | R41: - | S41: - | AQ41: Changan NEW CS35 PLUS | AR41: FIAT | AS41: Fastback | AT41: SUV mediano C | AU41: 192 | AV41: =+AU41/$AU$391 -> 0.007984364
A42: BAIC | B42: D20 | C42: Auto mediano B | D42: 0 | E42: 0 | F42: 0 | G42: 0 | H42: 0 | I42: 0 | J42: 0 | K42: 0 | L42: 0 | M42: 0 | N42: 0 | O42: 0 | P42: =SUM(D42:O42) -> 0 | Q42: =+P42/$P$766 -> 0 | R42: - | S42: - | AQ42: Geely Emgrand | AR42: FORD | AS42: Ranger | AT42: Pick up mediano | AU42: 191 | AV42: =+AU42/$AU$391 -> 0.0079427787
A43: BAIC | B43: EC3 | C43: City car | D43: 0 | E43: 0 | F43: 0 | G43: 0 | H43: 0 | I43: 0 | J43: 0 | K43: 0 | L43: 0 | M43: 0 | N43: 0 | O43: 0 | P43: =SUM(D43:O43) -> 0 | Q43: =+P43/$P$766 -> 0 | R43: - | S43: - | AQ43: Changan NEW CS55 PLUS | AR43: TOYOTA | AS43: Agya | AT43: Auto mediano B | AU43: 190 | AV43: =+AU43/$AU$391 -> 0.0079011935
A44: BAIC | B44: EU5 | C44: Auto mediano B | D44: 0 | E44: 0 | F44: 0 | G44: 0 | H44: 0 | I44: 0 | J44: 0 | K44: 0 | L44: 0 | M44: 0 | N44: 0 | O44: 0 | P44: =SUM(D44:O44) -> 0 | Q44: =+P44/$P$766 -> 0 | R44: - | S44: - | AQ44: Nissan Xtrail Epower | AR44: CHERY | AS44: T2 | AT44: SUV mediano C | AU44: 176 | AV44: =+AU44/$AU$391 -> 0.0073190003
A45: BAIC | B45: EX5 | C45: SUV mediano C | D45: 0 | E45: 0 | F45: 0 | G45: 0 | H45: 0 | I45: 0 | J45: 0 | K45: 0 | L45: 0 | M45: 0 | N45: 0 | O45: 0 | P45: =SUM(D45:O45) -> 0 | Q45: =+P45/$P$766 -> 0 | R45: - | S45: - | AR45: TOYOTA | AS45: Rush | AT45: SUV Mediano C | AU45: 171 | AV45: =+AU45/$AU$391 -> 0.0071110741
A46: BAIC | B46: X25 | C46: SUV mediano B | D46: 0 | E46: 0 | F46: 0 | G46: 0 | H46: 0 | I46: 0 | J46: 0 | K46: 0 | L46: 0 | M46: 0 | N46: 0 | O46: 0 | P46: =SUM(D46:O46) -> 0 | Q46: =+P46/$P$766 -> 0 | R46: - | S46: - | AR46: CHEVROLET | AS46: Traiblazer | AT46: SUV GRANDE E | AU46: 168 | AV46: =+AU46/$AU$391 -> 0.0069863185
A47: BAIC | B47: X35 | C47: SUV mediano B | D47: 0 | E47: 0 | F47: 1 | G47: 0 | H47: 2 | I47: 0 | J47: 0 | K47: 0 | L47: 0 | M47: 0 | N47: 0 | O47: 0 | P47: =SUM(D47:O47) -> 3 | Q47: =+P47/$P$766 -> 0.00012475569 | R47: - | S47: - | AQ47: M. Benz tipo GLC220 | AR47: MAZDA | AS47: CX30 | AT47: SUV mediano B | AU47: 147 | AV47: =+AU47/$AU$391 -> 0.0061130287
A48: BAIC | B48: X55 | C48: SUV mediano C | D48: 6 | E48: 3 | F48: 5 | G48: 0 | H48: 7 | I48: 0 | J48: 0 | K48: 0 | L48: 0 | M48: 0 | N48: 0 | O48: 0 | P48: =SUM(D48:O48) -> 21 | Q48: =+P48/$P$766 -> 0.00087328981 | R48: 17755.64 | S48: 17755.64 | AQ48: Nissan Qashqai | AR48: MAZDA | AS48: CX5 | AT48: SUV mediano C | AU48: 143 | AV48: =+AU48/$AU$391 -> 0.0059466877
A49: BAIC | B49: X75 | C49: SUV Mediano C | D49: 0 | E49: 4 | F49: 0 | G49: 0 | H49: 3 | I49: 0 | J49: 0 | K49: 0 | L49: 0 | M49: 0 | N49: 0 | O49: 0 | P49: =SUM(D49:O49) -> 7 | Q49: =+P49/$P$766 -> 0.0002910966 | R49: - | S49: - | AR49: Jetour | AS49: X50 | AT49: SUV mediano C | AU49: 141 | AV49: =+AU49/$AU$391 -> 0.0058635173
A50: BAOJUN | B50: LZN7007EVC2MBMA | C50: SUV mediano B | D50: 0 | E50: 0 | F50: 0 | G50: 0 | H50: 0 | I50: 0 | J50: 0 | K50: 0 | L50: 0 | M50: 0 | N50: 0 | O50: 0 | P50: =SUM(D50:O50) -> 0 | Q50: =+P50/$P$766 -> 0 | R50: - | S50: - | AQ50: Honda HRV | AR50: HYUNDAI | AS50: Venue | AT50: SUV mediano B | AU50: 137 | AV50: =+AU50/$AU$391 -> 0.0056971764
A51: BAOJUN | B51: YEP PLUS | C51: SUV mediano B | D51: 0 | E51: 0 | F51: 0 | G51: 0 | H51: 3 | I51: 0 | J51: 0 | K51: 0 | L51: 0 | M51: 0 | N51: 0 | O51: 0 | P51: =SUM(D51:O51) -> 3 | Q51: =+P51/$P$766 -> 0.00012475569 | AR51: KIA | AS51: Sorento | AT51: SUV grande E | AU51: 135 | AV51: =+AU51/$AU$391 -> 0.0056140059
A52: BEIJING | B52: EX3 R600 | C52: SUV mediano B | D52: 0 | E52: 0 | F52: 0 | G52: 0 | H52: 0 | I52: 0 | J52: 0 | K52: 0 | L52: 0 | M52: 0 | N52: 0 | O52: 0 | P52: =SUM(D52:O52) -> 0 | Q52: =+P52/$P$766 -> 0 | R52: - | S52: - | AQ52: Jetour X70 | AR52: GEELY | AS52: Cityray | AT52: SUV mediano B | AU52: 133 | AV52: =+AU52/$AU$391 -> 0.0055308354
A53: BESTUNE | B53: B70S ARES | C53: SUV mediano C | D53: 0 | E53: 0 | F53: 0 | G53: 0 | H53: 0 | I53: 0 | J53: 0 | K53: 0 | L53: 0 | M53: 0 | N53: 0 | O53: 0 | P53: =SUM(D53:O53) -> 0 | Q53: =+P53/$P$766 -> 0 | R53: - | S53: - | AQ53: Citroen C4 cactus | AR53: VW | AS53: Polo Track | AT53: Auto mediano B | AU53: 129 | AV53: =+AU53/$AU$391 -> 0.0053644945
A54: BESTUNE | B54: T55 | C54: SUV mediano C | D54: 0 | E54: 0 | F54: 0 | G54: 0 | H54: 0 | I54: 0 | J54: 0 | K54: 0 | L54: 0 | M54: 0 | N54: 0 | O54: 0 | P54: =SUM(D54:O54) -> 0 | Q54: =+P54/$P$766 -> 0 | R54: - | S54: - | AQ54: Hyundai Venue | AR54: RAM | AS54: RAMPAGE | AT54: Pick up mediano | AU54: 128 | AV54: =+AU54/$AU$391 -> 0.0053229093
A55: BESTUNE | B55: T77 | C55: SUV mediano C | D55: 0 | E55: 0 | F55: 0 | G55: 0 | H55: 0 | I55: 0 | J55: 0 | K55: 0 | L55: 0 | M55: 0 | N55: 0 | O55: 0 | P55: =SUM(D55:O55) -> 0 | Q55: =+P55/$P$766 -> 0 | R55: - | S55: - | AR55: CHERY | AS55: T8 | AT55: SUV grande E | AU55: 121 | AV55: =+AU55/$AU$391 -> 0.0050318127
A56: BESTUNE | B56: T99 | C56: SUV grande E | D56: 0 | E56: 0 | F56: 0 | G56: 0 | H56: 0 | I56: 0 | J56: 0 | K56: 0 | L56: 0 | M56: 0 | N56: 0 | O56: 0 | P56: =SUM(D56:O56) -> 0 | Q56: =+P56/$P$766 -> 0 | R56: - | S56: - | AQ56: M. Benz tipo GLE300 | AR56: GREAT WALL | AS56: H6 | AT56: SUV mediano C | AU56: 117 | AV56: =+AU56/$AU$391 -> 0.0048654718
A57: BMW | B57: 118 | C57: Auto mediano C | D57: 0 | E57: 0 | F57: 0 | G57: 0 | H57: 0 | I57: 0 | J57: 0 | K57: 0 | L57: 0 | M57: 0 | N57: 0 | O57: 0 | P57: =SUM(D57:O57) -> 0 | Q57: =+P57/$P$766 -> 0 | R57: - | S57: - | AR57: Jetour | AS57: T2 | AT57: SUV mediano C | AU57: 113 | AV57: =+AU57/$AU$391 -> 0.0046991309
A58: BMW | B58: 128 | C58: Auto mediano C | D58: 0 | E58: 0 | F58: 0 | G58: 0 | H58: 0 | I58: 0 | J58: 0 | K58: 0 | L58: 0 | M58: 0 | N58: 0 | O58: 0 | P58: =SUM(D58:O58) -> 0 | Q58: =+P58/$P$766 -> 0 | R58: - | S58: - | AQ58: Jetour Dashing | AR58: Jetour | AS58: T1 | AT58: SUV mediano C | AU58: 112 | AV58: =+AU58/$AU$391 -> 0.0046575456
A59: BMW | B59: 218 | C59: Auto mediano C | D59: 1 | E59: 0 | F59: 0 | G59: 0 | H59: 0 | I59: 4 | J59: 0 | K59: 0 | L59: 0 | M59: 0 | N59: 0 | O59: 0 | P59: =SUM(D59:O59) -> 5 | Q59: =+P59/$P$766 -> 0.00020792614 | R59: - | S59: - | AQ59: Maxus T60 | AR59: LYNK & CO | AS59: 06 | AT59: SUV mediano B | AU59: 109 | AV59: =+AU59/$AU$391 -> 0.00453279
A60: BMW | B60: 220 | C60: Auto mediano C | D60: 0 | E60: 0 | F60: 0 | G60: 0 | H60: 0 | I60: 0 | J60: 0 | K60: 0 | L60: 0 | M60: 0 | N60: 0 | O60: 0 | P60: =SUM(D60:O60) -> 0 | Q60: =+P60/$P$766 -> 0 | R60: - | S60: - | AQ60: M. Benz tipo GLE450 | AR60: MAZDA | AS60: BT50 | AT60: Pick up mediano | AU60: 109 | AV60: =+AU60/$AU$391 -> 0.00453279
A61: BMW | B61: 240 | C61: Auto mediano B | D61: 0 | E61: 0 | F61: 0 | G61: 0 | H61: 0 | I61: 0 | J61: 0 | K61: 0 | L61: 0 | M61: 0 | N61: 0 | O61: 0 | P61: =SUM(D61:O61) -> 0 | Q61: =+P61/$P$766 -> 0 | R61: - | S61: - | AQ61: Chevrolet Tracker | AR61: KGM | AS61: Tivoli | AT61: SUV mediano C | AU61: 108 | AV61: =+AU61/$AU$391 -> 0.0044912047
A62: BMW | B62: 320 | C62: Auto mediano B | D62: 0 | E62: 0 | F62: 0 | G62: 0 | H62: 0 | I62: 0 | J62: 0 | K62: 0 | L62: 0 | M62: 0 | N62: 0 | O62: 0 | P62: =SUM(D62:O62) -> 0 | Q62: =+P62/$P$766 -> 0 | R62: - | S62: - | AQ62: Honda Civic | AR62: KIA | AS62: Carens | AT62: SUV grande E | AU62: 107 | AV62: =+AU62/$AU$391 -> 0.0044496195
A63: BMW | B63: 330 | C63: Auto mediano C | D63: 0 | E63: 1 | F63: 0 | G63: 0 | H63: 0 | I63: 0 | J63: 0 | K63: 0 | L63: 0 | M63: 0 | N63: 0 | O63: 0 | P63: =SUM(D63:O63) -> 1 | Q63: =+P63/$P$766 -> 4.1585229e-05 | R63: - | S63: - | AQ63: Jeep Grand Cherokee Limited | AR63: Jetour | AS63: X70 | AT63: SUV mediano C | AU63: 103 | AV63: =+AU63/$AU$391 -> 0.0042832786
A64: BMW | B64: 420 | C64: Auto mediano C | D64: 0 | E64: 0 | F64: 0 | G64: 0 | H64: 0 | I64: 1 | J64: 0 | K64: 0 | L64: 0 | M64: 0 | N64: 0 | O64: 0 | P64: =SUM(D64:O64) -> 1 | Q64: =+P64/$P$766 -> 4.1585229e-05 | R64: - | S64: - | AQ64: Renault Kwid | AR64: MITSUBISHI | AS64: L200 Triton | AT64: Pick up mediano | AU64: 103 | AV64: =+AU64/$AU$391 -> 0.0042832786
A65: BMW | B65: 430 | C65: Auto mediano C | D65: 0 | E65: 0 | F65: 0 | G65: 0 | H65: 0 | I65: 0 | J65: 0 | K65: 0 | L65: 0 | M65: 0 | N65: 0 | O65: 0 | P65: =SUM(D65:O65) -> 0 | Q65: =+P65/$P$766 -> 0 | R65: - | S65: - | AQ65: Toyota Corolla | AR65: FIAT | AS65: Argo | AT65: Auto mediano B | AU65: 101 | AV65: =+AU65/$AU$391 -> 0.0042001081
A66: BMW | B66: 520 | C66: Auto grande E | D66: 0 | E66: 0 | F66: 0 | G66: 0 | H66: 0 | I66: 0 | J66: 0 | K66: 0 | L66: 0 | M66: 0 | N66: 0 | O66: 0 | P66: =SUM(D66:O66) -> 0 | Q66: =+P66/$P$766 -> 0 | R66: - | S66: - | AQ66: Vw Tiguan | AR66: Jetour | AS66: Dashing | AT66: SUV mediano C | AU66: 98 | AV66: =+AU66/$AU$391 -> 0.0040753524
A67: BMW | B67: 530 | C67: Auto grande E | D67: 1 | E67: 0 | F67: 0 | G67: 0 | H67: 0 | I67: 0 | J67: 0 | K67: 0 | L67: 0 | M67: 0 | N67: 0 | O67: 0 | P67: =SUM(D67:O67) -> 1 | Q67: =+P67/$P$766 -> 4.1585229e-05 | R67: - | S67: - | AQ67: Vw Touareg | AR67: BYD | AS67: Song | AT67: SUV mediano C | AU67: 94 | AV67: =+AU67/$AU$391 -> 0.0039090115
A68: BMW | B68: 745 | C68: Auto grande F | D68: 0 | E68: 0 | F68: 0 | G68: 0 | H68: 0 | I68: 0 | J68: 0 | K68: 0 | L68: 0 | M68: 0 | N68: 0 | O68: 0 | P68: =SUM(D68:O68) -> 0 | Q68: =+P68/$P$766 -> 0 | R68: - | S68: - | AQ68: Citroen Berlingo | AR68: SOUEAST | AS68: S06 | AT68: SUV mediano C | AU68: 92 | AV68: =+AU68/$AU$391 -> 0.0038258411
A69: BMW | B69: 750E XDRIVE LIMOUSINE | C69: Auto grande F | D69: 1 | E69: 0 | F69: 0 | G69: 0 | H69: 0 | I69: 0 | J69: 0 | K69: 0 | L69: 0 | M69: 0 | N69: 0 | O69: 0 | P69: =SUM(D69:O69) -> 1 | Q69: =+P69/$P$766 -> 4.1585229e-05 | R69: - | S69: - | AR69: TOYOTA | AS69: Land Cruiser 300 | AT69: SUV grande E | AU69: 91 | AV69: =+AU69/$AU$391 -> 0.0037842558
A70: BMW | B70: 228I | C70: Auto mediano B | D70: 0 | E70: 0 | F70: 0 | G70: 0 | H70: 0 | I70: 0 | J70: 0 | K70: 0 | L70: 0 | M70: 0 | N70: 0 | O70: 0 | P70: =SUM(D70:O70) -> 0 | Q70: =+P70/$P$766 -> 0 | R70: - | S70: - | AQ70: Gac GS3 | AR70: CHEVROLET | AS70: Silverado | AT70: Pick up grande | AU70: 85 | AV70: =+AU70/$AU$391 -> 0.0035347445
A71: BMW | B71: 330E LIMOUSINE | C71: Auto grande E | D71: 0 | E71: 0 | F71: 0 | G71: 0 | H71: 0 | I71: 0 | J71: 0 | K71: 0 | L71: 0 | M71: 0 | N71: 0 | O71: 0 | P71: =SUM(D71:O71) -> 0 | Q71: =+P71/$P$766 -> 0 | R71: - | S71: - | AQ71: Chevrolet Traiblazer | AR71: ISUZU | AS71: MU-X | AT71: SUV Mediano C | AU71: 84 | AV71: =+AU71/$AU$391 -> 0.0034931592
A72: BMW | B72: 740I | C72: Auto grande E | D72: 0 | E72: 0 | F72: 0 | G72: 0 | H72: 0 | I72: 0 | J72: 0 | K72: 0 | L72: 0 | M72: 0 | N72: 0 | O72: 0 | P72: =SUM(D72:O72) -> 0 | Q72: =+P72/$P$766 -> 0 | R72: - | S72: - | AQ72: Hyundai HB20S | AR72: PEUGEOT | AS72: 2008 | AT72: SUV Mediano C | AU72: 84 | AV72: =+AU72/$AU$391 -> 0.0034931592
A73: BMW | B73: I3S | C73: City car | D73: 0 | E73: 0 | F73: 0 | G73: 0 | H73: 0 | I73: 0 | J73: 0 | K73: 0 | L73: 0 | M73: 0 | N73: 0 | O73: 0 | P73: =SUM(D73:O73) -> 0 | Q73: =+P73/$P$766 -> 0 | R73: - | S73: - | AQ73: Hyundai Staria | AR73: NISSAN | AS73: Qashqai | AT73: SUV mediano C | AU73: 82 | AV73: =+AU73/$AU$391 -> 0.0034099888
A74: BMW | B74: I4 | C74: Auto mediano C | D74: 0 | E74: 0 | F74: 0 | G74: 0 | H74: 0 | I74: 0 | J74: 0 | K74: 0 | L74: 0 | M74: 0 | N74: 0 | O74: 0 | P74: =SUM(D74:O74) -> 0 | Q74: =+P74/$P$766 -> 0 | R74: - | S74: - | AQ74: Lexus NX350 | AR74: BYD | AS74: YUAN PRO | AT74: SUV mediano C | AU74: 81 | AV74: =+AU74/$AU$391 -> 0.0033684035
A75: BMW | B75: I4 EDRIVE40 | C75: Auto mediano C | D75: 0 | E75: 0 | F75: 0 | G75: 0 | H75: 0 | I75: 0 | J75: 0 | K75: 0 | L75: 0 | M75: 0 | N75: 0 | O75: 0 | P75: =SUM(D75:O75) -> 0 | Q75: =+P75/$P$766 -> 0 | R75: - | S75: - | AQ75: Chery T2 | AR75: KIA | AS75: K3 CROSS | AT75: SUV mediano C | AU75: 81 | AV75: =+AU75/$AU$391 -> 0.0033684035
A76: BMW | B76: I5 EDRIVE40 LIMOUSINE | C76: Auto grande E | D76: 0 | E76: 0 | F76: 0 | G76: 0 | H76: 0 | I76: 0 | J76: 0 | K76: 0 | L76: 0 | M76: 0 | N76: 0 | O76: 0 | P76: =SUM(D76:O76) -> 0 | Q76: =+P76/$P$766 -> 0 | R76: - | S76: - | AQ76: Chevrolet Silverado | AR76: HONDA | AS76: HRV | AT76: SUV mediano C | AU76: 80 | AV76: =+AU76/$AU$391 -> 0.0033268183
A77: BMW | B77: I7 | C77: Auto grande E | D77: 0 | E77: 0 | F77: 0 | G77: 0 | H77: 0 | I77: 0 | J77: 0 | K77: 0 | L77: 0 | M77: 0 | N77: 0 | O77: 0 | P77: =SUM(D77:O77) -> 0 | Q77: =+P77/$P$766 -> 0 | R77: - | S77: - | AQ77: Ram Ram 2500 | AR77: FORD | AS77: Raptor | AT77: Pick up grande | AU77: 77 | AV77: =+AU77/$AU$391 -> 0.0032020626
A78: BMW | B78: I8 | C78: Auto deportivo | D78: 0 | E78: 0 | F78: 0 | G78: 0 | H78: 0 | I78: 0 | J78: 0 | K78: 0 | L78: 0 | M78: 0 | N78: 0 | O78: 0 | P78: =SUM(D78:O78) -> 0 | Q78: =+P78/$P$766 -> 0 | R78: - | S78: - | AQ78: Vw Amarok | AR78: CITROEN | AS78: BASALT | AT78: SUV mediano B | AU78: 75 | AV78: =+AU78/$AU$391 -> 0.0031188922
A79: BMW | B79: IX1 | C79: SUV mediano C | D79: 0 | E79: 0 | F79: 0 | G79: 2 | H79: 0 | I79: 0 | J79: 0 | K79: 0 | L79: 0 | M79: 0 | N79: 0 | O79: 0 | P79: =SUM(D79:O79) -> 2 | Q79: =+P79/$P$766 -> 8.3170458e-05 | AR79: VW | AS79: Taos | AT79: SUV mediano B | AU79: 74 | AV79: =+AU79/$AU$391 -> 0.0030773069
A80: BMW | B80: IX1 25L | C80: SUV mediano C | D80: 0 | E80: 0 | F80: 2 | G80: 0 | H80: 0 | I80: 0 | J80: 0 | K80: 0 | L80: 0 | M80: 0 | N80: 0 | O80: 0 | P80: =SUM(D80:O80) -> 2 | Q80: =+P80/$P$766 -> 8.3170458e-05 | AR80: HONDA | AS80: WRV | AT80: SUV Mediano C | AU80: 72 | AV80: =+AU80/$AU$391 -> 0.0029941365
A81: BMW | B81: IX XDRIVE40 | C81: SUV grande E | D81: 0 | E81: 0 | F81: 0 | G81: 0 | H81: 0 | I81: 0 | J81: 0 | K81: 0 | L81: 0 | M81: 0 | N81: 0 | O81: 0 | P81: =SUM(D81:O81) -> 0 | Q81: =+P81/$P$766 -> 0 | R81: - | S81: - | AR81: TOYOTA | AS81: RAV4 | AT81: SUV mediano C | AU81: 71 | AV81: =+AU81/$AU$391 -> 0.0029525513
A82: BMW | B82: IX XDRIVE50 | C82: SUV mediano C | D82: 0 | E82: 0 | F82: 0 | G82: 0 | H82: 0 | I82: 0 | J82: 0 | K82: 0 | L82: 0 | M82: 0 | N82: 0 | O82: 0 | P82: =SUM(D82:O82) -> 0 | Q82: =+P82/$P$766 -> 0 | R82: - | S82: - | AQ82: Haval H6 HEV | AR82: FORD | AS82: Territory | AT82: SUV mediano C | AU82: 66 | AV82: =+AU82/$AU$391 -> 0.0027446251
A83: BMW | B83: IX1 EDRIVE20 | C83: SUV grande E | D83: 0 | E83: 0 | F83: 0 | G83: 0 | H83: 0 | I83: 0 | J83: 0 | K83: 0 | L83: 0 | M83: 0 | N83: 0 | O83: 0 | P83: =SUM(D83:O83) -> 0 | Q83: =+P83/$P$766 -> 0 | R83: - | S83: - | AQ83: Bmw X6 | AR83: VW | AS83: Tiguan | AT83: SUV mediano C | AU83: 66 | AV83: =+AU83/$AU$391 -> 0.0027446251
A84: BMW | B84: IX1 EDRIVE25LX DESIGN | C84: SUV mediano C | D84: 0 | E84: 0 | F84: 1 | G84: 0 | H84: 0 | I84: 0 | J84: 0 | K84: 0 | L84: 0 | M84: 0 | N84: 0 | O84: 0 | P84: =SUM(D84:O84) -> 1 | Q84: =+P84/$P$766 -> 4.1585229e-05 | AR84: MAHINDRA | AS84: XUV 3XO | AT84: SUV mediano B | AU84: 64 | AV84: =+AU84/$AU$391 -> 0.0026614547
A85: BMW | B85: IX1 XDRIVE30 | C85: SUV mediano C | D85: 0 | E85: 0 | F85: 0 | G85: 0 | H85: 0 | I85: 0 | J85: 0 | K85: 0 | L85: 0 | M85: 0 | N85: 0 | O85: 0 | P85: =SUM(D85:O85) -> 0 | Q85: =+P85/$P$766 -> 0 | R85: - | S85: - | AQ85: Ford F150 | AR85: TOYOTA | AS85: Corolla GLI | AT85: Auto mediano C | AU85: 62 | AV85: =+AU85/$AU$391 -> 0.0025782842
A86: BMW | B86: IX2 XDRIVE30 | C86: SUV mediano C | D86: 0 | E86: 0 | F86: 0 | G86: 0 | H86: 0 | I86: 0 | J86: 0 | K86: 0 | L86: 0 | M86: 0 | N86: 0 | O86: 0 | P86: =SUM(D86:O86) -> 0 | Q86: =+P86/$P$766 -> 0 | R86: - | S86: - | AQ86: Kia EV9 GTLINE | AR86: CHERY | AS86: HIMLA | AT86: Pick up mediano | AU86: 60 | AV86: =+AU86/$AU$391 -> 0.0024951137
A87: BMW | B87: IX3 M SPORT | C87: SUV mediano C | D87: 0 | E87: 0 | F87: 0 | G87: 0 | H87: 0 | I87: 0 | J87: 0 | K87: 0 | L87: 0 | M87: 0 | N87: 0 | O87: 0 | P87: =SUM(D87:O87) -> 0 | Q87: =+P87/$P$766 -> 0 | R87: - | S87: - | AR87: VOLVO | AS87: EX30 | AT87: SUV mediano B | AU87: 59 | AV87: =+AU87/$AU$391 -> 0.0024535285
A88: BMW | B88: M135 XDRIVE | C88: Auto deportivo | D88: 0 | E88: 1 | F88: 0 | G88: 0 | H88: 0 | I88: 0 | J88: 0 | K88: 0 | L88: 0 | M88: 0 | N88: 0 | O88: 0 | P88: =SUM(D88:O88) -> 1 | Q88: =+P88/$P$766 -> 4.1585229e-05 | R88: - | S88: - | AQ88: M. Benz tipo GLE53 | AR88: CHEVROLET | AS88: SPARK EUV T | AT88: City car | AU88: 56 | AV88: =+AU88/$AU$391 -> 0.0023287728
A89: BMW | B89: M2 | C89: Auto deportivo | D89: 0 | E89: 1 | F89: 0 | G89: 1 | H89: 0 | I89: 0 | J89: 0 | K89: 0 | L89: 0 | M89: 0 | N89: 0 | O89: 0 | P89: =SUM(D89:O89) -> 2 | Q89: =+P89/$P$766 -> 8.3170458e-05 | R89: - | S89: - | AQ89: Mitsubishi MIRAGE | AR89: CHEVROLET | AS89: SONIC | AT89: SUV mediano B | AU89: 55 | AV89: =+AU89/$AU$391 -> 0.0022871876
A90: BMW | B90: M235I | C90: Auto deportivo | D90: 0 | E90: 0 | F90: 0 | G90: 0 | H90: 0 | I90: 0 | J90: 0 | K90: 0 | L90: 0 | M90: 0 | N90: 0 | O90: 0 | P90: =SUM(D90:O90) -> 0 | Q90: =+P90/$P$766 -> 0 | R90: - | S90: - | AQ90: Porsche Cayenne | AR90: TOYOTA | AS90: Prado | AT90: SUV mediano D | AU90: 54 | AV90: =+AU90/$AU$391 -> 0.0022456024
A91: BMW | B91: M3 | C91: Auto deportivo | D91: 0 | E91: 0 | F91: 0 | G91: 0 | H91: 0 | I91: 0 | J91: 0 | K91: 0 | L91: 0 | M91: 0 | N91: 0 | O91: 0 | P91: =SUM(D91:O91) -> 0 | Q91: =+P91/$P$766 -> 0 | R91: - | S91: - | AQ91: Ram Ram 1500 | AR91: VW | AS91: Nivus | AT91: SUV mediano C | AU91: 54 | AV91: =+AU91/$AU$391 -> 0.0022456024
A92: BMW | B92: M340I | C92: Auto mediano C | D92: 0 | E92: 1 | F92: 0 | G92: 0 | H92: 0 | I92: 0 | J92: 0 | K92: 0 | L92: 0 | M92: 0 | N92: 0 | O92: 0 | P92: =SUM(D92:O92) -> 1 | Q92: =+P92/$P$766 -> 4.1585229e-05 | R92: - | S92: - | AQ92: Renault ARKANA E-TECH HYBRID | AR92: BMW | AS92: X3 | AT92: SUV mediano D | AU92: 50 | AV92: =+AU92/$AU$391 -> 0.0020792614
A93: BMW | B93: M4 | C93: Auto deportivo | D93: 0 | E93: 0 | F93: 1 | G93: 0 | H93: 0 | I93: 0 | J93: 0 | K93: 0 | L93: 0 | M93: 0 | N93: 0 | O93: 0 | P93: =SUM(D93:O93) -> 1 | Q93: =+P93/$P$766 -> 4.1585229e-05 | R93: - | S93: - | AQ93: Bmw X4 | AR93: GAC | AS93: GS4 | AT93: SUV Mediano B | AU93: 50 | AV93: =+AU93/$AU$391 -> 0.0020792614
A94: BMW | B94: M440I | C94: Auto deportivo | D94: 0 | E94: 0 | F94: 0 | G94: 0 | H94: 0 | I94: 0 | J94: 0 | K94: 0 | L94: 0 | M94: 0 | N94: 0 | O94: 0 | P94: =SUM(D94:O94) -> 0 | Q94: =+P94/$P$766 -> 0 | R94: - | S94: - | AQ94: Dodge Durango | AR94: GREAT WALL | AS94: Poer | AT94: Pick up grande | AU94: 50 | AV94: =+AU94/$AU$391 -> 0.0020792614
A95: BMW | B95: M5 | C95: Auto deportivo | D95: 0 | E95: 0 | F95: 1 | G95: 0 | H95: 0 | I95: 0 | J95: 0 | K95: 0 | L95: 0 | M95: 0 | N95: 0 | O95: 0 | P95: =SUM(D95:O95) -> 1 | Q95: =+P95/$P$766 -> 4.1585229e-05 | R95: - | S95: - | AQ95: Ford Bronco | AR95: RENAULT | AS95: Koleos | AT95: SUV mediano C | AU95: 50 | AV95: =+AU95/$AU$391 -> 0.0020792614
A96: BMW | B96: M550I XDRIVE LIMOUSINE | C96: Auto grande E | D96: 0 | E96: 0 | F96: 0 | G96: 0 | H96: 0 | I96: 0 | J96: 0 | K96: 0 | L96: 0 | M96: 0 | N96: 0 | O96: 0 | P96: =SUM(D96:O96) -> 0 | Q96: =+P96/$P$766 -> 0 | R96: - | S96: - | AQ96: M. Benz tipo GLA200 | AR96: MG | AS96: MG EHS | AT96: SUV mediano C | AU96: 49 | AV96: =+AU96/$AU$391 -> 0.0020376762
A97: BMW | B97: M8 | C97: Auto deportivo | D97: 0 | E97: 0 | F97: 0 | G97: 0 | H97: 0 | I97: 0 | J97: 0 | K97: 0 | L97: 0 | M97: 0 | N97: 0 | O97: 0 | P97: =SUM(D97:O97) -> 0 | Q97: =+P97/$P$766 -> 0 | R97: - | S97: - | AQ97: Maxus G10 | AR97: CHERY | AS97: M7 PRO 1.5 T A/T G COMFORT 2WD | AT97: SUV grande E | AU97: 48 | AV97: =+AU97/$AU$391 -> 0.001996091
A98: BMW | B98: M850 | C98: Auto deportivo | D98: 0 | E98: 0 | F98: 0 | G98: 0 | H98: 0 | I98: 0 | J98: 0 | K98: 0 | L98: 0 | M98: 0 | N98: 0 | O98: 0 | P98: =SUM(D98:O98) -> 0 | Q98: =+P98/$P$766 -> 0 | R98: - | S98: - | AQ98: Renault Oroch | AR98: FIAT | AS98: Toro | AT98: Pick up mediano | AU98: 47 | AV98: =+AU98/$AU$391 -> 0.0019545058
A99: BMW | B99: X1 | C99: SUV mediano C | D99: 1 | E99: 5 | F99: 7 | G99: 4 | H99: 0 | I99: 11 | J99: 0 | K99: 0 | L99: 0 | M99: 0 | N99: 0 | O99: 0 | P99: =SUM(D99:O99) -> 28 | Q99: =+P99/$P$766 -> 0.0011643864 | R99: - | S99: - | AQ99: Bmw X5 | AR99: SUZUKI | AS99: Swift | AT99: Auto mediano B | AU99: 47 | AV99: =+AU99/$AU$391 -> 0.0019545058
... A101: BMW | B101: X2 | C101: SUV mediano C | D101: 1 | E101: 2 | F101: 1 | G101: 1 | H101: 1 | I101: 0 | J101: 0 | K101: 0 | L101: 0 | M101: 0 | N101: 0 | O101: 0 | P101: =SUM(D101:O101) -> 6 | Q101: =+P101/$P$766 -> 0.00024951137 | R101: - | S101: - | AQ101: Changan CS15 | AR101: TOYOTA | AS101: 4RUNNER | AT101: SUV mediano C | AU101: 45 | AV101: =+AU101/$AU$391 -> 0.0018713353
...

Sheet 9
V1: Referencias
A2: Cuadro 9: Importación de vehículos por tipo, 2026 | V2: Segmento | W2: Modelos. Ejemplos | X2: Capacidad de carga o pasajeros | Y2: Dimensiones
A3: Tipo | B3: Ene | C3: Feb | D3: Mar | E3: Abr | F3: May | G3: Jun | H3: Jul | I3: Ago | J3: Sep | K3: Oct | L3: Nov | M3: Dic | N3: Total | O3: En % | V3: Auto deportivo | W3: Challenger, mustang, slk 200, slk 350 | X3: 2 pasajeros
A4: SUV mediano B | B4: 888 | C4: 953 | D4: 1011 | E4: 1209 | F4: 1139 | G4: 1329 | L4: 0 | M4: 0 | N4: =SUM(B4:M4) -> 6529 | O4: =+N4/$N$26 -> 0.27150996 | V4: Auto Familiar | W4: peugeot 3008, citroen c8 | X4: 7 adultos | Y4: 4,85 mts
A5: SUV mediano C | B5: 864 | C5: 923 | D5: 986 | E5: 1017 | F5: 1018 | G5: 953 | L5: 0 | M5: 0 | N5: =SUM(B5:M5) -> 5761 | O5: =+N5/$N$26 -> 0.2395725 | V5: Auto grande D | W5: kia optima, | X5: 5 adultos | Y5: 4,85 mts
A6: Pick up mediano | B6: 327 | C6: 440 | D6: 624 | E6: 722 | F6: 826 | G6: 408 | L6: 0 | M6: 0 | N6: =SUM(B6:M6) -> 3347 | O6: =+N6/$N$26 -> 0.13918576 | V6: Auto grande F (lujo) | W6: audi A8 BMW serie 7 | Y6: 5 mts
A7: Auto mediano B | B7: 456 | C7: 386 | D7: 425 | E7: 487 | F7: 543 | G7: 723 | L7: 0 | M7: 0 | N7: =SUM(B7:M7) -> 3020 | O7: =+N7/$N$26 -> 0.12558739 | V7: Auto mediano B | W7: Fiat palio, VW gol, Chevrolet Onix, Kia Rio | X7: 4 adultos 1 niño | Y7: 3,75 mts
A8: Pick up pequeño | B8: 177 | C8: 143 | D8: 270 | E8: 517 | F8: 315 | G8: 260 | L8: 0 | M8: 0 | N8: =SUM(B8:M8) -> 1682 | O8: =+N8/$N$26 -> 0.069946355 | V8: Auto mediano C | W8: Toyota corolla, nissan sentra | X8: 5 adultos 2 niño | Y8: 4,30 a 4,50 mts
A9: SUV grande D | B9: 111 | C9: 137 | D9: 297 | E9: 244 | F9: 182 | G9: 252 | L9: 0 | M9: 0 | N9: =SUM(B9:M9) -> 1223 | O9: =+N9/$N$26 -> 0.050858735 | V9: Auto mediano D | W9: Audi a4, citroen c5 | X9: 5 adultos | Y9: 4,85 mts
A10: SUV grande E | B10: 138 | C10: 139 | D10: 208 | E10: 135 | F10: 171 | G10: 252 | L10: 0 | M10: 0 | N10: =SUM(B10:M10) -> 1043 | O10: =+N10/$N$26 -> 0.043373394 | V10: Auto mediano E | W10: Mercedes E500 | X10: 5 adultos | Y10: 4,95 mts
A11: Furgon pequeño | B11: 55 | C11: 40 | D11: 23 | E11: 123 | F11: 20 | G11: 115 | L11: 0 | M11: 0 | N11: =SUM(B11:M11) -> 376 | O11: =+N11/$N$26 -> 0.015636046 | V11: City car | W11: Suzuki celerio, chevrolet spark, Hyundai I10, Kia Picanto | X11: 4 adultos | Y11: 3mts
A12: Pick up grande | B12: 54 | C12: 43 | D12: 45 | E12: 67 | F12: 17 | G12: 65 | L12: 0 | M12: 0 | N12: =SUM(B12:M12) -> 291 | O12: =+N12/$N$26 -> 0.012101302 | V12: Auto pequeño | X12: 4 adultos | Y12: 3,56 mts
A13: SUV mediano D | B13: 30 | C13: 57 | D13: 31 | E13: 40 | F13: 27 | G13: 24 | L13: 0 | M13: 0 | N13: =SUM(B13:M13) -> 209 | O13: =+N13/$N$26 -> 0.0086913128 | V13: Furgon Grande | W13: Ford e350, Renault master, sprinter | X13: 3800 kg | Y13: 5,50 mts
A14: Auto mediano C | B14: 18 | C14: 9 | D14: 12 | E14: 11 | F14: 14 | G14: 84 | L14: 0 | M14: 0 | N14: =SUM(B14:M14) -> 148 | O14: =+N14/$N$26 -> 0.0061546139 | V14: Furgon mediano | W14: Citroen Berlingo | X14: 620 kg | Y14: 4,30mts
A15: City car | B15: 3 | C15: 5 | D15: 36 | E15: 17 | F15: 33 | G15: 27 | L15: 0 | M15: 0 | N15: =SUM(B15:M15) -> 121 | O15: =+N15/$N$26 -> 0.0050318127 | V15: Furgon Pequeño | W15: Renault Kangoo | X15: 550 kg | Y15: 4 mts
A16: Minibus | B16: 5 | C16: 28 | D16: 14 | E16: 15 | F16: 12 | G16: 6 | L16: 0 | M16: 0 | N16: =SUM(B16:M16) -> 80 | O16: =+N16/$N$26 -> 0.0033268183 | V16: Minibus | W16: Mercedes Sprinter | X16: 20 pasajeros
A17: Furgon Grande | B17: 20 | C17: 6 | D17: 20 | E17: 5 | F17: 12 | G17: 9 | L17: 0 | M17: 0 | N17: =SUM(B17:M17) -> 72 | O17: =+N17/$N$26 -> 0.0029941365 | V17: Pick up grande | W17: Dodge Ram, Ford F150, Toyota Tundra | X17: de 1000 a 3500 kg
A18: SUV grande F | B18: 21 | C18: 5 | D18: 12 | E18: 5 | F18: 8 | G18: 8 | L18: 0 | M18: 0 | N18: =SUM(B18:M18) -> 59 | O18: =+N18/$N$26 -> 0.0024535285 | V18: Pick up mediano | W18: Toyota Hilux. Nissan Frontier, Isuzu D-MAX | X18: 1,5 toneladas
A19: Auto Familiar | B19: 29 | C19: 2 | D19: 18 | E19: 2 | F19: 1 | G19: 2 | N19: =SUM(B19:M19) -> 54 | O19: =+N19/$N$26 -> 0.0022456024 | V19: Pick up pequeño | W19: VW saveiro, ford courrier, Chev montana | X19: de 700 a 750 kg
A20: Auto deportivo | B20: 0 | C20: 3 | D20: 6 | E20: 5 | F20: 2 | G20: 2 | L20: 0 | M20: 0 | N20: =SUM(B20:M20) -> 18 | O20: =+N20/$N$26 -> 0.00074853412 | V20: SUV Grande D | W20: Hyundai Santa Fe, Toyota Fortuner | X20: 5 adultos | Y20: 4,5 mts
A21: Auto grande E | B21: 3 | C21: 0 | D21: 0 | E21: 1 | F21: 0 | G21: 0 | L21: 0 | M21: 0 | N21: =SUM(B21:M21) -> 4 | O21: =+N21/$N$26 -> 0.00016634092 | V21: SUV grande E | W21: Ford Explorer, Toyota Land Cruiser | X21: 7 pasajeros | Y21: 4,8 mts
A22: Furgon mediano | B22: 4 | C22: 0 | D22: 0 | E22: 0 | F22: 0 | G22: 0 | N22: =SUM(B22:M22) -> 4 | O22: =+N22/$N$26 -> 0.00016634092
A23: Auto grande F | B23: 2 | C23: 0 | D23: 0 | E23: 0 | F23: 0 | G23: 1 | L23: 0 | M23: 0 | N23: =SUM(B23:M23) -> 3 | O23: =+N23/$N$26 -> 0.00012475569
A24: No ident. | B24: 0 | C24: 0 | D24: 0 | E24: 2 | F24: 0 | G24: 0 | L24: 0 | M24: 0 | N24: =SUM(B24:M24) -> 2 | O24: =+N24/$N$26 -> 8.3170458e-05
A25: Auto grande D | B25: 0 | C25: 0 | D25: 0 | E25: 0 | F25: 1 | G25: 0 | L25: 0 | M25: 0 | N25: =SUM(B25:M25) -> 1 | O25: =+N25/$N$26 -> 4.1585229e-05
A26: Total | B26: =SUM(B4:B25) -> 3205 | C26: =SUM(C4:C25) -> 3319 | D26: =SUM(D4:D25) -> 4038 | E26: =SUM(E4:E25) -> 4624 | F26: =SUM(F4:F25) -> 4341 | G26: =SUM(G4:G25) -> 4520 | H26: =SUM(H4:H25) -> 0 | I26: =SUM(I4:I25) -> 0 | ... O26: =SUM(O4:O25) -> 1
A34: Cuadro 9A: Importación de vehiculos por segmento, 2026
A35: Automóviles | B35: Ene | C35: Feb | D35: Mar | E35: Abr | F35: May | G35: Jun | H35: Jul | I35: Ago | J35: Sep | K35: Oct | L35: Nov | M35: Dic | N35: Total | O35: En %
A36: Auto mediano B | B36: 456 | C36: 386 | D36: 425 | E36: 487 | F36: 543 | G36: 723 | L36: 0 | M36: 0 | N36: =SUM(B36:M36) -> 3020 | O36: =+N36/$N$44 -> 0.89640843
A37: Auto mediano C | B37: 18 | C37: 9 | D37: 12 | E37: 11 | F37: 14 | G37: 84 | L37: 0 | M37: 0 | N37: =SUM(B37:M37) -> 148 | O37: =+N37/$N$44 -> 0.04392995 | V37: SUV mediano C | W37: Toyota Rav 4, Captiva, Nissan Murano | X37: 5 adultos 2 niños | Y37: 4,50 mts
A38: City car | B38: 3 | C38: 5 | D38: 36 | E38: 17 | F38: 33 | G38: 27 | L38: 0 | M38: 0 | N38: =SUM(B38:M38) -> 121 | O38: =+N38/$N$44 -> 0.035915702
A39: Auto Familiar | B39: 29 | C39: 2 | D39: 18 | E39: 2 | F39: 1 | G39: 2 | L39: 0 | M39: 0 | N39: =SUM(B39:M39) -> 54 | O39: =+N39/$N$44 -> 0.016028495
A40: Auto deportivo | B40: 0 | C40: 3 | D40: 6 | E40: 5 | F40: 2 | G40: 2 | L40: 0 | M40: 0 | N40: =SUM(B40:M40) -> 18 | O40: =+N40/$N$44 -> 0.0053428317
A41: Auto grande E | B41: 3 | C41: 0 | D41: 0 | E41: 1 | F41: 0 | G41: 0 | L41: 0 | M41: 0 | N41: =SUM(B41:M41) -> 4 | O41: =+N41/$N$44 -> 0.0011872959
A42: Auto grande F | B42: 2 | C42: 0 | D42: 0 | E42: 0 | F42: 0 | G42: 1 | L42: 0 | M42: 0 | N42: =SUM(B42:M42) -> 3 | O42: =+N42/$N$44 -> 0.00089047195
A43: Auto grande D | B43: 0 | C43: 0 | D43: 0 | E43: 0 | F43: 1 | G43: 0 | L43: 0 | M43: 0 | N43: =SUM(B43:M43) -> 1 | O43: =+N43/$N$44 -> 0.00029682398
A44: Total | B44: =SUM(B36:B43) -> 511 | C44: =SUM(C36:C43) -> 405 | D44: =SUM(D36:D43) -> 497 | E44: =SUM(E36:E43) -> 523 | F44: =SUM(F36:F43) -> 594 | G44: =SUM(G36:G43) -> 839 | H44: =SUM(H36:H43) -> 0 | I44: =SUM(I36:I43) -> 0 | ... O44: =SUM(O36:O43) -> 1
A48: Pick Up | B48: Ene | C48: Feb | D48: Mar | E48: Abr | F48: May | G48: Jun | H48: Jul | I48: Ago | J48: Sep | K48: Oct | L48: Nov | M48: Dic | N48: Total | O48: En %
A49: Pick up mediano | B49: 327 | C49: 440 | D49: 624 | E49: 722 | F49: 826 | G49: 408 | L49: 0 | M49: 0 | N49: =SUM(B49:M49) -> 3347 | O49: =+N49/$N$52 -> 0.62913534
A50: Pick up pequeño | B50: 177 | C50: 143 | D50: 270 | E50: 517 | F50: 315 | G50: 260 | L50: 0 | M50: 0 | N50: =SUM(B50:M50) -> 1682 | O50: =+N50/$N$52 -> 0.31616541
A51: Pick up grande | B51: 54 | C51: 43 | D51: 45 | E51: 67 | F51: 17 | G51: 65 | L51: 0 | M51: 0 | N51: =SUM(B51:M51) -> 291 | O51: =+N51/$N$52 -> 0.054699248
A52: Total | B52: =SUM(B49:B51) -> 558 | C52: =SUM(C49:C51) -> 626 | D52: =SUM(D49:D51) -> 939 | E52: =SUM(E49:E51) -> 1306 | F52: =SUM(F49:F51) -> 1158 | G52: =SUM(G49:G51) -> 733 | H52: =SUM(H49:H51) -> 0 | I52: =SUM(I49:I51) -> 0 | ... N52: =SUM(N49:N51) -> 5320 | O52: =+N52/$N$52% -> 100
A54: SUV | B54: Ene | C54: Feb | D54: Mar | E54: Abr | F54: May | G54: Jun | H54: Jul | I54: Ago | J54: Sep | K54: Oct | L54: Nov | M54: Dic | N54: Total | O54: En %
A55: SUV mediano B | B55: 888 | C55: 953 | D55: 1011 | E55: 1209 | F55: 1139 | G55: 1329 | L55: 0 | M55: 0 | N55: =SUM(B55:M55) -> 6529 | O55: =+N55/$N$61% -> 44.043443
A56: SUV mediano C | B56: 864 | C56: 923 | D56: 986 | E56: 1017 | F56: 1018 | G56: 953 | L56: 0 | M56: 0 | N56: =SUM(B56:M56) -> 5761 | O56: =+N56/$N$61% -> 38.862655
A57: SUV grande D | B57: 111 | C57: 137 | D57: 297 | E57: 244 | F57: 182 | G57: 252 | L57: 0 | M57: 0 | N57: =SUM(B57:M57) -> 1223 | O57: =+N57/$N$61% -> 8.2501349
A58: SUV grande E | B58: 138 | C58: 139 | D58: 208 | E58: 135 | F58: 171 | G58: 252 | L58: 0 | M58: 0 | N58: =SUM(B58:M58) -> 1043 | O58: =+N58/$N$61% -> 7.0358877
A59: SUV mediano D | B59: 30 | C59: 57 | D59: 31 | E59: 40 | F59: 27 | G59: 24 | L59: 0 | M59: 0 | N59: =SUM(B59:M59) -> 209 | O59: =+N59/$N$61% -> 1.4098759
A60: SUV grande F | B60: 21 | C60: 5 | D60: 12 | E60: 5 | F60: 8 | G60: 8 | L60: 0 | M60: 0 | N60: =SUM(B60:M60) -> 59 | O60: =+N60/$N$61% -> 0.39800324
A61: Total | B61: =SUM(B55:B60) -> 2052 | C61: =SUM(C55:C60) -> 2214 | D61: =SUM(D55:D60) -> 2545 | E61: =SUM(E55:E60) -> 2650 | F61: =SUM(F55:F60) -> 2545 | G61: =SUM(G55:G60) -> 2818 | H61: =SUM(H55:H60) -> 0 | I61: =SUM(I55:I60) -> 0 | ... N61: =SUM(N55:N60) -> 14824 | O61: =+N61/$N$61% -> 100
A63: Furgón | B63: Ene | C63: Feb | D63: Mar | E63: Abr | F63: May | G63: Jun | H63: Jul | I63: Ago | J63: Sep | K63: Oct | L63: Nov | M63: Dic | N63: Total | O63: En %
A64: Furgon pequeño | B64: 55 | C64: 40 | D64: 23 | E64: 123 | F64: 20 | G64: 115 | L64: 0 | M64: 0 | N64: =SUM(B64:M64) -> 376 | O64: =+N64/$N$67% -> 83.185841
A65: Furgon Grande | B65: 20 | C65: 6 | D65: 20 | E65: 5 | F65: 12 | G65: 9 | L65: 0 | M65: 0 | N65: =SUM(B65:M65) -> 72 | O65: =+N65/$N$67% -> 15.929204
A66: Furgon mediano | B66: 4 | C66: 0 | D66: 0 | E66: 0 | F66: 0 | G66: 0 | L66: 0 | M66: 0 | N66: =SUM(B66:M66) -> 4 | O66: =+N66/$N$67% -> 0.88495575
A67: Total | B67: =SUM(B64:B66) -> 79 | C67: =SUM(C64:C66) -> 46 | D67: =SUM(D64:D66) -> 43 | E67: =SUM(E64:E66) -> 128 | F67: =SUM(F64:F66) -> 32 | G67: =SUM(G64:G66) -> 124 | H67: =SUM(H64:H66) -> 0 | I67: =SUM(I64:I66) -> 0 | ... O67: =SUM(O64:O66) -> 100
A69: Varios | B69: Ene | C69: Feb | D69: Mar | E69: Abr | F69: May | G69: Jun | H69: Jul | I69: Ago | J69: Sep | K69: Oct | L69: Nov | M69: Dic | N69: Total | O69: En %
A70: Minibus | B70: 5 | C70: 28 | D70: 14 | E70: 15 | F70: 12 | G70: 6 | L70: 0 | M70: 0 | N70: =SUM(B70:M70) -> 80 | O70: =+N70/$N$72% -> 97.560976
A71: No ident. | B71: 0 | C71: 0 | D71: 0 | E71: 2 | F71: 0 | G71: 0 | L71: 0 | M71: 0 | N71: =SUM(B71:M71) -> 2 | O71: =+N71/$N$72% -> 2.4390244
A72: Total | B72: =SUM(B70:B71) -> 5 | C72: =SUM(C70:C71) -> 28 | D72: =SUM(D70:D71) -> 14 | E72: =SUM(E70:E71) -> 17 | F72: =SUM(F70:F71) -> 12 | G72: =SUM(G70:G71) -> 6 | H72: =SUM(H70:H71) -> 0 | I72: =SUM(I70:I71) -> 0 | ... N72: =SUM(N70:N71) -> 82 | O72: =SUM(O70:O70) -> 97.560976
A74: Total | N74: =+N44+N52+N61+N67+N72 -> 24047
A77: Tipo | B77: Ene | C77: Feb | D77: Mar | E77: Abr | F77: May | G77: Jun | H77: Jul | I77: Ago | J77: Sep | K77: Oct | L77: Nov | M77: Dic | N77: Total | O77: En %
A78: =+A35 -> Automóviles | B78: =+B44 -> 511 | C78: =+C44 -> 405 | D78: =+D44 -> 497 | E78: =+E44 -> 523 | F78: =+F44 -> 594 | G78: =+G44 -> 839 | H78: =+H44 -> 0 | I78: =+I44 -> 0 | ... N78: =+N44 -> 3369 | O78: =+N78/$N$83% -> 14.010064
A79: =+A48 -> Pick Up | B79: =+B52 -> 558 | C79: =+C52 -> 626 | D79: =+D52 -> 939 | E79: =+E52 -> 1306 | F79: =+F52 -> 1158 | G79: =+G52 -> 733 | H79: =+H52 -> 0 | I79: =+I52 -> 0 | ... N79: =+N52 -> 5320 | O79: =+N79/$N$83% -> 22.123342
A80: =+A54 -> SUV | B80: =+B61 -> 2052 | C80: =+C61 -> 2214 | D80: =+D61 -> 2545 | E80: =+E61 -> 2650 | F80: =+F61 -> 2545 | G80: =+G61 -> 2818 | H80: =+H61 -> 0 | I80: =+I61 -> 0 | ... N80: =+N61 -> 14824 | O80: =+N80/$N$83% -> 61.645943
A81: =+A63 -> Furgón | B81: =+B67 -> 79 | C81: =+C67 -> 46 | D81: =+D67 -> 43 | E81: =+E67 -> 128 | F81: =+F67 -> 32 | G81: =+G67 -> 124 | H81: =+H67 -> 0 | I81: =+I67 -> 0 | ... N81: =+N67 -> 452 | O81: =+N81/$N$83% -> 1.8796523
A82: Otros automoviles | B82: =+B72 -> 5 | C82: =+C72 -> 28 | D82: =+D72 -> 14 | E82: =+E72 -> 17 | F82: =+F72 -> 12 | G82: =+G72 -> 6 | H82: =+H72 -> 0 | I82: =+I72 -> 0 | ... N82: =+N72 -> 82 | O82: =+N82/$N$83% -> 0.34099888
A83: Total | B83: =SUM(B78:B82) -> 3205 | C83: =SUM(C78:C82) -> 3319 | D83: =SUM(D78:D82) -> 4038 | E83: =SUM(E78:E82) -> 4624 | F83: =SUM(F78:F82) -> 4341 | G83: =SUM(G78:G82) -> 4520 | H83: =SUM(H78:H82) -> 0 | I83: =SUM(I78:I82) -> 0 | ... O83: =SUM(O78:O82) -> 100
A85: Cuadro 9A: Importación de vehiculos por segmento. Crecimiento, 2025-2026
A86: Automoviles | B86: 2025 | C86: 2026 | D86: Crecimiento 2026/2025 | E86: Part. % 2026
A88: Auto mediano B | B88: 2492 | C88: 3020 | D88: =+C88/B88-1 -> 0.21187801 | E88: =+C88/$C$96 -> 0.89640843
A89: City car | B89: 532 | C89: 121 | D89: =+C89/B89-1 -> -0.77255639 | E89: =+C89/$C$96 -> 0.035915702
A90: Auto mediano C | B90: 110 | C90: 148 | D90: =+C90/B90-1 -> 0.34545455 | E90: =+C90/$C$96 -> 0.04392995
A91: Auto Familiar | B91: 88 | C91: 54 | D91: =+C91/B91-1 -> -0.38636364 | E91: =+C91/$C$96 -> 0.016028495
A92: Auto deportivo | B92: 18 | C92: 18 | D92: =+C92/B92-1 -> 0 | E92: =+C92/$C$96 -> 0.0053428317
A93: Auto grande E | B93: 1 | C93: 4 | D93: =+C93/B93-1 -> 3 | E93: =+C93/$C$96 -> 0.0011872959
A94: Auto grande F | B94: 0 | C94: 3 | D94: =+C94/B94-1 -> #DIV/0! | E94: =+C94/$C$96 -> 0.00089047195
A95: Auto grande D | B95: 0 | C95: 1 | D95: =+C95/B95-1 -> #DIV/0! | E95: =+C95/$C$96 -> 0.00029682398
A96: Total | B96: =SUM(B88:B95) -> 3241 | C96: =SUM(C88:C95) -> 3369 | D96: =+C96/B96-1 -> 0.039493983 | E96: =SUM(E88:E95) -> 1
A98: Pick Up | B98: 2025 | C98: 2026 | D98: Crecimiento 2026/2025 | E98: Part. % 2026
A100: Pick up mediano | B100: 2725 | C100: 3347 | D100: =+C100/B100-1 -> 0.22825688 | E100: =+C100/$C$103 -> 0.62913534
A101: Pick up pequeño | B101: 856 | C101: 1682 | D101: =+C101/B101-1 -> 0.96495327 | E101: =+C101/$C$103 -> 0.31616541
A102: Pick up grande | B102: 207 | C102: 291 | D102: =+C102/B102-1 -> 0.4057971 | E102: =+C102/$C$103 -> 0.054699248
A103: Total pick up | B103: =SUM(B100:B102) -> 3788 | C103: =SUM(C100:C102) -> 5320 | D103: =+C103/B103-1 -> 0.40443506 | E103: =SUM(E100:E102) -> 1
A105: SUV | B105: 2025 | C105: 2026 | D105: Crecimiento 2026/2025 | E105: Part. % 2026
A107: SUV mediano C | B107: 3935 | C107: 5761 | D107: =+C107/B107-1 -> 0.46404066 | E107: =+C107/$C$113 -> 0.38862655
A108: SUV mediano B | B108: 3612 | C108: 6529 | D108: =+C108/B108-1 -> 0.80758583 | E108: =+C108/$C$113 -> 0.44043443
A109: SUV grande D | B109: 782 | C109: 1223 | D109: =+C109/B109-1 -> 0.56393862 | E109: =+C109/$C$113 -> 0.082501349
A110: SUV grande E | B110: 768 | C110: 1043 | D110: =+C110/B110-1 -> 0.35807292 | E110: =+C110/$C$113 -> 0.070358877
A111: SUV mediano D | B111: 150 | C111: 209 | D111: =+C111/B111-1 -> 0.39333333 | E111: =+C111/$C$113 -> 0.014098759
A112: SUV grande F | B112: 51 | C112: 59 | D112: =+C112/B112-1 -> 0.15686275 | E112: =+C112/$C$113 -> 0.0039800324
A113: Total SUV | B113: =SUM(B107:B112) -> 9298 | C113: =SUM(C107:C112) -> 14824 | D113: =+C113/B113-1 -> 0.59432136 | E113: =SUM(E107:E112) -> 1
A115: Furgon | B115: 2025 | C115: 2026 | D115: Crecimiento 2026/2025 | E115: Part. % 2026
A117: Furgon pequeño | B117: 251 | C117: 376 | D117: =+C117/B117-1 -> 0.49800797 | E117: =+C117/$C$120 -> 0.83185841
A118: Furgon grande | B118: 127 | C118: 72 | D118: =+C118/B118-1 -> -0.43307087 | E118: =+C118/$C$120 -> 0.15929204
A119: Furgon mediano | B119: 43 | C119: 4 | D119: =+C119/B119-1 -> -0.90697674 | E119: =+C119/$C$120 -> 0.0088495575
A120: Total Furgon | B120: =SUM(B117:B119) -> 421 | C120: =SUM(C117:C119) -> 452 | D120: =+C120/B120-1 -> 0.073634204 | E120: =SUM(E117:E119) -> 1
A122: Minibus | B122: 2025 | C122: 2026 | D122: Crecimiento 2026/2025 | E122: Part. % 2026
A124: Minibus | B124: 101 | C124: 80 | D124: =+C124/B124-1 -> -0.20792079 | E124: =+C124/$C$126 -> 0.97560976
A125: No ident. | B125: 1 | C125: 2 | D125: 1 | E125: =+C125/$C$126 -> 0.024390244
A126: Total varios | B126: =SUM(B124:B125) -> 102 | C126: =SUM(C124:C125) -> 82 | D126: =+C126/B126-1 -> -0.19607843 | E126: =SUM(E124:E125) -> 1
...

Sheet 10
A1: Cuadro 10A: Importaciones por tipo de combustibles y movilidad, por mes, 2026
A2: Meses/Tipo de vehiculos | B2: Nafta | D2: Diesel | F2: Flex | H2: Híbrido | J2: Eléctrico | L2: Total
B3: Unid. | C3: % | D3: Unid. | E3: % | F3: Unid. | G3: % | H3: Unid. | I3: % | J3: Unid. | K3: % | L3: Unid. | M3: %
A4: Enero | B4: =SUM(B5:B9) -> 1343 | C4: =+B4/L4 -> 0.41903276 | D4: =SUM(D5:D9) -> 635 | E4: =+D4/L4 -> 0.19812793 | F4: =SUM(F5:F9) -> 743 | G4: =+F4/L4 -> 0.23182527 | H4: =SUM(H5:H9) -> 441 | I4: =+H4/L4 -> 0.1375975 | J4: =SUM(J5:J9) -> 43 | K4: =+J4/L4 -> 0.013416537 | L4: =SUM(L5:L9) -> 3205 | M4: =+C4+E4+G4+I4+K4 -> 1
A5: Automovil | B5: 347 | C5: =+B5/L5 -> 0.79405034 | D5: 1 | E5: =+D5/L5 -> 0.0022883295 | F5: 65 | G5: =+F5/L5 -> 0.14874142 | H5: 11 | I5: =+H5/$L$5 -> 0.025171625 | J5: 13 | K5: =+J5/$L$5 -> 0.029748284 | L5: =+B5+D5+F5+H5+J5 -> 437 | M5: =+C5+E5+G5+I5+K5 -> 1
A6: Furgon | B6: 0 | C6: =+B6/L6 -> 0 | D6: 20 | E6: =+D6/L6 -> 0.31746032 | F6: 41 | G6: =+F6/L6 -> 0.65079365 | H6: 0 | I6: =+H6/$L$6 -> 0 | J6: 2 | K6: =+J6/$L$6 -> 0.031746032 | L6: =+B6+D6+F6+H6+J6 -> 63 | M6: =+C6+E6+G6+I6+K6 -> 1
A7: Mnibus | B7: 12 | C7: =+B7/L7 -> 0.26086957 | D7: 9 | E7: =+D7/L7 -> 0.19565217 | F7: 0 | G7: =+F7/L7 -> 0 | H7: 25 | I7: =+H7/$L$7 -> 0.54347826 | J7: 0 | K7: =+J7/$L$7 -> 0 | L7: =+B7+D7+F7+H7+J7 -> 46 | M7: =+C7+E7+G7+I7+K7 -> 1
A8: Pick Up | B8: 0 | C8: =+B8/L8 -> 0 | D8: 299 | E8: =+D8/L8 -> 0.53680431 | F8: 235 | G8: =+F8/L8 -> 0.42190305 | H8: 23 | I8: =+H8/$L$8 -> 0.041292639 | J8: 0 | K8: =+J8/$L$8 -> 0 | L8: =+B8+D8+F8+H8+J8 -> 557 | M8: =+C8+E8+G8+I8+K8 -> 1
A9: SUV | B9: =947+37 -> 984 | C9: =+B9/L9 -> 0.46812559 | D9: 306 | E9: =+D9/L9 -> 0.14557564 | F9: 402 | G9: =+F9/L9 -> 0.19124643 | H9: 382 | I9: =+H9/$L$9 -> 0.18173168 | J9: 28 | K9: =+J9/$L$9 -> 0.013320647 | L9: =+B9+D9+F9+H9+J9 -> 2102 | M9: =+C9+E9+G9+I9+K9 -> 1
A10: Febrero | B10: =SUM(B11:B15) -> 1596 | C10: =+B10/L10 -> 0.48086773 | D10: =SUM(D11:D15) -> 704 | E10: =+D10/L10 -> 0.21211208 | F10: =SUM(F11:F15) -> 555 | G10: =+F10/L10 -> 0.16721904 | H10: =SUM(H11:H15) -> 375 | I10: =+H10/L10 -> 0.11298584 | J10: =SUM(J11:J15) -> 89 | K10: =+J10/L10 -> 0.026815306 | L10: =SUM(L11:L15) -> 3319 | M10: =+C10+E10+G10+I10+K10 -> 1
A11: Automovil | B11: 258 | C11: =+B11/L11 -> 0.69541779 | D11: 0 | E11: =+D11/L11 -> 0 | F11: 82 | G11: =+F11/L11 -> 0.22102426 | H11: 6 | I11: =+H11/$L$11 -> 0.016172507 | J11: 25 | K11: =+J11/$L$11 -> 0.067385445 | L11: =+B11+D11+F11+H11+J11 -> 371 | M11: =+C11+E11+G11+I11+K11 -> 1
A12: Furgon | B12: 0 | C12: =+B12/L12 -> 0 | D12: 6 | E12: =+D12/L12 -> 0.125 | F12: 40 | G12: =+F12/L12 -> 0.83333333 | H12: 0 | I12: =+H12/$L$12 -> 0 | J12: 2 | K12: =+J12/$L$12 -> 0.041666667 | L12: =+B12+D12+F12+H12+J12 -> 48 | M12: =+C12+E12+G12+I12+K12 -> 1
A13: Mnibus | B13: 5 | C13: =+B13/L13 -> 0.19230769 | D13: 21 | E13: =+D13/L13 -> 0.80769231 | F13: 0 | G13: =+F13/L13 -> 0 | H13: 0 | I13: =+H13/$L$13 -> 0 | J13: 0 | K13: =+J13/$L$13 -> 0 | L13: =+B13+D13+F13+H13+J13 -> 26 | M13: =+C13+E13+G13+I13+K13 -> 1
A14: Pick Up | B14: 1 | C14: =+B14/L14 -> 0.0015948963 | D14: 427 | E14: =+D14/L14 -> 0.68102073 | F14: 176 | G14: =+F14/L14 -> 0.28070175 | H14: 16 | I14: =+H14/$L$14 -> 0.025518341 | J14: 7 | K14: =+J14/$L$14 -> 0.011164274 | L14: =+B14+D14+F14+H14+J14 -> 627 | M14: =+C14+E14+G14+I14+K14 -> 1
A15: SUV | B15: 1332 | C15: =+B15/L15 -> 0.59279039 | D15: 250 | E15: =+D15/L15 -> 0.11125946 | F15: 257 | G15: =+F15/L15 -> 0.11437472 | H15: 353 | I15: =+H15/$L$15 -> 0.15709835 | J15: 55 | K15: =+J15/$L$15 -> 0.024477081 | L15: =+B15+D15+F15+H15+J15 -> 2247 | M15: =+C15+E15+G15+I15+K15 -> 1
A16: Marzo | B16: =SUM(B17:B21) -> 1377 | C16: =+B16/L16 -> 0.3410104 | D16: =SUM(D17:D21) -> 871 | E16: =+D16/L16 -> 0.21570084 | F16: =SUM(F17:F21) -> 993 | G16: =+F16/L16 -> 0.24591382 | H16: =SUM(H17:H21) -> 637 | I16: =+H16/L16 -> 0.15775136 | J16: =SUM(J17:J21) -> 160 | K16: =+J16/L16 -> 0.039623576 | L16: =SUM(L17:L21) -> 4038 | M16: =+C16+E16+G16+I16+K16 -> 1
A17: Automovil | B17: 290 | C17: =+B17/L17 -> 0.69212411 | D17: 0 | E17: =+D17/L17 -> 0 | F17: 83 | G17: =+F17/L17 -> 0.19809069 | H17: 12 | I17: =+H17/$L$17 -> 0.028639618 | J17: 34 | K17: =+J17/$L$17 -> 0.081145585 | L17: =+B17+D17+F17+H17+J17 -> 419 | M17: =+C17+E17+G17+I17+K17 -> 1
A18: Furgon | B18: 0 | C18: =+B18/L18 -> 0 | D18: 8 | E18: =+D18/L18 -> 0.23529412 | F18: 18 | G18: =+F18/L18 -> 0.52941176 | H18: 0 | I18: =+H18/$L$17 -> 0 | J18: 8 | K18: =+J18/$L$18 -> 0.23529412 | L18: =+B18+D18+F18+H18+J18 -> 34 | M18: =+C18+E18+G18+I18+K18 -> 1
A19: Mnibus | B19: 2 | C19: =+B19/L19 -> 0.057142857 | D19: 15 | E19: =+D19/L19 -> 0.42857143 | F19: 0 | G19: =+F19/L19 -> 0 | H19: 16 | I19: =+H19/$L$17 -> 0.038186158 | J19: 2 | K19: =+J19/$L$19 -> 0.057142857 | L19: =+B19+D19+F19+H19+J19 -> 35 | M19: =+C19+E19+G19+I19+K19 -> 0.5810433
A20: Pick Up | B20: 0 | C20: =+B20/L20 -> 0 | D20: 645 | E20: =+D20/L20 -> 0.68763326 | F20: 288 | G20: =+F20/L20 -> 0.30703625 | H20: 5 | I20: =+H20/$L$17 -> 0.011933174 | J20: 0 | K20: =+J20/$L$20 -> 0 | L20: =+B20+D20+F20+H20+J20 -> 938 | M20: =+C20+E20+G20+I20+K20 -> 1.0066027
A21: SUV | B21: 1085 | C21: =+B21/L21 -> 0.41539051 | D21: 203 | E21: =+D21/L21 -> 0.077718224 | F21: 604 | G21: =+F21/L21 -> 0.23124043 | H21: 604 | I21: =+H21/$L$21 -> 0.23124043 | J21: 116 | K21: =+J21/$L$21 -> 0.044410413 | L21: =+B21+D21+F21+H21+J21 -> 2612 | M21: =+C21+E21+G21+I21+K21 -> 1
A22: Abril | B22: =SUM(B23:B27) -> 1594 | C22: =+B22/L22 -> 0.34472318 | D22: =SUM(D23:D27) -> 918 | E22: =+D22/L22 -> 0.19852941 | F22: =SUM(F23:F27) -> 1342 | G22: =+F22/L22 -> 0.29022491 | H22: =SUM(H23:H27) -> 678 | I22: =+H22/$L$22 -> 0.1466263 | J22: =SUM(J23:J27) -> 92 | K22: =+J22/L22 -> 0.019896194 | L22: =SUM(L23:L27) -> 4624 | M22: =+C22+E22+G22+I22+K22 -> 1
A23: Automovil | B23: 357 | C23: =+B23/L23 -> 0.78634361 | E23: =+D23/L23 -> 0 | F23: 77 | G23: =+F23/L23 -> 0.16960352 | H23: 8 | I23: =+H23/L$23 -> 0.017621145 | J23: 12 | K23: =+J23/$L$23 -> 0.026431718 | L23: =B23+D23+F23+H23+J23 -> 454 | M23: =+C23+E23+G23+I23+K23 -> 1
A24: Furgon | C24: =+B24/L24 -> 0 | D24: 5 | E24: =+D24/L24 -> 0.03875969 | F24: 123 | G24: =+F24/L24 -> 0.95348837 | H24: 0 | I24: =+H24/$L$24 -> 0 | J24: 1 | K24: =+J24/$L$24 -> 0.007751938 | L24: =B24+D24+F24+H24+J24 -> 129 | M24: =+C24+E24+G24+I24+K24 -> 1
A25: Mnibus | B25: 5 | C25: =+B25/L25 -> 0.35714286 | D25: 8 | E25: =+D25/L25 -> 0.57142857 | G25: =+F25/L25 -> 0 | H25: 0 | I25: =+H25/$L$25 -> 0 | J25: 1 | K25: =+J25/$L$25 -> 0.071428571 | L25: =B25+D25+F25+H25+J25 -> 14 | M25: =+C25+E25+G25+I25+K25 -> 1
A26: Pick Up | C26: =+B26/L26 -> 0 | D26: 754 | E26: =+D26/L26 -> 0.57866462 | F26: 535 | G26: =+F26/L26 -> 0.41059094 | H26: 14 | I26: =+H26/$L$26 -> 0.010744436 | K26: =+J26/$L$26 -> 0 | L26: =B26+D26+F26+H26+J26 -> 1303 | M26: =+C26+E26+G26+I26+K26 -> 1
A27: SUV | B27: 1232 | C27: =+B27/L27 -> 0.45227606 | D27: 151 | E27: =+D27/L27 -> 0.055433186 | F27: 607 | G27: =+F27/L27 -> 0.22283407 | H27: 656 | I27: =+H27/$L$27 -> 0.24082232 | J27: 78 | K27: =+J27/$L$27 -> 0.028634361 | L27: =B27+D27+F27+H27+J27 -> 2724 | M27: =+C27+E27+G27+I27+K27 -> 1
A28: Mayo | B28: =SUM(B29:B33) -> 1495 | C28: =+B28/L28 -> 0.34439069 | D28: =SUM(D29:D33) -> 1043 | E28: =+D28/L28 -> 0.24026722 | F28: =SUM(F29:F33) -> 996 | G28: =+F28/L28 -> 0.22944022 | H28: =SUM(H29:H33) -> 635 | I28: =+H28/L28 -> 0.14627966 | J28: =SUM(J29:J33) -> 172 | K28: =+J28/L28 -> 0.039622207 | L28: =B28+D28+F28+H28+J28 -> 4341 | M28: =+C28+E28+G28+I28+K28 -> 1
A29: Automovil | B29: 390 | C29: =+B29/L29 -> 0.7027027 | D29: 0 | E29: =+D29/L29 -> 0 | F29: 116 | G29: =+F29/L29 -> 0.20900901 | H29: 2 | I29: =+H29/$L$29 -> 0.0036036036 | J29: 47 | K29: =+J29/$L$29 -> 0.084684685 | L29: =B29+D29+F29+H29+J29 -> 555 | M29: =+C29+E29+G29+I29+K29 -> 1
A30: Furgon | B30: 0 | C30: =+B30/L30 -> 0 | D30: 10 | E30: =+D30/L30 -> 0.32258065 | F30: 20 | G30: =+F30/L30 -> 0.64516129 | H30: 0 | I30: =+H30/$L$30 -> 0 | J30: 1 | K30: =+J30/L30 -> 0.032258065 | L30: =B30+D30+F30+H30+J30 -> 31 | M30: =+C30+E30+G30+I30+K30 -> 1
A31: Mnibus | B31: 0 | C31: =+B31/L31 -> 0 | D31: 10 | E31: =+D31/L31 -> 1 | F31: 0 | G31: =+F31/L31 -> 0 | H31: 0 | I31: =+H31/$L$31 -> 0 | J31: 0 | K31: =+J31/$L$31 -> 0 | L31: =B31+D31+F31+H31+J31 -> 10 | M31: =+C31+E31+G31+I31+K31 -> 1
A32: Pick Up | B32: 0 | C32: =+B32/L32 -> 0 | D32: 819 | E32: =+D32/L32 -> 0.70786517 | F32: 326 | G32: =+F32/L32 -> 0.28176318 | H32: 12 | I32: =+H32/$L$32 -> 0.010371651 | J32: 0 | K32: =+J32/$L$32 -> 0 | L32: =B32+D32+F32+H32+J32 -> 1157 | M32: =+C32+E32+G32+I32+K32 -> 1
A33: SUV | B33: 1105 | C33: =+B33/L33 -> 0.42697063 | D33: 204 | E33: =+D33/L33 -> 0.078825348 | F33: 534 | G33: =+F33/L33 -> 0.20633694 | H33: 621 | I33: =+H33/$L$33 -> 0.23995363 | J33: 124 | K33: =+J33/$L$33 -> 0.047913447 | L33: =B33+D33+F33+H33+J33 -> 2588 | M33: =+C33+E33+G33+I33+K33 -> 1
A34: Junio | B34: =SUM(B35:B39) -> 1809 | C34: =+B34/L34 -> 0.40022124 | D34: =SUM(D35:D39) -> 690 | E34: =+D34/L34 -> 0.15265487 | F34: =SUM(F35:F39) -> 1263 | G34: =+F34/L34 -> 0.27942478 | H34: =SUM(H35:H39) -> 649 | I34: =+H34/L34 -> 0.14358407 | J34: =SUM(J35:J39) -> 109 | K34: =+J34/L34 -> 0.024115044 | L34: =SUM(L35:L39) -> 4520 | M34: =+C34+E34+G34+I34+K34 -> 1
A35: Automovil | B35: 462 | C35: =+B35/L35 -> 0.62096774 | D35: 0 | E35: =+D35/L35 -> 0 | F35: 180 | G35: =+F35/L35 -> 0.24193548 | H35: 74 | I35: =+H35/$L$35 -> 0.099462366 | J35: 28 | K35: =+J35/$L$35 -> 0.037634409 | L35: =B35+D35+F35+H35+J35 -> 744 | M35: =+C35+E35+G35+I35+K35 -> 1
A36: Furgon | B36: 0 | C36: =+B36/L36 -> 0 | D36: 5 | E36: =+D36/L36 -> 0.041322314 | F36: 112 | G36: =+F36/L36 -> 0.92561983 | H36: 0 | I36: =+H36/$L$36 -> 0 | J36: 4 | K36: =+J36/$L$36 -> 0.033057851 | L36: =B36+D36+F36+H36+J36 -> 121 | M36: =+C36+E36+G36+I36+K36 -> 1
A37: Mnibus | B37: 2 | C37: =+B37/L37 -> 0.2 | D37: 8 | E37: =+D37/L37 -> 0.8 | F37: 0 | G37: =+F37/L37 -> 0 | H37: 0 | I37: =+H37/$L$37 -> 0 | J37: 0 | K37: =+J37/$L$37 -> 0 | L37: =B37+D37+F37+H37+J37 -> 10 | M37: =+C37+E37+G37+I37+K37 -> 1
A38: Pick Up | B38: 0 | C38: =+B38/L38 -> 0 | D38: 425 | E38: =+D38/L38 -> 0.58060109 | F38: 304 | G38: =+F38/L38 -> 0.41530055 | H38: 3 | I38: =+H38/$L$38 -> 0.0040983607 | J38: 0 | K38: =+J38/$L$38 -> 0 | L38: =B38+D38+F38+H38+J38 -> 732 | M38: =+C38+E38+G38+I38+K38 -> 1
A39: SUV | B39: 1345 | C39: =+B39/L39 -> 0.46172331 | D39: 252 | E39: =+D39/L39 -> 0.086508754 | F39: 667 | G39: =+F39/L39 -> 0.22897357 | H39: 572 | I39: =+H39/$L$39 -> 0.19636114 | J39: 77 | K39: =+J39/$L$39 -> 0.02643323 | L39: =B39+D39+F39+H39+J39 -> 2913 | M39: =+C39+E39+G39+I39+K39 -> 1
A40: Julio | B40: =SUM(B41:B45) -> 0 | C40: =+B40/L40 -> #DIV/0! | D40: =SUM(D41:D45) -> 0 | E40: =+D40/L40 -> #DIV/0! | F40: =SUM(F41:F45) -> 0 | G40: =+F40/L40 -> #DIV/0! | H40: =SUM(H41:H45) -> 0 | I40: =+H40/L40 -> #DIV/0! | J40: =SUM(J41:J45) -> 0 | K40: =+J40/L40 -> #DIV/0! | L40: =SUM(L41:L45) -> 0 | M40: =+C40+E40+G40+I40+K40 -> #DIV/0!
A41: Automovil | C41: =+B41/L41 -> #DIV/0! | E41: =+D41/L41 -> #DIV/0! | G41: =+F41/L41 -> #DIV/0! | I41: =+H41/L41 -> #DIV/0! | K41: =+J41/L41 -> #DIV/0! | L41: =+B41+D41+F41+H41+J41 -> 0 | M41: =+C41+E41+G41+I41+K41 -> #DIV/0!
A42: Furgon | C42: =+B42/L42 -> #DIV/0! | E42: =+D42/L42 -> #DIV/0! | G42: =+F42/L42 -> #DIV/0! | I42: =+H42/L42 -> #DIV/0! | K42: =+J42/L42 -> #DIV/0! | L42: =+B42+D42+F42+H42+J42 -> 0 | M42: =+C42+E42+G42+I42+K42 -> #DIV/0!
A43: Mnibus | C43: =+B43/L43 -> #DIV/0! | E43: =+D43/L43 -> #DIV/0! | G43: =+F43/L43 -> #DIV/0! | I43: =+H43/L43 -> #DIV/0! | K43: =+J43/L43 -> #DIV/0! | L43: =+B43+D43+F43+H43+J43 -> 0 | M43: =+C43+E43+G43+I43+K43 -> #DIV/0!
A44: Pick Up | C44: =+B44/L44 -> #DIV/0! | E44: =+D44/L44 -> #DIV/0! | G44: =+F44/L44 -> #DIV/0! | I44: =+H44/L44 -> #DIV/0! | K44: =+J44/L44 -> #DIV/0! | L44: =+B44+D44+F44+H44+J44 -> 0 | M44: =+C44+E44+G44+I44+K44 -> #DIV/0!
A45: SUV | C45: =+B45/L45 -> #DIV/0! | E45: =+D45/L45 -> #DIV/0! | G45: =+F45/L45 -> #DIV/0! | I45: =+H45/L45 -> #DIV/0! | K45: =+J45/L45 -> #DIV/0! | L45: =+B45+D45+F45+H45+J45 -> 0 | M45: =+C45+E45+G45+I45+K45 -> #DIV/0!
A46: Agosto | B46: =SUM(B47:B51) -> 0 | C46: =+B46/L46 -> #DIV/0! | D46: =SUM(D47:D51) -> 0 | E46: =+D46/L46 -> #DIV/0! | F46: =SUM(F47:F51) -> 0 | G46: =+F46/L46 -> #DIV/0! | H46: =SUM(H47:H51) -> 0 | I46: =+H46/L46 -> #DIV/0! | J46: =SUM(J47:J51) -> 0 | K46: =+J46/L46 -> #DIV/0! | L46: =SUM(L47:L51) -> 0 | M46: =+C46+E46+G46+I46+K46 -> #DIV/0!
A47: Automovil | C47: =+B47/L47 -> #DIV/0! | E47: =+D47/L47 -> #DIV/0! | G47: =+F47/L47 -> #DIV/0! | I47: =+H47/L47 -> #DIV/0! | K47: =+J47/L47 -> #DIV/0! | L47: =+B47+D47+F47+H47+J47 -> 0 | M47: =+C47+E47+G47+I47+K47 -> #DIV/0!
A48: Furgon | C48: =+B48/L48 -> #DIV/0! | E48: =+D48/L48 -> #DIV/0! | G48: =+F48/L48 -> #DIV/0! | I48: =+H48/L48 -> #DIV/0! | K48: =+J48/L48 -> #DIV/0! | L48: =+B48+D48+F48+H48+J48 -> 0 | M48: =+C48+E48+G48+I48+K48 -> #DIV/0!
A49: Mnibus | C49: =+B49/L49 -> #DIV/0! | E49: =+D49/L49 -> #DIV/0! | G49: =+F49/L49 -> #DIV/0! | I49: =+H49/L49 -> #DIV/0! | K49: =+J49/L49 -> #DIV/0! | L49: =+B49+D49+F49+H49+J49 -> 0 | M49: =+C49+E49+G49+I49+K49 -> #DIV/0!
A50: Pick Up | C50: =+B50/L50 -> #DIV/0! | E50: =+D50/L50 -> #DIV/0! | G50: =+F50/L50 -> #DIV/0! | I50: =+H50/L50 -> #DIV/0! | K50: =+J50/L50 -> #DIV/0! | L50: =+B50+D50+F50+H50+J50 -> 0 | M50: =+C50+E50+G50+I50+K50 -> #DIV/0!
A51: SUV | C51: =+B51/L51 -> #DIV/0! | E51: =+D51/L51 -> #DIV/0! | G51: =+F51/L51 -> #DIV/0! | I51: =+H51/L51 -> #DIV/0! | K51: =+J51/L51 -> #DIV/0! | L51: =+B51+D51+F51+H51+J51 -> 0 | M51: =+C51+E51+G51+I51+K51 -> #DIV/0!
A52: Setiembre | B52: =SUM(B53:B57) -> 0 | C52: =+B52/L52 -> #DIV/0! | D52: =SUM(D53:D57) -> 0 | E52: =+D52/L52 -> #DIV/0! | F52: =SUM(F53:F57) -> 0 | G52: =+F52/L52 -> #DIV/0! | H52: =SUM(H53:H57) -> 0 | I52: =+H52/L52 -> #DIV/0! | J52: =SUM(J53:J57) -> 0 | K52: =+J52/L52 -> #DIV/0! | L52: =SUM(L53:L57) -> 0 | M52: =+C52+E52+G52+I52+K52 -> #DIV/0!
A53: Automovil | C53: =+B53/L53 -> #DIV/0! | E53: =+D53/L53 -> #DIV/0! | G53: =+F53/L53 -> #DIV/0! | I53: =+H53/L53 -> #DIV/0! | K53: =+J53/L53 -> #DIV/0! | L53: =+B53+D53+F53+H53+J53 -> 0 | M53: =+C53+E53+G53+I53+K53 -> #DIV/0!
A54: Furgon | C54: =+B54/L54 -> #DIV/0! | E54: =+D54/L54 -> #DIV/0! | G54: 0 | I54: =+H54/L54 -> #DIV/0! | K54: =+J54/L54 -> #DIV/0! | L54: =+B54+D54+F54+H54+J54 -> 0 | M54: =+C54+E54+G54+I54+K54 -> #DIV/0!
A55: Mnibus | C55: =+B55/L55 -> #DIV/0! | E55: =+D55/L55 -> #DIV/0! | G55: =+F55/L55 -> #DIV/0! | I55: =+H55/L55 -> #DIV/0! | K55: =+J55/L55 -> #DIV/0! | L55: =+B55+D55+F55+H55+J55 -> 0 | M55: =+C55+E55+G55+I55+K55 -> #DIV/0!
A56: Pick Up | C56: =+B56/L56 -> #DIV/0! | E56: =+D56/L56 -> #DIV/0! | G56: =+F56/L56 -> #DIV/0! | I56: =+H56/L56 -> #DIV/0! | K56: =+J56/L56 -> #DIV/0! | L56: =+B56+D56+F56+H56+J56 -> 0 | M56: =+C56+E56+G56+I56+K56 -> #DIV/0!
A57: SUV | C57: =+B57/L57 -> #DIV/0! | E57: =+D57/L57 -> #DIV/0! | G57: =+F57/L57 -> #DIV/0! | I57: =+H57/L57 -> #DIV/0! | K57: =+J57/L57 -> #DIV/0! | L57: =+B57+D57+F57+H57+J57 -> 0 | M57: =+C57+E57+G57+I57+K57 -> #DIV/0!
A58: Octubre | B58: =SUM(B59:B63) -> 0 | C58: =+B58/L58 -> #DIV/0! | D58: =SUM(D59:D63) -> 0 | E58: =+D58/L58 -> #DIV/0! | F58: =SUM(F59:F63) -> 0 | G58: =+F58/L58 -> #DIV/0! | H58: =SUM(H59:H63) -> 0 | I58: =+H58/L58 -> #DIV/0! | J58: =SUM(J59:J63) -> 0 | K58: =+J58/L58 -> #DIV/0! | L58: =+B58+D58+F58+H58+J58 -> 0 | M58: =+C58+E58+G58+I58+K58 -> #DIV/0!
A59: Automovil | C59: =+B59/L59 -> #DIV/0! | E59: =+D59/L59 -> #DIV/0! | G59: =+F59/L59 -> #DIV/0! | I59: =+H59/L59 -> #DIV/0! | K59: =+J59/L59 -> #DIV/0! | L59: =+B59+D59+F59+H59+J59 -> 0 | M59: =+C59+E59+G59+I59+K59 -> #DIV/0!
A60: Furgon | C60: =+B60/L60 -> #DIV/0! | E60: =+D60/L60 -> #DIV/0! | G60: =+F60/L60 -> #DIV/0! | I60: =+H60/L60 -> #DIV/0! | K60: =+J60/L60 -> #DIV/0! | L60: =+B60+D60+F60+H60+J60 -> 0 | M60: =+C60+E60+G60+I60+K60 -> #DIV/0!
A61: Mnibus | C61: =+B61/L61 -> #DIV/0! | E61: =+D61/L61 -> #DIV/0! | G61: 0 | I61: =+H61/L61 -> #DIV/0! | K61: =+J61/L61 -> #DIV/0! | L61: =+B61+D61+F61+H61+J61 -> 0 | M61: =+C61+E61+G61+I61+K61 -> #DIV/0!
A62: Pick Up | C62: =+B62/L62 -> #DIV/0! | E62: =+D62/L62 -> #DIV/0! | G62: =+F62/L62 -> #DIV/0! | I62: =+H62/L62 -> #DIV/0! | K62: =+J62/L62 -> #DIV/0! | L62: =+B62+D62+F62+H62+J62 -> 0 | M62: =+C62+E62+G62+I62+K62 -> #DIV/0!
A63: SUV | C63: =+B63/L63 -> #DIV/0! | E63: =+D63/L63 -> #DIV/0! | G63: =+F63/L63 -> #DIV/0! | I63: =+H63/L63 -> #DIV/0! | K63: =+J63/L63 -> #DIV/0! | L63: =+B63+D63+F63+H63+J63 -> 0 | M63: =+C63+E63+G63+I63+K63 -> #DIV/0!
A64: Noviembre | B64: =SUM(B65:B69) -> 0 | C64: =+B64/L64 -> #DIV/0! | D64: =SUM(D65:D69) -> 0 | E64: =+D64/L64 -> #DIV/0! | F64: =SUM(F65:F69) -> 0 | G64: =+F64/L64 -> #DIV/0! | H64: =SUM(H65:H69) -> 0 | I64: =+H64/L64 -> #DIV/0! | J64: =SUM(J65:J69) -> 0 | K64: =+J64/L64 -> #DIV/0! | L64: =SUM(L65:L69) -> 0 | M64: =+C64+E64+G64+I64+K64 -> #DIV/0!
A65: Automovil | C65: =+B65/L65 -> #DIV/0! | E65: =+D65/L65 -> #DIV/0! | G65: =+F65/L65 -> #DIV/0! | I65: =+H65/L65 -> #DIV/0! | K65: =+J65/L65 -> #DIV/0! | L65: =+B65+D65+F65+H65+J65 -> 0 | M65: =+C65+E65+G65+I65+K65 -> #DIV/0!
A66: Furgon | C66: =+B66/L66 -> #DIV/0! | E66: =+D66/L66 -> #DIV/0! | G66: =+F66/L66 -> #DIV/0! | I66: =+H66/L66 -> #DIV/0! | K66: =+J66/L66 -> #DIV/0! | L66: =+B66+D66+F66+H66+J66 -> 0 | M66: =+C66+E66+G66+I66+K66 -> #DIV/0!
A67: Mnibus | C67: =+B67/L67 -> #DIV/0! | E67: =+D67/L67 -> #DIV/0! | G67: =+F67/L67 -> #DIV/0! | I67: =+H67/L67 -> #DIV/0! | K67: =+J67/L67 -> #DIV/0! | L67: =+B67+D67+F67+H67+J67 -> 0 | M67: =+C67+E67+G67+I67+K67 -> #DIV/0!
A68: Pick Up | C68: =+B68/L68 -> #DIV/0! | E68: =+D68/L68 -> #DIV/0! | G68: =+F68/L68 -> #DIV/0! | I68: =+H68/L68 -> #DIV/0! | K68: =+J68/L68 -> #DIV/0! | L68: =+B68+D68+F68+H68+J68 -> 0 | M68: =+C68+E68+G68+I68+K68 -> #DIV/0!
A69: SUV | C69: =+B69/L69 -> #DIV/0! | E69: =+D69/L69 -> #DIV/0! | G69: =+F69/L69 -> #DIV/0! | I69: =+H69/L69 -> #DIV/0! | K69: =+J69/L69 -> #DIV/0! | L69: =+B69+D69+F69+H69+J69 -> 0 | M69: =+C69+E69+G69+I69+K69 -> #DIV/0!
A70: Diciembre | B70: =SUM(B71:B75) -> 0 | C70: =+B70/L70 -> #DIV/0! | D70: =SUM(D71:D75) -> 0 | E70: =+D70/L70 -> #DIV/0! | F70: =SUM(F71:F75) -> 0 | G70: =+F70/L70 -> #DIV/0! | H70: =SUM(H71:H75) -> 0 | I70: =+H70/L70 -> #DIV/0! | J70: =SUM(J71:J75) -> 0 | K70: =+J70/L70 -> #DIV/0! | L70: =+B70+D70+F70+H70+J70 -> 0 | M70: =+C70+E70+G70+I70+K70 -> #DIV/0!
A71: Automovil | C71: =+B71/L71 -> #DIV/0! | E71: =+D71/L71 -> #DIV/0! | G71: =+F71/L71 -> #DIV/0! | I71: =+H71/$L$71 -> #DIV/0! | K71: =+J71/$L$71 -> #DIV/0! | L71: =+B71+D71+F71+H71+J71 -> 0 | M71: =+C71+E71+G71+I71+K71 -> #DIV/0!
A72: Furgon | C72: =+B72/L72 -> #DIV/0! | E72: =+D72/L72 -> #DIV/0! | G72: =+F72/L72 -> #DIV/0! | I72: =+H72/$L$71 -> #DIV/0! | K72: =+J72/$L$71 -> #DIV/0! | L72: =+B72+D72+F72+H72+J72 -> 0 | M72: =+C72+E72+G72+I72+K72 -> #DIV/0!
A73: Mnibus | C73: =+B73/L73 -> #DIV/0! | E73: =+D73/L73 -> #DIV/0! | G73: =+F73/L73 -> #DIV/0! | I73: =+H73/$L$71 -> #DIV/0! | K73: =+J73/$L$71 -> #DIV/0! | L73: =+B73+D73+F73+H73+J73 -> 0 | M73: =+C73+E73+G73+I73+K73 -> #DIV/0!
A74: Pick Up | C74: =+B74/L74 -> #DIV/0! | E74: =+D74/L74 -> #DIV/0! | G74: =+F74/L74 -> #DIV/0! | I74: =+H74/$L$71 -> #DIV/0! | K74: =+J74/$L$71 -> #DIV/0! | L74: =+B74+D74+F74+H74+J74 -> 0 | M74: =+C74+E74+G74+I74+K74 -> #DIV/0!
A75: SUV | C75: =+B75/L75 -> #DIV/0! | E75: =+D75/L75 -> #DIV/0! | G75: =+F75/L75 -> #DIV/0! | I75: =+H75/$L$71 -> #DIV/0! | K75: =+J75/$L$71 -> #DIV/0! | L75: =+B75+D75+F75+H75+J75 -> 0 | M75: =+C75+E75+G75+I75+K75 -> #DIV/0!
A76: TOTAL | B76: =+B4+B10+B16+B22+B28+B34+B40+B46+B52+B58+B64+B70 -> 9214 | C76: =+B76/L76 -> 0.3831663 | D76: =+D52+D46+D40+D34+D28+D22+D16+D10+D4+D58+D64+D70 -> 4861 | E76: =+D76/L76 -> 0.2021458 | F76: =+F4+F10+F16+F22+F28+F34+F40+F46+F52+F58+F64+F70 -> 5892 | G76: =+F76/L76 -> 0.24502017 | H76: =+H4+H10+H16+H22+H28+H34+H40+H46+H52+H58+H64+H70 -> 3415 | I76: =+H76/L76 -> 0.14201356 | J76: =+J4+J10+J16+J22+J28+J34+J40+J46+J52+J58+J64+J70 -> 665 | K76: =+J76/L76 -> 0.027654177 | L76: =+L4+L10+L16+L22+L28+L34+L40+L46+L52+L58+L64+L70 -> 24047 | M76: =C76+E76+G76+I76+K76 -> 1
B77: Nafta | C77: Diesel | D77: Flex | E77: Híbrido | F77: Eléctrico | G77: Total
A78: Total | B78: =+C76 -> 0.3831663 | C78: =+E76 -> 0.2021458 | D78: =+G76 -> 0.24502017 | E78: =+I76 -> 0.14201356 | F78: =+K76 -> 0.027654177 | G78: =SUM(B78:F78) -> 1
A79: Cuadro 10B: Importaciones por tipo vehículo y de combustibles y movilidad, por mes, 2026
A80: 2026 | B80: Nafta | D80: Diesel | F80: Flex | H80: Híbrido | J80: Eléctrico | L80: Total
B81: Unid. | C81: % | D81: Unid. | E81: % | F81: Unid. | G81: % | H81: Unid. | I81: % | J81: Unid. | K81: % | L81: Unid. | M81: %
A82: Automovil | B82: =+B5+B11+B17+B23+B29+B35+B41+B47+B53+B59+B65+B71 -> 2104 | C82: =+B82/$B$87 -> 0.22834817 | D82: =+D5+D11+D17+D23+D29+D35+D41+D47+D53+D59+D65+D71 -> 1 | E82: =+D82/$D$87 -> 0.00020571899 | F82: =+F5+F11+F17+F23+F29+F35+F41+F47+F53+F59+F65+F71 -> 603 | G82: =+F82/$F$87 -> 0.10234216 | H82: =+H5+H11+H17+H23+H29+H35+H41+H47+H53+H59+H65+H71 -> 113 | I82: =+H82/$F$87 -> 0.019178547 | J82: =+J5+J11+J17+J23+J29+J35+J41+J47+J53+J59+J65+J71 -> 159 | K82: =+J82/$F$87 -> 0.026985743 | L82: =+L5+L11+L17+L23+L29+L35+L41+L47+L53+L59+L65+L71 -> 2980 | M82: =+L82/$L$87 -> 0.12392398
A83: Furgon | B83: =+B6+B12+B18+B24+B30+B36+B42+B48+B54+B60+B66+B72 -> 0 | C83: =+B83/$B$87 -> 0 | D83: =+D6+D12+D18+D24+D30+D36+D42+D48+D54+D60+D66+D72 -> 54 | E83: =+D83/$D$87 -> 0.011108825 | F83: =+F6+F12+F18+F24+F30+F36+F42+F48+F54+F60+F66+F72 -> 354 | G83: =+F83/$F$87 -> 0.060081466 | H83: =+H6+H12+H18+H24+H30+H36+H42+H48+H54+H60+H66+H72 -> 0 | I83: =+H83/$F$87 -> 0 | J83: =+J6+J12+J18+J24+J30+J36+J42+J48+J54+J60+J66+J72 -> 18 | K83: =+J83/$F$87 -> 0.0030549898 | L83: =+L6+L12+L18+L24+L30+L36+L42+L48+L54+L60+L66+L72 -> 426 | M83: =+L83/$L$87 -> 0.017715308
A84: Mnibus | B84: =+B7+B13+B19+B25+B31+B37+B43+B49+B55+B61+B67+B73 -> 26 | C84: =+B84/$B$87 -> 0.0028217929 | D84: =+D7+D13+D19+D25+D31+D37+D43+D49+D55+D61+D67+D73 -> 71 | E84: =+D84/$D$87 -> 0.014606048 | F84: =+F7+F13+F19+F25+F31+F37+F43+F49+F55+F61+F67+F73 -> 0 | G84: =+F84/$F$87 -> 0 | H84: =+H7+H13+H19+H25+H31+H37+H43+H49+H55+H61+H67+H73 -> 41 | I84: =+H84/$F$87 -> 0.0069585879 | J84: =+J7+J13+J19+J25+J31+J37+J43+J49+J55+J61+J67+J73 -> 3 | K84: =+J84/$F$87 -> 0.00050916497 | L84: =+L7+L13+L19+L25+L31+L37+L43+L49+L55+L61+L67+L73 -> 141 | M84: =+L84/$L$87 -> 0.0058635173
A85: Pick Up | B85: =+B8+B14+B20+B26+B32+B38+B44+B50+B56+B62+B68+B74 -> 1 | C85: =+B85/$B$87 -> 0.0001085305 | D85: =+D8+D14+D20+D26+D32+D38+D44+D50+D56+D62+D68+D74 -> 3369 | E85: =+D85/$D$87 -> 0.69306727 | F85: =+F8+F14+F20+F26+F32+F38+F44+F50+F56+F62+F68+F74 -> 1864 | G85: =+F85/$F$87 -> 0.31636117 | H85: =+H8+H14+H20+H26+H32+H38+H44+H50+H56+H62+H68+H74 -> 73 | I85: =+H85/$F$87 -> 0.012389681 | J85: =+J8+J14+J20+J26+J32+J38+J44+J50+J56+J62+J68+J74 -> 7 | K85: =+J85/$F$87 -> 0.0011880516 | L85: =+L8+L14+L20+L26+L32+L38+L44+L50+L56+L62+L68+L74 -> 5314 | M85: =+L85/$L$87 -> 0.22098391
A86: SUV | B86: =+B9+B15+B21+B27+B33+B39+B45+B51+B57+B63+B69+B75 -> 7083 | C86: =+B86/$B$87 -> 0.76872151 | D86: =+D9+D15+D21+D27+D33+D39+D45+D51+D57+D63+D69+D75 -> 1366 | E86: =+D86/$D$87 -> 0.28101214 | F86: =+F9+F15+F21+F27+F33+F39+F45+F51+F57+F63+F69+F75 -> 3071 | G86: =+F86/$F$87 -> 0.52121521 | H86: =+H9+H15+H21+H27+H33+H39+H45+H51+H57+H63+H69+H75 -> 3188 | I86: =+H86/$F$87 -> 0.54107264 | J86: =+J9+J15+J21+J27+J33+J39+J45+J51+J57+J63+J69+J75 -> 478 | K86: =+J86/$F$87 -> 0.081126952 | L86: =+L9+L15+L21+L27+L33+L39+L45+L51+L57+L63+L69+L75 -> 15186 | M86: =+L86/$L$87 -> 0.63151329
A87: Total | B87: =SUM(B82:B86) -> 9214 | C87: =SUM(C82:C86) -> 1 | D87: =SUM(D82:D86) -> 4861 | E87: =+D87/$D$87 -> 1 | F87: =SUM(F82:F86) -> 5892 | G87: =SUM(G82:G86) -> 1 | H87: =SUM(H82:H86) -> 3415 | I87: =+H87/$F$87 -> 0.57959946 | J87: =SUM(J82:J86) -> 665 | K87: =+J87/$F$87 -> 0.1128649 | L87: =SUM(L82:L86) -> 24047 | M87: =SUM(M82:M86) -> 1
A88: Fuente: CADAM
A90: Importacion de Vehiculos Flex por marca y año, 2010-2022
B91: 2010 | C91: % | D91: 2011 | E91: % | F91: 2012 | G91: % | H91: 2013 | I91: % | J91: 2014 | K91: % | L91: 2015 | M91: % | N91: 2016 | O91: % | P91: 2017 | Q91: % | R91: 2018 | S91: % | T91: 2019 | U91: % | V91: 2020 | W91: % | X91: 2021 | Y91: % | Z91: 2022 | AA91: %
A92: Chevrolet | B92: 1588 | C92: =+B92/$B$108% -> 45.384396 | D92: 1898 | E92: =+D92/$D$108% -> 41.091145 | F92: 750 | G92: =+F92/$F$108% -> 20.150457 | H92: 1043 | I92: =+H92/$H$108% -> 21.045198 | J92: 1297 | K92: =+J92/$J$108% -> 22.042828 | L92: 1385 | M92: =+L92/$L$108% -> 21.590023 | N92: 596 | O92: =+N92/$N$108% -> 12.28866 | P92: 1825 | Q92: =+P92/$P$108% -> 25.116983 | R92: 3503 | S92: =+R92/$R$108% -> 28.553962 | T92: 2989 | U92: =+T92/$T$108 -> 0.27088998 | V92: 2553 | W92: =+V92/$V$108 -> 0.2776811 | X92: 659 | Y92: =+X92/$V$108 -> 0.071677181 | Z92: 895 | AA92: =+Z92/$Z$108 -> 0.27812306
A93: Citroen | B93: 80 | C93: =+B93/$B$108% -> 2.2863675 | D93: 107 | E93: =+D93/$D$108% -> 2.3165187 | F93: 74 | G93: =+F93/$F$108% -> 1.9881784 | H93: 77 | I93: =+H93/$H$108% -> 1.5536723 | J93: 75 | K93: =+J93/$J$108% -> 1.2746431 | L93: 38 | M93: =+L93/$L$108% -> 0.59236165 | N93: 43 | O93: =+N93/$N$108% -> 0.88659794 | P93: 70 | Q93: =+P93/$P$108% -> 0.96339114 | R93: 112 | S93: =+R93/$R$108% -> 0.91294425 | T93: 230 | U93: =+T93/$T$108 -> 0.020844662 | V93: 139 | W93: =+V93/$V$108 -> 0.015118556 | X93: 100 | Y93: =+X93/$V$108 -> 0.010876659 | Z93: 176 | AA93: =+Z93/$Z$108 -> 0.054692356
A94: Dodge | B94: 0 | C94: =+B94/$B$108% -> 0 | D94: 0 | E94: =+D94/$D$108% -> 0 | F94: 0 | G94: =+F94/$F$108% -> 0 | H94: 0 | I94: =+H94/$H$108% -> 0 | J94: 0 | Q94: =+P94/$P$108% -> 0 | R94: 0 | S94: =+R94/$R$108% -> 0 | T94: 26 | U94: =+T94/$T$108 -> 0.0023563531 | V94: 0 | W94: =+V94/$V$108 -> 0 | X94: 0 | Y94: =+X94/$V$108 -> 0 | Z94: 0 | AA94: =+Z94/$Z$108 -> 0
A95: Fiat | B95: 626 | C95: =+B95/$B$108% -> 17.890826 | D95: 539 | E95: =+D95/$D$108% -> 11.669192 | F95: 671 | G95: =+F95/$F$108% -> 18.027942 | H95: 568 | I95: =+H95/$H$108% -> 11.460856 | J95: 363 | K95: =+J95/$J$108% -> 6.1692726 | L95: 292 | M95: =+L95/$L$108% -> 4.5518316 | N95: 106 | O95: =+N95/$N$108% -> 2.185567 | P95: 166 | Q95: =+P95/$P$108% -> 2.2846133 | R95: 498 | S95: =+R95/$R$108% -> 4.0593414 | T95: 178 | U95: =+T95/$T$108 -> 0.016131956 | V95: 496 | W95: =+V95/$V$108 -> 0.053948227 | X95: 46 | Y95: =+X95/$V$108 -> 0.005003263 | Z95: 4 | AA95: =+Z95/$Z$108 -> 0.0012430081
A96: Ford | B96: 99 | C96: =+B96/$B$108% -> 2.8293798 | D96: 112 | E96: =+D96/$D$108% -> 2.4247673 | F96: 111 | G96: =+F96/$F$108% -> 2.9822676 | H96: 269 | I96: =+H96/$H$108% -> 5.4277643 | J96: 219 | K96: =+J96/$J$108% -> 3.7219579 | L96: 178 | M96: =+L96/$L$108% -> 2.7747467 | N96: 250 | O96: =+N96/$N$108% -> 5.1546392 | P96: 288 | Q96: =+P96/$P$108% -> 3.9636664 | R96: 385 | S96: =+R96/$R$108% -> 3.1382458 | T96: 152 | U96: =+T96/$T$108 -> 0.013775603 | V96: 57 | W96: =+V96/$V$108 -> 0.0061996955 | X96: 22 | Y96: =+X96/$V$108 -> 0.0023928649 | Z96: 1 | AA96: =+Z96/$Z$108 -> 0.00031075202
A97: Honda | B97: 0 | C97: 0 | D97: 0 | E97: 0 | F97: 0 | G97: 0 | H97: 0 | I97: 0 | J97: 0 | K97: 0 | L97: 0 | M97: 0 | N97: 330 | O97: =+N97/$N$108% -> 6.8041237 | P97: 29 | Q97: =+P97/$P$108% -> 0.39911919 | R97: 59 | S97: =+R97/$R$108% -> 0.48092599 | T97: 220 | U97: =+T97/$T$108 -> 0.019938372 | V97: 72 | W97: =+V97/$V$108 -> 0.0078311943 | X97: 85 | Y97: =+X97/$V$108 -> 0.0092451599 | Z97: 24 | AA97: =+Z97/$Z$108 -> 0.0074580485
A98: Hyundai | B98: 51 | C98: =+B98/$B$108% -> 1.4575593 | D98: 30 | E98: =+D98/$D$108% -> 0.64949123 | F98: 41 | G98: =+F98/$F$108% -> 1.1015583 | H98: 49 | I98: =+H98/$H$108% -> 0.98870056 | J98: 40 | K98: =+J98/$J$108% -> 0.67980965 | L98: 22 | M98: =+L98/$L$108% -> 0.34294622 | N98: 3 | O98: =+N98/$N$108% -> 0.06185567 | P98: 634 | Q98: =+P98/$P$108% -> 8.7255712 | R98: 470 | S98: =+R98/$R$108% -> 3.8311053 | T98: 897 | U98: =+T98/$T$108 -> 0.081294182 | V98: 1319 | W98: =+V98/$V$108 -> 0.14346313 | X98: 314 | Y98: =+X98/$V$108 -> 0.034152708 | Z98: 496 | AA98: =+Z98/$Z$108 -> 0.154133
A99: Jeep | B99: 0 | C99: =+B99/$B$108% -> 0 | D99: 0 | E99: =+D99/$D$108% -> 0 | F99: 0 | G99: =+F99/$F$108% -> 0 | H99: 0 | I99: =+H99/$H$108% -> 0 | J99: 0 | K99: =+J99/$J$108% -> 0 | L99: 0 | M99: =+L99/$L$108% -> 0 | N99: 0 | O99: =+N99/$N$108% -> 0 | P99: 415 | Q99: =+P99/$P$108% -> 5.7115332 | R99: 497 | S99: =+R99/$R$108% -> 4.0511901 | T99: 609 | U99: =+T99/$T$108 -> 0.05519304 | V99: 482 | W99: =+V99/$V$108 -> 0.052425495 | X99: 318 | Y99: =+X99/$V$108 -> 0.034587775 | Z99: 137 | AA99: =+Z99/$Z$108 -> 0.042573027
A100: Kia | B100: 0 | C100: =+B100/$B$108% -> 0 | D100: 0 | E100: =+D100/$D$108% -> 0 | F100: 510 | G100: =+F100/$F$108% -> 13.702311 | H100: 1571 | I100: =+H100/$H$108% -> 31.698951 | J100: 2124 | K100: =+J100/$J$108% -> 36.097893 | L100: 3806 | M100: =+L100/$L$108% -> 59.329696 | N100: 2623 | O100: =+N100/$N$108% -> 54.082474 | P100: 2563 | Q100: =+P100/$P$108% -> 35.273878 | R100: 3237 | S100: =+R100/$R$108% -> 26.385719 | T100: 2380 | U100: =+T100/$T$108 -> 0.21569694 | V100: 2051 | W100: =+V100/$V$108 -> 0.22308027 | X100: 416 | Y100: =+X100/$V$108 -> 0.0452469 | Z100: 188 | AA100: =+Z100/$Z$108 -> 0.05842138
A101: Nissan | B101: 0 | C101: =+B101/$B$108% -> 0 | D101: 0 | E101: =+D101/$D$108% -> 0 | F101: 0 | G101: =+F101/$F$108% -> 0 | H101: 0 | I101: =+H101/$H$108% -> 0 | J101: 0 | K101: =+J101/$J$108% -> 0 | L101: 0 | M101: =+L101/$L$108% -> 0 | N101: 0 | O101: =+N101/$N$108% -> 0 | P101: 0 | Q101: =+P101/$P$108% -> 0 | R101: 162 | S101: =+R101/$R$108% -> 1.3205086 | T101: 142 | U101: =+T101/$T$108 -> 0.012869313 | V101: 366 | W101: =+V101/$V$108 -> 0.039808571 | X101: 261 | Y101: =+X101/$V$108 -> 0.028388079 | Z101: 30 | AA101: =+Z101/$Z$108 -> 0.0093225606
...

Sheet 11
A1: Cuadro 11A: Importación de vehículos por tipo y mes 2008-2026, unidades | I1: Cuadro 11B: Variación mensual de importación de vehículos, por tipo y mes 2008-2026, en %
A2: Meses | B2: Automóvil | C2: Furgon | D2: Minibus | E2: Pick Up | F2: SUV | G2: Total | I2: Meses | J2: Automóvil | K2: Furgon | L2: Minibus | M2: Pick Up | N2: SUV | O2: Total
A3: 39448 | B3: 431 | C3: 83 | D3: 34 | E3: 373 | F3: 302 | G3: =SUM(B3:F3) -> 1223 | I3: 39448 | J3: - | K3: - | L3: - | M3: - | N3: - | O3: =SUM(J3:N3) -> 0
A4: 39479 | B4: 382 | C4: 38 | D4: 4 | E4: 596 | F4: 321 | G4: =SUM(B4:F4) -> 1341 | I4: 39479 | J4: =+B4/B3-1 -> -0.1136891 | K4: =+C4/C3-1 -> -0.54216867 | L4: =+D4/D3-1 -> -0.88235294 | M4: =+E4/E3-1 -> 0.59785523 | N4: =+F4/F3-1 -> 0.062913907 | O4: =+G4/G3-1 -> 0.096484056
A5: 39508 | B5: 504 | C5: 20 | D5: 19 | E5: 469 | F5: 338 | G5: =SUM(B5:F5) -> 1350 | I5: 39508 | J5: =+B5/B4-1 -> 0.31937173 | K5: =+C5/C4-1 -> -0.47368421 | L5: =+D5/D4-1 -> 3.75 | M5: =+E5/E4-1 -> -0.21308725 | N5: =+F5/F4-1 -> 0.052959502 | O5: =+G5/G4-1 -> 0.0067114094
A6: 39539 | B6: 519 | C6: 69 | D6: 31 | E6: 611 | F6: 453 | G6: =SUM(B6:F6) -> 1683 | I6: 39539 | J6: =+B6/B5-1 -> 0.029761905 | K6: =+C6/C5-1 -> 2.45 | L6: =+D6/D5-1 -> 0.63157895 | M6: =+E6/E5-1 -> 0.30277186 | N6: =+F6/F5-1 -> 0.34023669 | O6: =+G6/G5-1 -> 0.24666667
A7: 39569 | B7: 833 | C7: 30 | D7: 24 | E7: 640 | F7: 367 | G7: =SUM(B7:F7) -> 1894 | I7: 39569 | J7: =+B7/B6-1 -> 0.60500963 | K7: =+C7/C6-1 -> -0.56521739 | L7: =+D7/D6-1 -> -0.22580645 | M7: =+E7/E6-1 -> 0.047463175 | N7: =+F7/F6-1 -> -0.18984547 | O7: =+G7/G6-1 -> 0.12537136
A8: 39600 | B8: 414 | C8: 8 | D8: 9 | E8: 653 | F8: 304 | G8: =SUM(B8:F8) -> 1388 | I8: 39600 | J8: =+B8/B7-1 -> -0.5030012 | K8: =+C8/C7-1 -> -0.73333333 | L8: =+D8/D7-1 -> -0.625 | M8: =+E8/E7-1 -> 0.0203125 | N8: =+F8/F7-1 -> -0.17166213 | O8: =+G8/G7-1 -> -0.26715945
A9: 39630 | B9: 881 | C9: 63 | D9: 17 | E9: 775 | F9: 557 | G9: =SUM(B9:F9) -> 2293 | I9: 39630 | J9: =+B9/B8-1 -> 1.1280193 | K9: =+C9/C8-1 -> 6.875 | L9: =+D9/D8-1 -> 0.88888889 | M9: =+E9/E8-1 -> 0.18683002 | N9: =+F9/F8-1 -> 0.83223684 | O9: =+G9/G8-1 -> 0.65201729
A10: 39661 | B10: 690 | C10: 40 | D10: 8 | E10: 509 | F10: 325 | G10: =SUM(B10:F10) -> 1572 | I10: 39661 | J10: =+B10/B9-1 -> -0.21679909 | K10: =+C10/C9-1 -> -0.36507937 | L10: =+D10/D9-1 -> -0.52941176 | M10: =+E10/E9-1 -> -0.34322581 | N10: =+F10/F9-1 -> -0.41651706 | O10: =+G10/G9-1 -> -0.31443524
A11: 39692 | B11: 1010 | C11: 84 | D11: 27 | E11: 722 | F11: 623 | G11: =SUM(B11:F11) -> 2466 | I11: 39692 | J11: =+B11/B10-1 -> 0.46376812 | K11: =+C11/C10-1 -> 1.1 | L11: =+D11/D10-1 -> 2.375 | M11: =+E11/E10-1 -> 0.41846758 | N11: =+F11/F10-1 -> 0.91692308 | O11: =+G11/G10-1 -> 0.56870229
A12: 39722 | B12: 835 | C12: 119 | D12: 1 | E12: 776 | F12: 493 | G12: =SUM(B12:F12) -> 2224 | I12: 39722 | J12: =+B12/B11-1 -> -0.17326733 | K12: =+C12/C11-1 -> 0.41666667 | L12: =+D12/D11-1 -> -0.96296296 | M12: =+E12/E11-1 -> 0.074792244 | N12: =+F12/F11-1 -> -0.20866774 | O12: =+G12/G11-1 -> -0.098134631
A13: 39753 | B13: 408 | C13: 43 | D13: 6 | E13: 692 | F13: 437 | G13: =SUM(B13:F13) -> 1586 | I13: 39753 | J13: =+B13/B12-1 -> -0.51137725 | K13: =+C13/C12-1 -> -0.63865546 | L13: =+D13/D12-1 -> 5 | M13: =+E13/E12-1 -> -0.10824742 | N13: =+F13/F12-1 -> -0.11359026 | O13: =+G13/G12-1 -> -0.2868705
A14: 39783 | B14: 493 | C14: 24 | D14: - | E14: 468 | F14: 261 | G14: =SUM(B14:F14) -> 1246 | I14: 39783 | J14: =+B14/B13-1 -> 0.20833333 | K14: =+C14/C13-1 -> -0.44186047 | L14: =+D14/D13-1 -> #VALUE! | M14: =+E14/E13-1 -> -0.32369942 | N14: =+F14/F13-1 -> -0.402746 | O14: =+G14/G13-1 -> -0.21437579
A15: 39814 | B15: 407 | C15: 23 | D15: 42 | E15: 421 | F15: 351 | G15: =SUM(B15:F15) -> 1244 | I15: 39814 | J15: =+B15/B14-1 -> -0.17444219 | K15: =+C15/C14-1 -> -0.041666667 | L15: =+D15/D14-1 -> #VALUE! | M15: =+E15/E14-1 -> -0.10042735 | N15: =+F15/F14-1 -> 0.34482759 | O15: =+G15/G14-1 -> -0.0016051364
A16: 39845 | B16: 233 | C16: 14 | D16: 8 | E16: 453 | F16: 169 | G16: =SUM(B16:F16) -> 877 | I16: 39845 | J16: =+B16/B15-1 -> -0.42751843 | K16: =+C16/C15-1 -> -0.39130435 | L16: =+D16/D15-1 -> -0.80952381 | M16: =+E16/E15-1 -> 0.076009501 | N16: =+F16/F15-1 -> -0.51851852 | O16: =+G16/G15-1 -> -0.29501608
A17: 39873 | B17: 287 | C17: 12 | D17: 18 | E17: 451 | F17: 253 | G17: =SUM(B17:F17) -> 1021 | I17: 39873 | J17: =+B17/B16-1 -> 0.23175966 | K17: =+C17/C16-1 -> -0.14285714 | L17: =+D17/D16-1 -> 1.25 | M17: =+E17/E16-1 -> -0.004415011 | N17: =+F17/F16-1 -> 0.49704142 | O17: =+G17/G16-1 -> 0.16419612
A18: 39904 | B18: 276 | C18: 0 | D18: 41 | E18: 386 | F18: 227 | G18: =SUM(B18:F18) -> 930 | I18: 39904 | J18: =+B18/B17-1 -> -0.038327526 | K18: =+C18/C17-1 -> -1 | L18: =+D18/D17-1 -> 1.2777778 | M18: =+E18/E17-1 -> -0.14412417 | N18: =+F18/F17-1 -> -0.1027668 | O18: =+G18/G17-1 -> -0.089128306
A19: 39934 | B19: 347 | C19: 23 | D19: 20 | E19: 391 | F19: 232 | G19: =SUM(B19:F19) -> 1013 | I19: 39934 | J19: =+B19/B18-1 -> 0.25724638 | K19: =+C19/C18-1 -> #DIV/0! | L19: =+D19/D18-1 -> -0.51219512 | M19: =+E19/E18-1 -> 0.012953368 | N19: =+F19/F18-1 -> 0.022026432 | O19: =+G19/G18-1 -> 0.089247312
A20: 39965 | B20: 460 | C20: 47 | D20: 3 | E20: 607 | F20: 252 | G20: =SUM(B20:F20) -> 1369 | I20: 39965 | J20: =+B20/B19-1 -> 0.32564841 | K20: =+C20/C19-1 -> 1.0434783 | L20: =+D20/D19-1 -> -0.85 | M20: =+E20/E19-1 -> 0.55242967 | N20: =+F20/F19-1 -> 0.086206897 | O20: =+G20/G19-1 -> 0.35143139
A21: 39995 | B21: 661 | C21: 39 | D21: 0 | E21: 459 | F21: 319 | G21: =SUM(B21:F21) -> 1478 | I21: 39995 | J21: =+B21/B20-1 -> 0.43695652 | K21: =+C21/C20-1 -> -0.17021277 | L21: =+D21/D20-1 -> -1 | M21: =+E21/E20-1 -> -0.24382208 | N21: =+F21/F20-1 -> 0.26587302 | O21: =+G21/G20-1 -> 0.079620161
A22: 40026 | B22: 209 | C22: 15 | D22: 1 | E22: 283 | F22: 124 | G22: =SUM(B22:F22) -> 632 | I22: 40026 | J22: =+B22/B21-1 -> -0.68381241 | K22: =+C22/C21-1 -> -0.61538462 | L22: =+D22/D21-1 -> #DIV/0! | M22: =+E22/E21-1 -> -0.38344227 | N22: =+F22/F21-1 -> -0.61128527 | O22: =+G22/G21-1 -> -0.57239513
A23: 40057 | B23: 273 | C23: 9 | D23: 10 | E23: 363 | F23: 141 | G23: =SUM(B23:F23) -> 796 | I23: 40057 | J23: =+B23/B22-1 -> 0.3062201 | K23: =+C23/C22-1 -> -0.4 | L23: =+D23/D22-1 -> 9 | M23: =+E23/E22-1 -> 0.28268551 | N23: =+F23/F22-1 -> 0.13709677 | O23: =+G23/G22-1 -> 0.25949367
A24: 40087 | B24: 437 | C24: 17 | D24: 5 | E24: 251 | F24: 137 | G24: =SUM(B24:F24) -> 847 | I24: 40087 | J24: =+B24/B23-1 -> 0.6007326 | K24: =+C24/C23-1 -> 0.88888889 | L24: =+D24/D23-1 -> -0.5 | M24: =+E24/E23-1 -> -0.30853994 | N24: =+F24/F23-1 -> -0.028368794 | O24: =+G24/G23-1 -> 0.064070352
A25: 40118 | B25: 345 | C25: - | D25: 3 | E25: 275 | F25: 121 | G25: =SUM(B25:F25) -> 744 | I25: 40118 | J25: =+B25/B24-1 -> -0.21052632 | K25: - | L25: =+D25/D24-1 -> -0.4 | M25: =+E25/E24-1 -> 0.09561753 | N25: =+F25/F24-1 -> -0.11678832 | O25: =+G25/G24-1 -> -0.12160567
A26: 40148 | B26: 536 | C26: 19 | D26: 33 | E26: 290 | F26: 331 | G26: =SUM(B26:F26) -> 1209 | I26: 40148 | J26: =+B26/B25-1 -> 0.55362319 | K26: - | L26: =+D26/D25-1 -> 10 | M26: =+E26/E25-1 -> 0.054545455 | N26: =+F26/F25-1 -> 1.7355372 | O26: =+G26/G25-1 -> 0.625
A27: 40179 | B27: 413 | C27: 30 | D27: 8 | E27: 480 | F27: 199 | G27: =SUM(B27:F27) -> 1130 | I27: 40179 | J27: =+B27/B26-1 -> -0.22947761 | K27: =+C27/C26-1 -> 0.57894737 | L27: =+D27/D26-1 -> -0.75757576 | M27: =+E27/E26-1 -> 0.65517241 | N27: =+F27/F26-1 -> -0.39879154 | O27: =+G27/G26-1 -> -0.065343259
A28: 40210 | B28: 424 | C28: 21 | D28: 5 | E28: 636 | F28: 186 | G28: =SUM(B28:F28) -> 1272 | I28: 40210 | J28: =+B28/B27-1 -> 0.026634383 | K28: =+C28/C27-1 -> -0.3 | L28: =+D28/D27-1 -> -0.375 | M28: =+E28/E27-1 -> 0.325 | N28: =+F28/F27-1 -> -0.065326633 | O28: =+G28/G27-1 -> 0.12566372
A29: 40238 | B29: 611 | C29: 61 | D29: 32 | E29: 563 | F29: 130 | G29: =SUM(B29:F29) -> 1397 | I29: 40238 | J29: =+B29/B28-1 -> 0.44103774 | K29: =+C29/C28-1 -> 1.9047619 | L29: =+D29/D28-1 -> 5.4 | M29: =+E29/E28-1 -> -0.11477987 | N29: =+F29/F28-1 -> -0.30107527 | O29: =+G29/G28-1 -> 0.09827044
A30: 40269 | B30: 783 | C30: 34 | D30: 36 | E30: 565 | F30: 305 | G30: =SUM(B30:F30) -> 1723 | I30: 40269 | J30: =+B30/B29-1 -> 0.28150573 | K30: =+C30/C29-1 -> -0.44262295 | L30: =+D30/D29-1 -> 0.125 | M30: =+E30/E29-1 -> 0.0035523979 | N30: =+F30/F29-1 -> 1.3461538 | O30: =+G30/G29-1 -> 0.23335719
A31: 40299 | B31: 524 | C31: 70 | D31: 47 | E31: 529 | F31: 198 | G31: =SUM(B31:F31) -> 1368 | I31: 40299 | J31: =+B31/B30-1 -> -0.33077905 | K31: =+C31/C30-1 -> 1.0588235 | L31: =+D31/D30-1 -> 0.30555556 | M31: =+E31/E30-1 -> -0.063716814 | N31: =+F31/F30-1 -> -0.35081967 | O31: =+G31/G30-1 -> -0.20603598
A32: 40330 | B32: 749 | C32: 59 | D32: 27 | E32: 617 | F32: 442 | G32: =SUM(B32:F32) -> 1894 | I32: 40330 | J32: =+B32/B31-1 -> 0.42938931 | K32: =+C32/C31-1 -> -0.15714286 | L32: =+D32/D31-1 -> -0.42553191 | M32: =+E32/E31-1 -> 0.16635161 | N32: =+F32/F31-1 -> 1.2323232 | O32: =+G32/G31-1 -> 0.38450292
A33: 40360 | B33: 694 | C33: 98 | D33: 26 | E33: 569 | F33: 203 | G33: =SUM(B33:F33) -> 1590 | I33: 40360 | J33: =+B33/B32-1 -> -0.073431242 | K33: =+C33/C32-1 -> 0.66101695 | L33: =+D33/D32-1 -> -0.037037037 | M33: =+E33/E32-1 -> -0.077795786 | N33: =+F33/F32-1 -> -0.54072398 | O33: =+G33/G32-1 -> -0.16050686
A34: 40391 | B34: 672 | C34: 51 | D34: 18 | E34: 844 | F34: 342 | G34: =SUM(B34:F34) -> 1927 | I34: 40391 | J34: =+B34/B33-1 -> -0.031700288 | K34: =+C34/C33-1 -> -0.47959184 | L34: =+D34/D33-1 -> -0.30769231 | M34: =+E34/E33-1 -> 0.48330404 | N34: =+F34/F33-1 -> 0.68472906 | O34: =+G34/G33-1 -> 0.21194969
A35: 40422 | B35: 521 | C35: 78 | D35: 24 | E35: 479 | F35: 234 | G35: =SUM(B35:F35) -> 1336 | I35: 40422 | J35: =+B35/B34-1 -> -0.22470238 | K35: =+C35/C34-1 -> 0.52941176 | L35: =+D35/D34-1 -> 0.33333333 | M35: =+E35/E34-1 -> -0.43246445 | N35: =+F35/F34-1 -> -0.31578947 | O35: =+G35/G34-1 -> -0.30669434
A36: 40452 | B36: 842 | C36: 134 | D36: 1 | E36: 825 | F36: 445 | G36: =SUM(B36:F36) -> 2247 | I36: 40452 | J36: =+B36/B35-1 -> 0.61612284 | K36: =+C36/C35-1 -> 0.71794872 | L36: =+D36/D35-1 -> -0.95833333 | M36: =+E36/E35-1 -> 0.7223382 | N36: =+F36/F35-1 -> 0.9017094 | O36: =+G36/G35-1 -> 0.68188623
A37: 40483 | B37: 691 | C37: 45 | D37: 19 | E37: 709 | F37: 379 | G37: =SUM(B37:F37) -> 1843 | I37: 40483 | J37: =+B37/B36-1 -> -0.17933492 | K37: =+C37/C36-1 -> -0.6641791 | L37: =+D37/D36-1 -> 18 | M37: =+E37/E36-1 -> -0.14060606 | N37: =+F37/F36-1 -> -0.14831461 | O37: =+G37/G36-1 -> -0.17979528
A38: 40513 | B38: 1031 | C38: 60 | D38: 23 | E38: 983 | F38: 391 | G38: =SUM(B38:F38) -> 2488 | I38: 40513 | J38: =+B38/B37-1 -> 0.49204052 | K38: =+C38/C37-1 -> 0.33333333 | L38: =+D38/D37-1 -> 0.21052632 | M38: =+E38/E37-1 -> 0.3864598 | N38: =+F38/F37-1 -> 0.031662269 | O38: =+G38/G37-1 -> 0.34997287
... A46: 40756 | B46: 927 | C46: 52 | D46: 26 | E46: 992 | F46: 422 | G46: =SUM(B46:F46) -> 2419 | I46: 40756 | J46: =+B46/B45-1 -> -0.29236641 | K46: =+C46/C45-1 -> 0.26829268 | L46: =+D46/D45-1 -> 0.3 | M46: =+E46/E45-1 -> 0.21419829 | N46: =+F46/F45-1 -> -0.055928412 | O46: =+G46/G45-1 -> -0.081973435
A47: Set-11 | B47: 908 | C47: 25 | D47: 16 | E47: 664 | F47: 583 | G47: =SUM(B47:F47) -> 2196 | I47: Set-11 | J47: =+B47/B46-1 -> -0.020496224 | K47: =+C47/C46-1 -> -0.51923077 | L47: =+D47/D46-1 -> -0.38461538 | M47: =+E47/E46-1 -> -0.33064516 | N47: =+F47/F46-1 -> 0.38151659 | O47: =+G47/G46-1 -> -0.092186854
A48: 40817 | B48: 1177 | C48: 44 | D48: 0 | E48: 865 | F48: 671 | G48: =SUM(B48:F48) -> 2757 | I48: 40817 | J48: =+B48/B47-1 -> 0.29625551 | K48: =+C48/C47-1 -> 0.76 | L48: =+D48/D47-1 -> -1 | M48: =+E48/E47-1 -> 0.30271084 | N48: =+F48/F47-1 -> 0.1509434 | O48: =+G48/G47-1 -> 0.25546448
A49: 40848 | B49: 1155 | C49: 42 | D49: 6 | E49: 823 | F49: 670 | G49: =SUM(B49:F49) -> 2696 | I49: 40848 | J49: =+B49/B48-1 -> -0.018691589 | K49: =+C49/C48-1 -> -0.045454545 | L49: =+D49/D48-1 -> #DIV/0! | M49: =+E49/E48-1 -> -0.048554913 | N49: =+F49/F48-1 -> -0.001490313 | O49: =+G49/G48-1 -> -0.022125499
A50: 40878 | B50: 1257 | C50: 38 | D50: 40 | E50: 721 | F50: 675 | G50: =SUM(B50:F50) -> 2731 | I50: 40878 | J50: =+B50/B49-1 -> 0.088311688 | K50: =+C50/C49-1 -> -0.095238095 | L50: =+D50/D49-1 -> 5.6666667 | M50: =+E50/E49-1 -> -0.12393682 | N50: =+F50/F49-1 -> 0.0074626866 | O50: =+G50/G49-1 -> 0.012982196
A51: 40909 | B51: 821 | C51: 53 | D51: 60 | E51: 841 | F51: 294 | G51: =SUM(B51:F51) -> 2069 | I51: 40909 | J51: =+B51/B50-1 -> -0.3468576 | K51: =+C51/C50-1 -> 0.39473684 | L51: =+D51/D50-1 -> 0.5 | M51: =+E51/E50-1 -> 0.16643551 | N51: =+F51/F50-1 -> -0.56444444 | O51: =+G51/G50-1 -> -0.24240205
A52: 40940 | B52: 629 | C52: 61 | D52: 12 | E52: 902 | F52: 600 | G52: =SUM(B52:F52) -> 2204 | I52: 40940 | J52: =+B52/B51-1 -> -0.23386114 | K52: =+C52/C51-1 -> 0.1509434 | L52: =+D52/D51-1 -> -0.8 | M52: =+E52/E51-1 -> 0.072532699 | N52: =+F52/F51-1 -> 1.0408163 | O52: =+G52/G51-1 -> 0.065248913
A53: 40969 | B53: 1136 | C53: 69 | D53: 66 | E53: 678 | F53: 506 | G53: =SUM(B53:F53) -> 2455 | I53: 40969 | J53: =+B53/B52-1 -> 0.80604134 | K53: =+C53/C52-1 -> 0.13114754 | L53: =+D53/D52-1 -> 4.5 | M53: =+E53/E52-1 -> -0.24833703 | N53: =+F53/F52-1 -> -0.15666667 | O53: =+G53/G52-1 -> 0.11388385
A54: 41000 | B54: 803 | C54: 56 | D54: 9 | E54: 751 | F54: 461 | G54: =SUM(B54:F54) -> 2080 | I54: 41000 | J54: =+B54/B53-1 -> -0.2931338 | K54: =+C54/C53-1 -> -0.1884058 | L54: =+D54/D53-1 -> -0.86363636 | M54: =+E54/E53-1 -> 0.10766962 | N54: =+F54/F53-1 -> -0.088932806 | O54: =+G54/G53-1 -> -0.15274949
A55: 41030 | B55: 1348 | C55: 102 | D55: 0 | E55: 901 | F55: 857 | G55: =SUM(B55:F55) -> 3208 | I55: 41030 | J55: =+B55/B54-1 -> 0.67870486 | K55: =+C55/C54-1 -> 0.82142857 | L55: =+D55/D54-1 -> -1 | M55: =+E55/E54-1 -> 0.19973369 | N55: =+F55/F54-1 -> 0.85900217 | O55: =+G55/G54-1 -> 0.54230769
A56: 41061 | B56: 1083 | C56: 57 | D56: 33 | E56: =1184-200 -> 984 | F56: 696 | G56: =SUM(B56:F56) -> 2853 | I56: 41061 | J56: =+B56/B55-1 -> -0.19658754 | K56: =+C56/C55-1 -> -0.44117647 | L56: =+D56/D55-1 -> #DIV/0! | M56: =+E56/E55-1 -> 0.092119867 | N56: =+F56/F55-1 -> -0.18786464 | O56: =+G56/G55-1 -> -0.11066085
A57: 41091 | B57: 1088 | C57: 56 | D57: 45 | E57: 897 | F57: 614 | G57: =SUM(B57:F57) -> 2700 | I57: 41091 | J57: =+B57/B56-1 -> 0.0046168052 | K57: =+C57/C56-1 -> -0.01754386 | L57: =+D57/D56-1 -> 0.36363636 | M57: =+E57/E56-1 -> -0.088414634 | N57: =+F57/F56-1 -> -0.11781609 | O57: =+G57/G56-1 -> -0.05362776
A58: 41122 | B58: 768 | C58: 75 | D58: 61 | E58: 1296 | F58: 481 | G58: =SUM(B58:F58) -> 2681 | I58: 41122 | J58: =+B58/B57-1 -> -0.29411765 | K58: =+C58/C57-1 -> 0.33928571 | L58: =+D58/D57-1 -> 0.35555556 | M58: =+E58/E57-1 -> 0.44481605 | N58: =+F58/F57-1 -> -0.21661238 | O58: =+G58/G57-1 -> -0.007037037
A59: set-12 | B59: 760 | C59: 16 | D59: 12 | E59: 787 | F59: 576 | G59: =SUM(B59:F59) -> 2151 | I59: set-12 | J59: =+B59/B58-1 -> -0.010416667 | K59: =+C59/C58-1 -> -0.78666667 | L59: =+D59/D58-1 -> -0.80327869 | M59: =+E59/E58-1 -> -0.39274691 | N59: =+F59/F58-1 -> 0.1975052 | O59: =+G59/G58-1 -> -0.19768743
A60: 41183 | B60: 675 | C60: 48 | D60: 20 | E60: 605 | F60: 619 | G60: =SUM(B60:F60) -> 1967 | I60: 41183 | J60: =+B60/B59-1 -> -0.11184211 | K60: =+C60/C59-1 -> 2 | L60: =+D60/D59-1 -> 0.66666667 | M60: =+E60/E59-1 -> -0.23125794 | N60: =+F60/F59-1 -> 0.074652778 | O60: =+G60/G59-1 -> -0.085541609
A61: 41214 | B61: 729 | C61: 11 | D61: 3 | E61: 751 | F61: 467 | G61: =SUM(B61:F61) -> 1961 | I61: 41214 | J61: =+B61/B60-1 -> 0.08 | K61: =+C61/C60-1 -> -0.77083333 | L61: =+D61/D60-1 -> -0.85 | M61: =+E61/E60-1 -> 0.24132231 | N61: =+F61/F60-1 -> -0.24555735 | O61: =+G61/G60-1 -> -0.0030503305
A62: 41244 | B62: 1137 | C62: 77 | D62: 44 | E62: 910 | F62: 390 | G62: =SUM(B62:F62) -> 2558 | I62: 41244 | J62: =+B62/B61-1 -> 0.55967078 | K62: =+C62/C61-1 -> 6 | L62: =+D62/D61-1 -> 13.666667 | M62: =+E62/E61-1 -> 0.21171771 | N62: =+F62/F61-1 -> -0.16488223 | O62: =+G62/G61-1 -> 0.30443651
A63: 41275 | B63: 685 | C63: 45 | D63: 53 | E63: 487 | F63: 316 | G63: =SUM(B63:F63) -> 1586 | I63: 41275 | J63: =+B63/B62-1 -> -0.39753738 | K63: =+C63/C62-1 -> -0.41558442 | L63: =+D63/D62-1 -> 0.20454545 | M63: =+E63/E62-1 -> -0.46483516 | N63: =+F63/F62-1 -> -0.18974359 | O63: =+G63/G62-1 -> -0.37998436
A64: 41306 | B64: 636 | C64: 20 | D64: 17 | E64: 620 | F64: 191 | G64: =SUM(B64:F64) -> 1484 | I64: 41306 | J64: =+B64/B63-1 -> -0.071532847 | K64: =+C64/C63-1 -> -0.55555556 | L64: =+D64/D63-1 -> -0.67924528 | M64: =+E64/E63-1 -> 0.27310062 | N64: =+F64/F63-1 -> -0.39556962 | O64: =+G64/G63-1 -> -0.064312736
A65: 41334 | B65: 530 | C65: 49 | D65: 13 | E65: 584 | F65: 363 | G65: =SUM(B65:F65) -> 1539 | I65: 41334 | J65: =+B65/B64-1 -> -0.16666667 | K65: =+C65/C64-1 -> 1.45 | L65: =+D65/D64-1 -> -0.23529412 | M65: =+E65/E64-1 -> -0.058064516 | N65: =+F65/F64-1 -> 0.90052356 | O65: =+G65/G64-1 -> 0.037061995
A66: 41365 | B66: 1176 | C66: 43 | D66: 60 | E66: 840 | F66: 481 | G66: =SUM(B66:F66) -> 2600 | I66: 41365 | J66: =+B66/B65-1 -> 1.2188679 | K66: =+C66/C65-1 -> -0.12244898 | L66: =+D66/D65-1 -> 3.6153846 | M66: =+E66/E65-1 -> 0.43835616 | N66: =+F66/F65-1 -> 0.32506887 | O66: =+G66/G65-1 -> 0.68940871
A67: 41395 | B67: 966 | C67: 52 | D67: 37 | E67: 605 | F67: 296 | G67: =SUM(B67:F67) -> 1956 | I67: 41395 | J67: =+B67/B66-1 -> -0.17857143 | K67: =+C67/C66-1 -> 0.20930233 | L67: =+D67/D66-1 -> -0.38333333 | M67: =+E67/E66-1 -> -0.2797619 | N67: =+F67/F66-1 -> -0.38461538 | O67: =+G67/G66-1 -> -0.24769231
A68: 41426 | B68: 1087 | C68: 62 | D68: 29 | E68: 697 | F68: 631 | G68: =SUM(B68:F68) -> 2506 | I68: 41426 | J68: =+B68/B67-1 -> 0.1252588 | K68: =+C68/C67-1 -> 0.19230769 | L68: =+D68/D67-1 -> -0.21621622 | M68: =+E68/E67-1 -> 0.15206612 | N68: =+F68/F67-1 -> 1.1317568 | O68: =+G68/G67-1 -> 0.28118609
A69: 41456 | B69: 1023 | C69: 53 | D69: 0 | E69: 645 | F69: 380 | G69: =SUM(B69:F69) -> 2101 | I69: 41456 | J69: =+B69/B68-1 -> -0.058877645 | K69: =+C69/C68-1 -> -0.14516129 | L69: =+D69/D68-1 -> -1 | M69: =+E69/E68-1 -> -0.074605452 | N69: =+F69/F68-1 -> -0.3977813 | O69: =+G69/G68-1 -> -0.16161213
A70: 41487 | B70: 1566 | C70: 54 | D70: 44 | E70: 519 | F70: 684 | G70: =SUM(B70:F70) -> 2867 | I70: 41487 | J70: =+B70/B69-1 -> 0.53079179 | K70: =+C70/C69-1 -> 0.018867925 | L70: =+D70/D69-1 -> #DIV/0! | M70: =+E70/E69-1 -> -0.19534884 | N70: =+F70/F69-1 -> 0.8 | O70: =+G70/G69-1 -> 0.36458829
A71: 41518 | B71: 526 | C71: 57 | D71: 27 | E71: 999 | F71: 338 | G71: =SUM(B71:F71) -> 1947 | I71: 41518 | J71: =+B71/B70-1 -> -0.66411239 | K71: =+C71/C70-1 -> 0.055555556 | L71: =+D71/D70-1 -> -0.38636364 | M71: =+E71/E70-1 -> 0.92485549 | N71: =+F71/F70-1 -> -0.50584795 | O71: =+G71/G70-1 -> -0.32089292
... A224: 46174 | B224: 744 | C224: 121 | D224: 10 | E224: 733 | F224: 2912 | G224: =SUM(B224:F224) -> 4520 | I224: 46174 | J224: =+B224/B223-1 -> 0.34054054 | K224: =+C224/C223-1 -> 2.9032258 | L224: =+D224/D223-1 -> 0 | M224: =+E224/E223-1 -> -0.366465 | N224: =+F224/F223-1 -> 0.1251932 | O224: =+G224/G223-1 -> 0.041234739
A225: Años | B225: Automovil | C225: Furgon | D225: Minibus | E225: Pick Up | F225: SUV | G225: Total | I225: Años | J225: Automovil | K225: Furgon | L225: Minibus | M225: Pick Up | N225: SUV | O225: Total
A226: 2008 | B226: =SUM(B3:B14) -> 7400 | C226: =SUM(C3:C14) -> 621 | D226: =SUM(D3:D14) -> 180 | E226: =SUM(E3:E14) -> 7284 | F226: =SUM(F3:F14) -> 4781 | G226: =SUM(G3:G14) -> 20266 | I226: 2008 | J226: - | K226: - | L226: - | M226: - | N226: - | O226: -
A227: 2009 | B227: =SUM(B15:B26) -> 4471 | C227: =SUM(C15:C26) -> 218 | D227: =SUM(D15:D26) -> 184 | E227: =SUM(E15:E26) -> 4630 | F227: =SUM(F15:F26) -> 2657 | G227: =SUM(G15:G26) -> 12160 | I227: 2009 | J227: =+B227/B226-1 -> -0.39581081 | K227: =+C227/C226-1 -> -0.6489533 | L227: =+D227/D226-1 -> 0.022222222 | M227: =+E227/E226-1 -> -0.36436024 | N227: =+F227/F226-1 -> -0.44425852 | O227: =+G227/G226-1 -> -0.39998026
A228: 2010 | B228: =SUM(B27:B38) -> 7955 | C228: =SUM(C27:C38) -> 741 | D228: =SUM(D27:D38) -> 266 | E228: =SUM(E27:E38) -> 7799 | F228: =SUM(F27:F38) -> 3454 | G228: =SUM(G27:G38) -> 20215 | I228: 2010 | J228: =+B228/B227-1 -> 0.77924402 | K228: =+C228/C227-1 -> 2.3990826 | L228: =+D228/D227-1 -> 0.44565217 | M228: =+E228/E227-1 -> 0.68444924 | N228: =+F228/F227-1 -> 0.29996236 | O228: =+G228/G227-1 -> 0.66241776
A229: 2011 | B229: =SUM(B39:B50) -> 11732 | C229: =SUM(C39:C50) -> 668 | D229: =SUM(D39:D50) -> 286 | E229: =SUM(E39:E50) -> 10326 | F229: =SUM(F39:F50) -> 6380 | G229: =SUM(G39:G50) -> 29392 | I229: 2011 | J229: =+B229/B228-1 -> 0.47479573 | K229: =+C229/C228-1 -> -0.09851552 | L229: =+D229/D228-1 -> 0.07518797 | M229: =+E229/E228-1 -> 0.3240159 | N229: =+F229/F228-1 -> 0.84713376 | O229: =+G229/G228-1 -> 0.45396982
A230: 2012 | B230: =SUM(B51:B62) -> 10977 | C230: =SUM(C51:C62) -> 681 | D230: =SUM(D51:D62) -> 365 | E230: =SUM(E51:E62) -> 10303 | F230: =SUM(F51:F62) -> 6561 | G230: =SUM(G51:G62) -> 28887 | I230: 2012 | J230: =+B230/B229-1 -> -0.064353904 | K230: =+C230/C229-1 -> 0.019461078 | L230: =+D230/D229-1 -> 0.27622378 | M230: =+E230/E229-1 -> -0.0022273872 | N230: =+F230/F229-1 -> 0.028369906 | O230: =+G230/G229-1 -> -0.017181546
A231: 2013 | B231: =SUM(B63:B74) -> 12739 | C231: =SUM(C63:C74) -> 670 | D231: =SUM(D63:D74) -> 398 | E231: =SUM(E63:E74) -> 8759 | F231: =SUM(F63:F74) -> 5623 | G231: =SUM(B231:F231) -> 28189 | I231: 2013 | J231: =+B231/B230-1 -> 0.16051745 | K231: =+C231/C230-1 -> -0.016152717 | L231: =+D231/D230-1 -> 0.090410959 | M231: =+E231/E230-1 -> -0.14985926 | N231: =+F231/F230-1 -> -0.14296601 | O231: =+G231/G230-1 -> -0.024163118
A232: 2014 | B232: =SUM(B75:B86) -> 13747 | C232: =SUM(C75:C86) -> 389 | D232: =SUM(D75:D86) -> 408 | E232: =SUM(E75:E86) -> 8557 | F232: =SUM(F75:F86) -> 7590 | G232: =SUM(B232:F232) -> 30691 | I232: 2014 | J232: =+B232/B231-1 -> 0.07912709 | K232: =+C232/C231-1 -> -0.41940299 | L232: =+D232/D231-1 -> 0.025125628 | M232: =+E232/E231-1 -> -0.023061993 | N232: =+F232/F231-1 -> 0.34981327 | O232: =+G232/G231-1 -> 0.088758026
A233: 2015 | B233: =SUM(B87:B98) -> 9108 | C233: =SUM(C87:C98) -> 587 | D233: =SUM(D87:D98) -> 285 | E233: =SUM(E87:E98) -> 7465 | F233: =SUM(F87:F98) -> 7114 | G233: =SUM(G87:G98) -> 24559 | I233: 2015 | J233: =+B233/B232-1 -> -0.33745544 | K233: =+C233/C232-1 -> 0.50899743 | L233: =+D233/D232-1 -> -0.30147059 | M233: =+E233/E232-1 -> -0.12761482 | N233: =+F233/F232-1 -> -0.062714097 | O233: =+G233/G232-1 -> -0.19979799
A234: 2016 | B234: =SUM(B99:B110) -> 8053 | C234: =SUM(C99:C110) -> 215 | D234: =SUM(D99:D110) -> 163 | E234: =SUM(E99:E110) -> 5823 | F234: =SUM(F99:F110) -> 6548 | G234: =SUM(G99:G110) -> 20802 | I234: 2016 | J234: =+B234/B233-1 -> -0.11583224 | K234: =+C234/C233-1 -> -0.63373083 | L234: =+D234/D233-1 -> -0.42807018 | M234: =+E234/E233-1 -> -0.21995981 | N234: =+F234/F233-1 -> -0.079561428 | O234: =+G234/G233-1 -> -0.15297854
A235: 2017 | B235: 10886 | C235: 388 | D235: 197 | E235: 8478 | F235: 7902 | G235: 27851 | I235: 2017 | J235: =+B235/B234-1 -> 0.35179436 | K235: =+C235/C234-1 -> 0.80465116 | L235: =+D235/D234-1 -> 0.20858896 | M235: =+E235/E234-1 -> 0.45595054 | N235: =+F235/F234-1 -> 0.2067807 | O235: =+G235/G234-1 -> 0.33886165
A236: 2018 | B236: =SUM(B123:B134) -> 15256 | C236: =SUM(C123:C134) -> 368 | D236: =SUM(D123:D134) -> 163 | E236: =SUM(E123:E134) -> 9645 | F236: =SUM(F123:F134) -> 10458 | G236: =SUM(G123:G134) -> 35890 | I236: 2018 | J236: =+B236/B235-1 -> 0.40143303 | K236: =+C236/C235-1 -> -0.051546392 | L236: =+D236/D235-1 -> -0.17258883 | M236: =+E236/E235-1 -> 0.13765039 | N236: =+F236/F235-1 -> 0.32346241 | O236: =+G236/G235-1 -> 0.28864314
A237: 2019 | B237: =SUM(B135:B146) -> 12974 | C237: =SUM(C135:C146) -> 411 | D237: =SUM(D135:D146) -> 197 | E237: =SUM(E135:E146) -> 6147 | F237: =SUM(F135:F146) -> 8708 | G237: =SUM(G135:G146) -> 28437 | I237: 2019 | J237: =+B237/B236-1 -> -0.14958049 | K237: =+C237/C236-1 -> 0.11684783 | L237: =+D237/D236-1 -> 0.20858896 | M237: =+E237/E236-1 -> -0.36267496 | N237: =+F237/F236-1 -> -0.16733601 | O237: =+G237/G236-1 -> -0.2076623
A238: 2020 | B238: =SUM(B147:B158) -> 10827 | C238: =SUM(C147:C158) -> 188 | D238: =SUM(D147:D158) -> 106 | E238: =SUM(E147:E158) -> 4440 | F238: =SUM(F147:F158) -> 6439 | G238: =SUM(G147:G158) -> 22000 | I238: 2020 | J238: =+B238/B237-1 -> -0.16548482 | K238: =+C238/C237-1 -> -0.54257908 | L238: =+D238/D237-1 -> -0.46192893 | M238: =+E238/E237-1 -> -0.27769644 | N238: =+F238/F237-1 -> -0.260565 | O238: =+G238/G237-1 -> -0.22636002
A239: 2021 | B239: =SUM(B159:B170) -> 10890 | C239: =SUM(C159:C170) -> 316 | D239: =SUM(D159:D170) -> 124 | E239: =SUM(E159:E170) -> 7737 | F239: =SUM(F159:F170) -> 8843 | G239: =SUM(G159:G170) -> 27910 | I239: 2021 | J239: =+B239/B238-1 -> 0.0058187864 | K239: =+C239/C238-1 -> 0.68085106 | L239: =+D239/D238-1 -> 0.16981132 | M239: =+E239/E238-1 -> 0.74256757 | N239: =+F239/F238-1 -> 0.3733499 | O239: =+G239/G238-1 -> 0.26863636
A240: 2022 | B240: =SUM(B171:B182) -> 9379 | C240: =SUM(C171:C182) -> 417 | D240: =SUM(D171:D182) -> 271 | E240: =SUM(E171:E182) -> 7997 | F240: =SUM(F171:F182) -> 16121 | G240: =SUM(G171:G182) -> 34185 | I240: 2022 | J240: =+B240/B239-1 -> -0.13875115 | K240: =+C240/C239-1 -> 0.31962025 | L240: =+D240/D239-1 -> 1.1854839 | M240: =+E240/E239-1 -> 0.033604756 | N240: =+F240/F239-1 -> 0.82302386 | O240: =+G240/G239-1 -> 0.22482981
A241: 2023 | B241: =SUM(B183:B194) -> 6056 | C241: =SUM(C183:C194) -> 480 | D241: =SUM(D183:D194) -> 251 | E241: =SUM(E183:E194) -> 8292 | F241: =SUM(F183:F194) -> 14641 | G241: =SUM(G183:G194) -> 29720 | I241: 2023 | J241: =+B241/B240-1 -> -0.35430216 | K241: =+C241/C240-1 -> 0.15107914 | L241: =+D241/D240-1 -> -0.073800738 | M241: =+E241/E240-1 -> 0.036888833 | N241: =+F241/F240-1 -> -0.091805719 | O241: =+G241/G240-1 -> -0.13061284
A242: 2024 | B242: =SUM(B195:B206) -> 6059 | C242: =SUM(C195:C206) -> 529 | D242: =SUM(D195:D206) -> 373 | E242: =SUM(E195:E206) -> 9267 | F242: =SUM(F195:F206) -> 18477 | G242: =SUM(G195:G206) -> 34705 | I242: 2024 | J242: =+B242/B241-1 -> 0.00049537649 | K242: =+C242/C241-1 -> 0.10208333 | L242: =+D242/D241-1 -> 0.48605578 | M242: =+E242/E241-1 -> 0.11758321 | N242: =+F242/F241-1 -> 0.26200396 | O242: =+G242/G241-1 -> 0.16773217
A243: 2025 | B243: =SUM(B207:B218) -> 6024 | C243: =SUM(C207:C218) -> 798 | D243: =SUM(D207:D218) -> 293 | E243: =SUM(E207:E218) -> 9179 | F243: =SUM(F207:F218) -> 22326 | G243: =SUM(G207:G218) -> 38620 | I243: 2025 | J243: =+B243/B242-1 -> -0.0057765308 | K243: =+C243/C242-1 -> 0.50850662 | L243: =+D243/D242-1 -> -0.21447721 | M243: =+E243/E242-1 -> -0.0094960613 | N243: =+F243/F242-1 -> 0.20831304 | O243: =+G243/G242-1 -> 0.11280795
A244: Fuente: CADAM | I244: Fuente: CADAM
A245: Cuadro 12C: % de participación por tipo de vehículo, 2008-2025
A246: Años | B246: Automovil | C246: Furgon | D246: Minibus | E246: Pick Up | F246: SUV | G246: Total
A247: 2008 | B247: =+B226/$G$226 -> 0.36514359 | C247: =+C226/$G$226 -> 0.030642455 | D247: =+D226/$G$226 -> 0.0088818711 | E247: =+E226/$G$226 -> 0.35941972 | F247: =+F226/$G$226 -> 0.23591237 | G247: =SUM(B247:F247) -> 1
A248: 2009 | B248: =+B227/$G$227 -> 0.36768092 | C248: =+C227/$G$227 -> 0.017927632 | D248: =+D227/$G$227 -> 0.015131579 | E248: =+E227/$G$227 -> 0.38075658 | F248: =+F227/$G$227 -> 0.21850329 | G248: =SUM(B248:F248) -> 1
A249: 2010 | B249: =+B228/$G$228 -> 0.39351966 | C249: =+C228/$G$228 -> 0.036655949 | D249: =+D228/$G$228 -> 0.013158546 | E249: =+E228/$G$228 -> 0.38580262 | F249: =+F228/$G$228 -> 0.17086322 | G249: =SUM(B249:F249) -> 1
A250: 2011 | B250: =+B229/$G$229 -> 0.39915623 | C250: =+C229/$G$229 -> 0.022727273 | D250: =+D229/$G$229 -> 0.0097305389 | E250: =+E229/$G$229 -> 0.35132009 | F250: =+F229/$G$229 -> 0.21706587 | G250: =SUM(B250:F250) -> 1
A251: 2012 | B251: =+B230/$G$230 -> 0.37999792 | C251: =+C230/$G$230 -> 0.023574618 | D251: =+D230/$G$230 -> 0.012635442 | E251: =+E230/$G$230 -> 0.35666563 | F251: =+F230/$G$230 -> 0.22712639 | G251: =SUM(B251:F251) -> 1
A252: 2013 | B252: =+B231/$G$231 -> 0.45191387 | C252: =+C231/$G$231 -> 0.023768137 | D252: =+D231/$G$231 -> 0.014118983 | E252: =+E231/$G$231 -> 0.31072404 | F252: =+F231/$G$231 -> 0.19947497 | G252: =SUM(B252:F252) -> 1
A253: 2014 | B253: =+B232/$G$232 -> 0.44791633 | C253: =+C232/$G$232 -> 0.012674725 | D253: =+D232/$G$232 -> 0.013293799 | E253: =+E232/$G$232 -> 0.27881138 | F253: =+F232/$G$232 -> 0.24730377 | G253: =SUM(B253:F253) -> 1
A254: 2015 | B254: =+B233/$G$233 -> 0.37086201 | C254: =+C233/$G$233 -> 0.023901625 | D254: =+D233/$G$233 -> 0.011604707 | E254: =+E233/$G$233 -> 0.30396189 | F254: =+F233/$G$233 -> 0.28966977 | G254: =SUM(B254:F254) -> 1
A255: 2016 | B255: =+B234/$G$234 -> 0.38712624 | C255: =+C234/$G$234 -> 0.010335545 | D255: =+D234/$G$234 -> 0.007835785 | E255: =+E234/$G$234 -> 0.27992501 | F255: =+F234/$G$234 -> 0.31477743 | G255: =+G234/$G$234 -> 1
A256: 2017 | B256: =+B235/$G$235 -> 0.39086568 | C256: =+C235/$G$235 -> 0.013931277 | D256: =+D235/$G$235 -> 0.0070733546 | E256: =+E235/$G$235 -> 0.30440559 | F256: =+F235/$G$235 -> 0.2837241 | G256: =+G235/$G$235 -> 1
A257: 2018 | B257: =+B236/$G$236 -> 0.42507662 | C257: =+C236/$G$236 -> 0.010253553 | D257: =+D236/$G$236 -> 0.0045416551 | E257: =+E236/$G$236 -> 0.26873781 | F257: =+F236/$G$236 -> 0.29139036 | G257: =+G236/$G$236 -> 1
A258: 2019 | B258: =+B237/$G$237 -> 0.45623659 | C258: =+C237/$G$237 -> 0.014453001 | D258: =+D237/$G$237 -> 0.0069275943 | E258: =+E237/$G$237 -> 0.21616204 | F258: =+F237/$G$237 -> 0.30622077 | G258: =+G237/$G$237 -> 1
A259: 2020 | B259: =+B238/$G$238 -> 0.49213636 | C259: =+C238/$G$238 -> 0.0085454545 | D259: =+D238/$G$238 -> 0.0048181818 | E259: =+E238/$G$238 -> 0.20181818 | F259: =+F238/$G$238 -> 0.29268182 | G259: =+G238/$G$238 -> 1
...

Sheet 12
A1: Cuadro 12: Importación de vehículos 0km y usados por año, 1998-2026
A2: Año | B2: 0 Km | C2: % Var. | D2: Usados | E2: % Var. | F2: Total | G2: % Var. | H2: % Part. 0km en total | I2: % Part. Usados en total
A4: 1998 | B4: 15259 | C4: - | D4: 2555 | E4: - | F4: =+B4+D4 -> 17814 | H4: =+B4/F4 -> 0.85657348 | I4: =+D4/F4 -> 0.14342652
A5: 1999 | B5: 9666 | C5: =+B5/B4-1 -> -0.36653778 | D5: 3607 | E5: =+D5/D4-1 -> 0.41174168 | F5: =+B5+D5 -> 13273 | G5: =+F5/F4-1 -> -0.25491187 | H5: =+B5/F5 -> 0.72824531 | I5: =+D5/F5 -> 0.27175469
A6: 2000 | B6: 6780 | C6: =+B6/B5-1 -> -0.29857232 | D6: 6364 | E6: =+D6/D5-1 -> 0.7643471 | F6: =+B6+D6 -> 13144 | G6: =+F6/F5-1 -> -0.0097189784 | H6: =+B6/F6 -> 0.51582471 | I6: =+D6/F6 -> 0.48417529
A7: 2001 | B7: 6559 | C7: =+B7/B6-1 -> -0.03259587 | D7: 6827 | E7: =+D7/D6-1 -> 0.072752986 | F7: =+B7+D7 -> 13386 | G7: =+F7/F6-1 -> 0.018411442 | H7: =+B7/F7 -> 0.48998954 | I7: =+D7/F7 -> 0.51001046
A8: 2002 | B8: 2842 | C8: =+B8/B7-1 -> -0.56670224 | D8: 3861 | E8: =+D8/D7-1 -> -0.43445144 | F8: =+B8+D8 -> 6703 | G8: =+F8/F7-1 -> -0.49925295 | H8: =+B8/F8 -> 0.42398926 | I8: =+D8/F8 -> 0.57601074
A9: 2003 | B9: 3209 | C9: =+B9/B8-1 -> 0.12913441 | D9: 3492 | E9: =+D9/D8-1 -> -0.095571096 | F9: =+B9+D9 -> 6701 | G9: =+F9/F8-1 -> -0.00029837386 | H9: =+B9/F9 -> 0.47888375 | I9: =+D9/F9 -> 0.52111625
A10: 2004 | B10: 5720 | C10: =+B10/B9-1 -> 0.78248676 | D10: 7769 | E10: =+D10/D9-1 -> 1.2247995 | F10: =+B10+D10 -> 13489 | G10: =+F10/F9-1 -> 1.0129831 | H10: =+B10/F10 -> 0.42404923 | I10: =+D10/F10 -> 0.57595077
A11: 2005 | B11: 6710 | C11: =+B11/B10-1 -> 0.17307692 | D11: 9313 | E11: =+D11/D10-1 -> 0.19873858 | F11: =+B11+D11 -> 16023 | G11: =+F11/F10-1 -> 0.18785677 | H11: =+B11/F11 -> 0.41877301 | I11: =+D11/F11 -> 0.58122699
A12: 2006 | B12: 8417 | C12: =+B12/B11-1 -> 0.25439642 | D12: 13004 | E12: =+D12/D11-1 -> 0.39632771 | F12: =+B12+D12 -> 21421 | G12: =+F12/F11-1 -> 0.33689072 | H12: =+B12/F12 -> 0.39293217 | I12: =+D12/F12 -> 0.60706783
A13: 2007 | B13: 11898 | C13: =+B13/B12-1 -> 0.41356778 | D13: 20320 | E13: =+D13/D12-1 -> 0.56259612 | F13: =+B13+D13 -> 32218 | G13: =+F13/F12-1 -> 0.50403809 | H13: =+B13/F13 -> 0.36929667 | I13: =+D13/F13 -> 0.63070333
A14: 2008 | B14: 20266 | C14: =+B14/B13-1 -> 0.70331148 | D14: 35163 | E14: =+D14/D13-1 -> 0.7304626 | F14: =+B14+D14 -> 55429 | G14: =+F14/F13-1 -> 0.72043578 | H14: =+B14/F14 -> 0.36562088 | I14: =+D14/F14 -> 0.63437912
A15: 2009 | B15: 12160 | C15: =+B15/B14-1 -> -0.39998026 | D15: 30885 | E15: =+D15/D14-1 -> -0.12166197 | F15: =+B15+D15 -> 43045 | G15: =+F15/F14-1 -> -0.22342095 | H15: =+B15/F15 -> 0.28249506 | I15: =+D15/F15 -> 0.71750494
A16: 2010 | B16: 20215 | C16: =+B16/B15-1 -> 0.66241776 | D16: 46425 | E16: =+D16/D15-1 -> 0.50315687 | F16: =+B16+D16 -> 66640 | G16: =+F16/F15-1 -> 0.54814729 | H16: =+B16/F16 -> 0.30334634 | I16: =+D16/F16 -> 0.69665366
... A31: 2025 | B31: 38611 | C31: =+B31/B30-1 -> 0.11254862 | D31: 56397 | E31: =+D31/D30-1 -> 0.23718328 | F31: =+B31+D31 -> 95008 | G31: =+F31/F30-1 -> 0.1833105 | H31: =+B31/F31 -> 0.40639736 | I31: =+D31/F31 -> 0.59360264
A32: Fuente: CADAM

Sheet 13
A1: Cuadro 13A: Importación de vehículos usados por marca y mes, 2026
A2: MARCAS | B2: Ene | C2: Feb | D2: Mar | E2: Abr | F2: May | G2: Jun | H2: Jul | I2: Ago | J2: Sep | K2: Oct | L2: Nov | M2: Dic | N2: Total | O2: % | R2: Marcas | S2: % | T2: % Acum
A3: ALFA ROMEO | B3: 0 | C3: 2 | D3: 0 | E3: 1 | F3: 0 | G3: 0 | N3: =SUM(B3:M3) -> 3 | O3: =+N3/$N$70 -> 9.5108265e-05 | R3: TOYOTA | S3: 0.77056716 | T3: =+S3 -> 0.77056716
A4: AUDI | B4: 4 | C4: 2 | D4: 17 | E4: 8 | F4: 2 | G4: 6 | N4: =SUM(B4:M4) -> 39 | O4: =+N4/$N$70 -> 0.0012364074 | R4: KIA | S4: 0.11860001 | T4: =+S4+T3 -> 0.88916717
A5: BMW | B5: 24 | C5: 35 | D5: 43 | E5: 19 | F5: 40 | G5: 41 | N5: =SUM(B5:M5) -> 202 | O5: =+N5/$N$70 -> 0.0064039565 | R5: HYUNDAI | S5: 0.040959959 | T5: =+S5+T4 -> 0.93012713
A6: BUICK | B6: 1 | C6: 0 | D6: 0 | E6: 0 | F6: 0 | G6: 0 | N6: =SUM(B6:M6) -> 1 | O6: =+N6/$N$70 -> 3.1702755e-05 | R6: MERCEDES BENZ | S6: 0.011254478 | T6: =+S6+T5 -> 0.94138161
A7: CADILAC | B7: 0 | C7: 0 | D7: 0 | E7: 0 | F7: 1 | G7: 0 | N7: =SUM(B7:M7) -> 1 | O7: =+N7/$N$70 -> 3.1702755e-05 | R7: SUBARU | S7: 0.010525315 | T7: =+S7+T6 -> 0.95190692
A8: CADILLAC | B8: 1 | C8: 1 | D8: 2 | E8: 3 | F8: 1 | G8: 5 | N8: =SUM(B8:M8) -> 13 | O8: =+N8/$N$70 -> 0.00041213581 | R8: NISSAN | S8: 0.0074501474 | T8: =+S8+T7 -> 0.95935707
A9: CHEVROLET | B9: 17 | C9: 7 | D9: 5 | E9: 3 | F9: 17 | G9: 12 | N9: =SUM(B9:M9) -> 61 | O9: =+N9/$N$70 -> 0.0019338681 | R9: BMW | S9: 0.0064039565 | T9: =+S9+T8 -> 0.96576102
A10: CHRYSLER | B10: 1 | C10: 0 | D10: 0 | E10: 0 | F10: 0 | G10: 2 | N10: =SUM(B10:M10) -> 3 | O10: =+N10/$N$70 -> 9.5108265e-05 | R10: DAIHATSU | S10: 0.0056113876 | T10: =+S10+T9 -> 0.97137241
A11: CITROEN | B11: 0 | C11: 1 | D11: 1 | E11: 0 | F11: 0 | G11: 0 | N11: =SUM(B11:M11) -> 2 | O11: =+N11/$N$70 -> 6.340551e-05 | R11: FORD | S11: 0.0040579526 | T11: =+S11+T10 -> 0.97543036
A12: DAEWOO | B12: 1 | C12: 0 | D12: 0 | E12: 0 | F12: 0 | G12: 0 | N12: =SUM(B12:M12) -> 1 | O12: =+N12/$N$70 -> 3.1702755e-05 | R12: MAZDA | S12: 0.0038360334 | T12: =+S12+T11 -> 0.9792664
A13: DAIHATSU | B13: 59 | C13: 59 | D13: 38 | E13: 11 | F13: 4 | G13: 6 | N13: =SUM(B13:M13) -> 177 | O13: =+N13/$N$70 -> 0.0056113876 | R13: SUZUKI | S13: 0.0027264369 | T13: =+S13+T12 -> 0.98199284
A14: DISCOVERY | B14: 0 | C14: 0 | D14: 0 | E14: 1 | F14: 0 | G14: 0 | N14: =SUM(B14:M14) -> 1 | O14: =+N14/$N$70 -> 3.1702755e-05 | R14: DODGE | S14: 0.0024094094 | T14: =+S14+T13 -> 0.98440224
A15: DODGE | B15: 9 | C15: 14 | D15: 13 | E15: 12 | F15: 12 | G15: 16 | N15: =SUM(B15:M15) -> 76 | O15: =+N15/$N$70 -> 0.0024094094 | R15: CHEVROLET | S15: 0.0019338681 | T15: =+S15+T14 -> 0.98633611
... A69: VOLVO | B69: 0 | C69: 0 | D69: 1 | E69: 0 | F69: 0 | G69: 1 | N69: =SUM(B69:M69) -> 2 | O69: =+N69/$N$70 -> 6.340551e-05 | R69: DOGDE | S69: 0 | T69: =+S69+T68 -> 1
A70: Total | B70: =SUM(B3:B69) -> 4662 | C70: =SUM(C3:C69) -> 4869 | D70: =SUM(D3:D69) -> 6330 | E70: =SUM(E3:E69) -> 5062 | F70: =SUM(F3:F69) -> 5056 | G70: =SUM(G3:G69) -> 5564 | H70: =SUM(H3:H69) -> 0 | I70: =SUM(I3:I69) -> 0 | ... N70: =SUM(N3:N69) -> 31543 | O70: =SUM(O3:O61) -> 0.21389849 | R70: Total | S70: =SUM(S3:S69) -> 1
A72: Variacion mes | C72: =+C70/B70-1 -> 0.044401544 | D72: =+D70/C70-1 -> 0.30006161 | E72: =+E70/D70-1 -> -0.20031596 | F72: =+F70/E70-1 -> -0.0011853023 | G72: =+G70/F70-1 -> 0.10047468 | H72: =+H70/G70-1 -> -1 | I72: =+I70/#REF!-1 -> #REF! | J72: =+J70/I70-1 -> #DIV/0! | K72: =+K71/J70-1 -> #DIV/0! | L72: =+L71/K71-1 -> #DIV/0! | M72: =+M70/L71-1 -> #DIV/0!

Sheet 14
A1: Cuadro 14 A: Importación de vehículos 0 km y usados, por marca, unidades y %, 2026 | K1: Cuadro 14B: Importación de vehículos 0 km y usados totales , por mes, unidades, 2026
A2: Marcas | B2: 0 Km | C2: 0 Km, % del total | D2: Usados | E2: Usados, % del total | F2: Total | G2: partic. En % por marca | K2: 2026 | L2: Ene | M2: Feb | N2: Mar | O2: Abr | P2: May | Q2: Jun | R2: Jul | S2: Ago | T2: Sep | U2: Oct | V2: Nov | W2: Dic | X2: Total
K3: 0km | L3: 3205 | M3: 3319 | N3: 4038 | O3: 4624 | P3: 4341 | Q3: 4520 | X3: =SUM(L3:W3) -> 24047
A4: AION | B4: 19 | C4: =+B4/F4 -> 1 | D4: 0 | E4: =+D4/F4 -> 0 | F4: =+B4+D4 -> 19 | G4: =+F4/$F$114 -> 0.00034178809 | K4: Usados | L4: 4662 | M4: 4869 | N4: 6330 | O4: 5062 | P4: 5056 | Q4: 5564 | X4: =SUM(L4:W4) -> 31543
A5: ALFA ROMEO | B5: 0 | C5: =+B5/F5 -> 0 | D5: 3 | E5: =+D5/F5 -> 1 | F5: =+B5+D5 -> 3 | G5: =+F5/$F$114 -> 5.3966541e-05 | K5: Total | L5: =SUM(L3:L4) -> 7867 | M5: =SUM(M3:M4) -> 8188 | N5: =SUM(N3:N4) -> 10368 | O5: =SUM(O3:O4) -> 9686 | P5: =SUM(P3:P4) -> 9397 | Q5: =SUM(Q3:Q4) -> 10084 | R5: =SUM(R3:R4) -> 0 | S5: =SUM(S3:S4) -> 0 | ... X5: =SUM(X3:X4) -> 55590
A6: ARCFOX | B6: 2 | C6: =+B6/F6 -> 1 | D6: 0 | E6: =+D6/F6 -> 0 | F6: =+B6+D6 -> 2 | G6: =+F6/$F$114 -> 3.5977694e-05
A7: AUDI | B7: 98 | C7: =+B7/F7 -> 0.71532847 | D7: 39 | E7: =+D7/F7 -> 0.28467153 | F7: =+B7+D7 -> 137 | G7: =+F7/$F$114 -> 0.002464472 | K7: Cuadro 14C: Importación de vehículos 0 km y usados totales , por mes, en %, 2025
A8: AVATR | B8: 21 | C8: =+B8/F8 -> 1 | D8: 0 | E8: =+D8/F8 -> 0 | F8: =+B8+D8 -> 21 | G8: =+F8/$F$114 -> 0.00037776579 | K8: 2026 | L8: Ene | M8: Feb | N8: Mar | O8: Abr | P8: May | Q8: Jun | R8: Jul | S8: Ago | T8: Sep | U8: Oct | V8: Nov | W8: Dic | X8: Total
A9: BAIC | B9: 74 | C9: =+B9/F9 -> 1 | D9: 0 | E9: =+D9/F9 -> 0 | F9: =+B9+D9 -> 74 | G9: =+F9/$F$114 -> 0.0013311747 | K9: 0km | L9: =+L3/L5 -> 0.40739799 | M9: =+M3/M5 -> 0.40534929 | N9: =+N3/N5 -> 0.38946759 | O9: =+O3/O5 -> 0.47739005 | P9: =+P3/P5 -> 0.46195594 | Q9: =+Q3/Q5 -> 0.44823483 | R9: =+R3/R5 -> #DIV/0! | S9: =+S3/S5 -> #DIV/0! | ... X9: =+X3/X5 -> 0.4325778
A10: BAOJUN | B10: 3 | C10: =+B10/F10 -> 1 | D10: 0 | E10: =+D10/F10 -> 0 | F10: =+B10+D10 -> 3 | G10: =+F10/$F$114 -> 5.3966541e-05 | K10: Usados | L10: =+L4/L5 -> 0.59260201 | M10: =+M4/M5 -> 0.59465071 | N10: =+N4/N5 -> 0.61053241 | O10: =+O4/O5 -> 0.52260995 | P10: =+P4/P5 -> 0.53804406 | Q10: =+Q4/Q5 -> 0.55176517 | R10: =+R4/R5 -> #DIV/0! | S10: =+S4/S5 -> #DIV/0! | ... X10: =+X4/X5 -> 0.5674222
A11: BMW | B11: 193 | C11: =+B11/F11 -> 0.48860759 | D11: 202 | E11: =+D11/F11 -> 0.51139241 | F11: =+B11+D11 -> 395 | G11: =+F11/$F$114 -> 0.0071055945 | K11: Total | L11: =SUM(L9:L10) -> 1 | M11: =SUM(M9:M10) -> 1 | N11: =SUM(N9:N10) -> 1 | O11: =SUM(O9:O10) -> 1 | P11: =SUM(P9:P10) -> 1 | Q11: =SUM(Q9:Q10) -> 1 | R11: =SUM(R9:R10) -> #DIV/0! | S11: =SUM(S9:S10) -> #DIV/0! | ... X11: =SUM(X9:X10) -> 1
A12: BUICK | B12: 0 | C12: =+B12/F12 -> 0 | D12: 1 | E12: =+D12/F12 -> 1 | F12: =+B12+D12 -> 1 | G12: =+F12/$F$114 -> 1.7988847e-05
A13: BYD | B13: 281 | C13: =+B13/F13 -> 1 | D13: 0 | E13: =+D13/F13 -> 0 | F13: =+B13+D13 -> 281 | G13: =+F13/$F$114 -> 0.005054866
A14: CADILAC | B14: 0 | C14: =+B14/F14 -> 0 | D14: 1 | E14: =+D14/F14 -> 1 | F14: =+B14+D14 -> 1 | G14: =+F14/$F$114 -> 1.7988847e-05 | I14: Cuadro 15D: Participación de mercado por marca, vehículos 0 km y usados, en%, 2026
A15: CADILLAC | B15: 1 | C15: =+B15/F15 -> 0.071428571 | D15: 13 | E15: =+D15/F15 -> 0.92857143 | F15: =+B15+D15 -> 14 | G15: =+F15/$F$114 -> 0.00025184386 | I15: Marca | J15: %
A16: CHANGAN | B16: 227 | C16: =+B16/F16 -> 1 | D16: 0 | E16: =+D16/F16 -> 0 | F16: =+B16+D16 -> 227 | G16: =+F16/$F$114 -> 0.0040834682 | I16: TOYOTA | J16: 0.49546681
A17: CHERY | B17: 882 | C17: =+B17/F17 -> 1 | D17: 0 | E17: =+D17/F17 -> 0 | F17: =+B17+D17 -> 882 | G17: =+F17/$F$114 -> 0.015866163 | I17: KIA | J17: 0.11036158
A18: CHEVROLET | B18: 2144 | C18: =+B18/F18 -> 0.9723356 | D18: 61 | E18: =+D18/F18 -> 0.027664399 | F18: =+B18+D18 -> 2205 | G18: =+F18/$F$114 -> 0.039665407 | I18: HYUNDAI | J18: 0.063680518
A19: CHRYSLER | B19: 0 | C19: =+B19/F19 -> 0 | D19: 3 | E19: =+D19/F19 -> 1 | F19: =+B19+D19 -> 3 | G19: =+F19/$F$114 -> 5.3966541e-05 | I19: FIAT | J19: 0.03993524
A20: CITROEN | B20: 91 | C20: =+B20/F20 -> 0.97849462 | D20: 2 | E20: =+D20/F20 -> 0.021505376 | F20: =+B20+D20 -> 93 | G20: =+F20/$F$114 -> 0.0016729628 | I20: CHEVROLET | J20: 0.039665407
A21: DAEWOO | B21: 0 | C21: =+B21/F21 -> 0 | D21: 1 | E21: =+D21/F21 -> 1 | F21: =+B21+D21 -> 1 | G21: =+F21/$F$114 -> 1.7988847e-05 | I21: VOLKSWAGEN | J21: 0.027325058
A22: DAIHATSU | B22: 0 | C22: =+B22/F22 -> 0 | D22: 177 | E22: =+D22/F22 -> 1 | F22: =+B22+D22 -> 177 | G22: =+F22/$F$114 -> 0.0031840259 | I22: SUZUKI | J22: 0.022486059
A23: DEEPAL | B23: 58 | C23: =+B23/F23 -> 1 | D23: 0 | E23: =+D23/F23 -> 0 | F23: =+B23+D23 -> 58 | G23: =+F23/$F$114 -> 0.0010433531 | I23: NISSAN | J23: 0.021586616
A24: DEEPAL SO5 | B24: 3 | C24: =+B24/F24 -> 1 | D24: 0 | E24: =+D24/F24 -> 0 | F24: =+B24+D24 -> 3 | G24: =+F24/$F$114 -> 5.3966541e-05 | I24: CHERY | J24: 0.015866163
A25: DFSK | B25: 21 | C25: =+B25/F25 -> 1 | D25: 0 | E25: =+D25/F25 -> 0 | F25: =+B25+D25 -> 21 | G25: =+F25/$F$114 -> 0.00037776579 | I25: GEELY | J25: 0.014966721
A26: DISCOVERY | B26: 0 | C26: =+B26/F26 -> 0 | D26: 1 | E26: =+D26/F26 -> 1 | F26: =+B26+D26 -> 1 | G26: =+F26/$F$114 -> 1.7988847e-05 | I26: JETOUR | J26: 0.010505487
A27: DODGE | B27: 0 | C27: =+B27/F27 -> 0 | D27: 75 | E27: =+D27/F27 -> 1 | F27: =+B27+D27 -> 75 | G27: =+F27/$F$114 -> 0.0013491635 | I27: MERCEDES BENZ | J27: 0.010163699
... A113: YUFENG | B113: 2 | C113: =+B113/F113 -> 1 | D113: 0 | E113: =+D113/F113 -> 0 | F113: =+B113+D113 -> 2 | G113: =+F113/$F$114 -> 3.5977694e-05 | I113: LOTUS | J113: 1.7988847e-05
A114: Total | B114: =SUM(B4:B113) -> 24047 | D114: =SUM(D4:D113) -> 31543 | F114: =SUM(F4:F113) -> 55590 | G114: =SUM(G4:G113) -> 1 | I114: MCLAREN | J114: 1.7988847e-05
I115: MONACO | J115: 1.7988847e-05
I116: PONTIAC | J116: 1.7988847e-05
I117: ROVER | J117: 1.7988847e-05
I118: SAMSUNG | J118: 1.7988847e-05
I119: SAUR | J119: 1.7988847e-05
I120: SBARU | J120: 1.7988847e-05
I121: SCANIA | J121: 1.7988847e-05
I122: SMART | J122: 1.7988847e-05
I123: SPORTAGE | J123: 1.7988847e-05
I124: TESLA | J124: 1.7988847e-05
I125: VOYAH DREAMER | J125: 1.7988847e-05
I126: TOTAL | J126: =SUM(J16:J125) -> 1

Sheet 15
A1: Cuadro 15: Importación de camiones por tipo y mes, 2026
A2: Tipo | B2: Ene | C2: Feb | D2: Mar | E2: Abr | F2: May | G2: Jun | H2: Jul | I2: Ago | J2: Sep | K2: Oct | L2: Nov | M2: Dic | N2: Total | O2: %
A3: Camión | B3: 180 | C3: 189 | D3: 212 | E3: 278 | F3: 169 | G3: 198 | N3: =SUM(B3:M3) -> 1226 | O3: =+N3/$N$7 -> 0.94453005
A4: Omnibus | B4: 2 | C4: 9 | D4: 2 | E4: 12 | F4: 37 | G4: 10 | N4: =SUM(B4:M4) -> 72 | O4: =+N4/$N$7 -> 0.055469954
A5: Chasis c/Cabina | B5: - | C5: - | D5: - | E5: - | F5: - | G5: - | H5: - | I5: - | J5: - | K5: - | L5: - | M5: - | N5: =SUM(B5:M5) -> 0 | O5: =+N5/$N$7 -> 0
A6: Tractocamión | B6: - | C6: - | D6: - | E6: - | F6: - | G6: - | H6: - | I6: - | J6: - | K6: - | L6: - | M6: - | N6: 0 | O6: =+N6/$N$7 -> 0
A7: Total | B7: =SUM(B3:B6) -> 182 | C7: =SUM(C3:C6) -> 198 | D7: =SUM(D3:D6) -> 214 | E7: =SUM(E3:E6) -> 290 | F7: =SUM(F3:F6) -> 206 | G7: =SUM(G3:G6) -> 208 | H7: =SUM(H3:H6) -> 0 | I7: =SUM(I3:I6) -> 0 | ... N7: =SUM(N3:N6) -> 1298 | O7: =+N7/$N$7 -> 1
A8: Fuente: CADAM
A14: Importación de camiones por tipo
A15: Tipo | B15: 2011 | C15: 2012 | D15: 2013 | E15: 2014 | F15: 2015 | G15: 2016 | H15: 2017 | I15: 2018 | J15: 2019 | K15: 2020 | L15: 2021 | M15: 2022 | N15: 2023 | O15: 2024 | P15: 2025 | Q15: 2026
A17: Camión | B17: 1559 | C17: 2183 | D17: 2713 | E17: 3422 | F17: 3435 | G17: 1755 | H17: 2263 | I17: 2281 | J17: 2208 | K17: 1442 | L17: 1797 | M17: 1553 | N17: 1606 | O17: 1948 | P17: 2218 | Q17: =+N3 -> 1226
A18: Chasis c/Cabina | B18: 729 | C18: 362 | D18: 104 | E18: 0 | F18: 0 | G18: 0 | H18: 0 | I18: 0 | J18: 0 | K18: 0 | L18: 0 | M18: 0 | N18: 0 | O18: 0 | Q18: 0
A19: Omnibus | B19: 107 | C19: 154 | D19: 113 | E19: 48 | F19: 351 | G19: 262 | H19: 247 | I19: 228 | J19: 90 | K19: 37 | L19: 24 | M19: 10 | N19: 71 | O19: 65 | P19: 123 | Q19: =+N4 -> 72
A20: Tractocamión | B20: 20 | C20: 16 | D20: - | E20: 0 | F20: 0 | G20: 0 | H20: =+M6 -> - | I20: 0 | J20: 0 | K20: 0 | L20: 0 | M20: 0 | N20: 0 | O20: 0 | Q20: 0
A21: Total | B21: 2415 | C21: 2715 | D21: 2930 | E21: =SUM(E17:E20) -> 3470 | F21: =SUM(F17:F20) -> 3786 | G21: =SUM(G17:G20) -> 2017 | H21: =SUM(H17:H20) -> 2510 | I21: =SUM(I17:I20) -> 2509 | J21: =SUM(J17:J20) -> 2298 | K21: =SUM(K17:K20) -> 1479 | L21: =SUM(L17:L20) -> 1821 | ... O21: =SUM(O17:O20) -> 2013 | Q21: =SUM(Q17:Q20) -> 1298
A22: Fuente: CADAM

Sheet 16
A1: Cuadro 16: Importación de camiones, variación mensual, 2025-2026
A2: Meses | B2: 2025 | C2: Var. % 2025 | D2: 2026 | E2: Var. % 2026 | F2: Var % 2026/2025
A4: Ene | B4: 167 | C4: - | D4: 182 | E4: - | F4: =+D4/B4-1 -> 0.089820359
A5: Feb | B5: 104 | C5: =+B5/B4-1 -> -0.37724551 | D5: 198 | E5: =+D5/D4-1 -> 0.087912088 | F5: =+D5/B5-1 -> 0.90384615
A6: Mar | B6: 202 | C6: =+B6/B5-1 -> 0.94230769 | D6: 214 | E6: =+D6/D5-1 -> 0.080808081 | F6: =+D6/B6-1 -> 0.059405941
A7: Abr | B7: 149 | C7: =+B7/B6-1 -> -0.26237624 | D7: 290 | E7: =+D7/D6-1 -> 0.35514019 | F7: =+D7/B7-1 -> 0.94630872
A8: May | B8: 174 | C8: =+B8/B7-1 -> 0.16778523 | D8: 206 | E8: =+D8/D7-1 -> -0.28965517 | F8: =+D8/B8-1 -> 0.18390805
A9: Jun | B9: 143 | C9: =+B9/B8-1 -> -0.17816092 | D9: 208 | E9: =+D9/D8-1 -> 0.0097087379 | F9: =+D9/B9-1 -> 0.45454545
A10: Jul | B10: 264 | C10: =+B10/B9-1 -> 0.84615385 | E10: =+D10/D9-1 -> -1 | F10: =+D10/B10-1 -> -1
A11: Ago | B11: 209 | C11: =+B11/B10-1 -> -0.20833333 | E11: =+D11/D10-1 -> #DIV/0! | F11: =+D11/B11-1 -> -1 | S11: 0.76
A12: Sep | B12: 182 | C12: =+B12/B11-1 -> -0.1291866 | E12: =+D12/D11-1 -> #DIV/0! | F12: =+D12/B12-1 -> -1
A13: Oct | B13: 238 | C13: =+B13/B12-1 -> 0.30769231 | E13: =+D13/D12-1 -> #DIV/0! | F13: =+D13/B13-1 -> -1
A14: Nov | B14: 235 | C14: =+B14/B13-1 -> -0.012605042 | E14: =+D14/D13-1 -> #DIV/0! | F14: =+D14/B14-1 -> -1
A15: Dic | B15: 274 | C15: =+B15/B14-1 -> 0.16595745 | E15: =+D15/D14-1 -> #DIV/0! | F15: =+D15/B15-1 -> -1
A16: Total | B16: =SUM(B4:B9) -> 939 | D16: =SUM(D4:D9) -> 1298 | F16: =+D16/B16-1 -> 0.38232162
A17: Fuente: CADAM
A41: Cuadro 16: Importación de camiones, variación mensual, 2021-2022
A42: Meses | B42: 2021 | C42: var. % 2021 | D42: 2022 | E42: var. % 2022 | F42: Var % 2022/2021
G43: Proyección
A44: Ene | B44: 104 | C44: - | D44: 148 | E44: - | F44: =+D44/B44-1 -> 0.42307692
A45: Feb | B45: 146 | C45: =+B45/B44-1 -> 0.40384615 | E45: =+D45/D44-1 -> -1 | F45: =+D45/B45-1 -> -1
A46: Mar | B46: 127 | C46: =+B46/B45-1 -> -0.13013699 | E46: =+D46/D45-1 -> #DIV/0! | F46: =+D46/B46-1 -> -1
A47: Abr | B47: 230 | C47: =+B47/B46-1 -> 0.81102362 | E47: =+D47/D46-1 -> #DIV/0! | F47: =+D47/B47-1 -> -1
A48: May | B48: 72 | C48: =+B48/B47-1 -> -0.68695652 | E48: =+D48/D47-1 -> #DIV/0! | F48: =+D48/B48-1 -> -1
A49: Jun | B49: 128 | C49: =+B49/B48-1 -> 0.77777778 | E49: =+D49/D48-1 -> #DIV/0! | F49: =+D49/B49-1 -> -1
A50: Jul | B50: 223 | C50: =+B50/B49-1 -> 0.7421875 | E50: =+D50/D49-1 -> #DIV/0! | F50: =+D50/B50-1 -> -1
A51: Ago | B51: 129 | C51: =+B51/B50-1 -> -0.42152466 | E51: =+D51/D50-1 -> #DIV/0! | F51: =+D51/B51-1 -> -1
A52: Sep | B52: 149 | C52: =+B52/B51-1 -> 0.15503876 | E52: =+D52/D51-1 -> #DIV/0! | F52: =+D52/B52-1 -> -1
A53: Oct | B53: 132 | C53: =+B53/B52-1 -> -0.11409396 | E53: =+D53/D52-1 -> #DIV/0! | F53: =+D53/B53-1 -> -1
A54: Nov | B54: 267 | C54: =+B54/B53-1 -> 1.0227273 | E54: =+D54/D53-1 -> #DIV/0! | F54: =+D54/B54-1 -> -1
A55: Dic | B55: 114 | C55: =+B55/B54-1 -> -0.57303371 | E55: =+D55/D54-1 -> #DIV/0! | F55: =+D55/B55-1 -> -1
A56: Total | B56: =SUM(B44:B55) -> 1821 | D56: =SUM(D44:D55) -> 148 | E56: =+D56/B56-1 -> -0.91872597 | F56: =+D56/B56-1 -> -0.91872597
A57: Fuente: CADAM

Sheet 17
A1: Cuadro 17: Importación de camiones por marca y mes, 2026
A2: Marcas | B2: Ene | C2: Feb | D2: Mar | E2: Abr | F2: May | G2: Jun | H2: Jul | I2: Ago | J2: Sep | K2: Oct | L2: Nov | M2: Dic | N2: Total | O2: % | R2: Marcas | S2: Unidades | T2: %
A3: CHANGAN | B3: 0 | C3: 0 | D3: 0 | E3: 0 | F3: 0 | G3: 9 | H3: 0 | I3: 0 | J3: 0 | K3: 0 | L3: 0 | M3: 0 | N3: =SUM(B3:M3) -> 9 | O3: =+N3/$N$29 -> 0.0069337442 | R3: KIA | S3: 297 | T3: =+S3/$S$29 -> 0.22881356
A4: CHUFENG | B4: 0 | C4: 0 | D4: 0 | E4: 0 | F4: 2 | G4: 2 | H4: 0 | I4: 0 | J4: 0 | K4: 0 | L4: 0 | M4: 0 | N4: =SUM(B4:M4) -> 4 | O4: =+N4/$N$29 -> 0.0030816641 | R4: ISUZU | S4: 166 | T4: =+S4/$S$29 -> 0.12788906
A5: CLW | B5: 0 | C5: 0 | D5: 0 | E5: 3 | F5: 0 | G5: 0 | H5: 0 | I5: 0 | J5: 0 | K5: 0 | L5: 0 | M5: 0 | N5: =SUM(B5:M5) -> 3 | O5: =+N5/$N$29 -> 0.0023112481 | R5: HYUNDAI | S5: 163 | T5: =+S5/$S$29 -> 0.12557781
A6: DFSK | B6: 0 | C6: 0 | D6: 0 | E6: 0 | F6: 0 | G6: 10 | H6: 0 | I6: 0 | J6: 0 | K6: 0 | L6: 0 | M6: 0 | N6: =SUM(B6:M6) -> 10 | O6: =+N6/$N$29 -> 0.0077041602 | R6: MITSUBISHI | S6: 108 | T6: =+S6/$S$29 -> 0.083204931
A7: FARIZON | B7: 0 | C7: 0 | D7: 19 | E7: 0 | F7: 0 | G7: 0 | H7: 0 | I7: 0 | J7: 0 | K7: 0 | L7: 0 | M7: 0 | N7: =SUM(B7:M7) -> 19 | O7: =+N7/$N$29 -> 0.014637904 | R7: FOTON | S7: 98 | T7: =+S7/$S$29 -> 0.07550077
A8: FAW | B8: 0 | C8: 0 | D8: 0 | E8: 32 | F8: 0 | G8: 6 | H8: 0 | I8: 0 | J8: 0 | K8: 0 | L8: 0 | M8: 0 | N8: =SUM(B8:M8) -> 38 | O8: =+N8/$N$29 -> 0.029275809 | R8: MERCEDES BENZ | S8: 92 | T8: =+S8/$S$29 -> 0.070878274
A9: FOTON | B9: 15 | C9: 1 | D9: 20 | E9: 32 | F9: 30 | G9: 0 | H9: 0 | I9: 0 | J9: 0 | K9: 0 | L9: 0 | M9: 0 | N9: =SUM(B9:M9) -> 98 | O9: =+N9/$N$29 -> 0.07550077 | R9: JAC | S9: 50 | T9: =+S9/$S$29 -> 0.038520801
A10: HENGTOP | B10: 0 | C10: 0 | D10: 0 | E10: 0 | F10: 0 | G10: 1 | H10: 0 | I10: 0 | J10: 0 | K10: 0 | L10: 0 | M10: 0 | N10: =SUM(B10:M10) -> 1 | O10: =+N10/$N$29 -> 0.00077041602 | R10: HINO | S10: 48 | T10: =+S10/$S$29 -> 0.036979969
A11: HINO | B11: 24 | C11: 8 | D11: 10 | E11: 0 | F11: 6 | G11: 0 | H11: 0 | I11: 0 | J11: 0 | K11: 0 | L11: 0 | M11: 0 | N11: =SUM(B11:M11) -> 48 | O11: =+N11/$N$29 -> 0.036979969 | R11: SINOTRUK | S11: 42 | T11: =+S11/$S$29 -> 0.032357473
A12: HYUNDAI | B12: 11 | C12: 18 | D12: 30 | E12: 12 | F12: 32 | G12: 60 | H12: 0 | I12: 0 | J12: 0 | K12: 0 | L12: 0 | M12: 0 | N12: =SUM(B12:M12) -> 163 | O12: =+N12/$N$29 -> 0.12557781 | R12: VOLKSWAGEN | S12: 42 | T12: =+S12/$S$29 -> 0.032357473
A13: ISUZU | B13: 26 | C13: 17 | D13: 53 | E13: 41 | F13: 0 | G13: 29 | H13: 0 | I13: 0 | J13: 0 | K13: 0 | L13: 0 | M13: 0 | N13: =SUM(B13:M13) -> 166 | O13: =+N13/$N$29 -> 0.12788906 | R13: FAW | S13: 38 | T13: =+S13/$S$29 -> 0.029275809
A14: IVECO | B14: 2 | C14: 21 | D14: 1 | E14: 6 | F14: 3 | G14: 2 | H14: 0 | I14: 0 | J14: 0 | K14: 0 | L14: 0 | M14: 0 | N14: =SUM(B14:M14) -> 35 | O14: =+N14/$N$29 -> 0.026964561 | R14: IVECO | S14: 35 | T14: =+S14/$S$29 -> 0.026964561
... A28: YUCHAI | B28: 0 | C28: 0 | D28: 1 | E28: 0 | F28: 0 | G28: 0 | H28: 0 | I28: 0 | J28: 0 | K28: 0 | L28: 0 | M28: 0 | N28: =SUM(B28:M28) -> 1 | O28: =+N28/$N$29 -> 0.00077041602 | R28: YUCHAI | S28: 1 | T28: =+S28/$S$29 -> 0.00077041602
A29: Total | B29: =SUM(B3:B28) -> 182 | C29: =SUM(C3:C28) -> 198 | D29: =SUM(D3:D28) -> 214 | E29: =SUM(E3:E28) -> 290 | F29: =SUM(F3:F28) -> 206 | G29: =SUM(G3:G28) -> 208 | H29: =SUM(H3:H28) -> 0 | I29: =SUM(I3:I28) -> 0 | ... O29: =SUM(O3:O28) -> 1 | R29: TOTAL | S29: =SUM(S3:S28) -> 1298 | T29: =SUM(T3:T28) -> 1
A30: Fuente: CADAM
A35: Marcas | B35: 45809 | C35: 46174 | D35: VAR % 2026/2025 | E35: Part. en total % 2026
A37: KIA | B37: 123 | C37: 297 | D37: =+C37/B37-1 -> 1.4146341 | E37: =+C37/$C$70 -> 0.22881356
A38: ISUZU | B38: 209 | C38: 166 | D38: =+C38/B38-1 -> -0.20574163 | E38: =+C38/$C$70 -> 0.12788906
A39: HYUNDAI | B39: 164 | C39: 163 | D39: =+C39/B39-1 -> -0.006097561 | E39: =+C39/$C$70 -> 0.12557781
A40: MITSUBISHI | B40: 59 | C40: 108 | D40: =+C40/B40-1 -> 0.83050847 | E40: =+C40/$C$70 -> 0.083204931
A41: FOTON | B41: 17 | C41: 98 | D41: =+C41/B41-1 -> 4.7647059 | E41: =+C41/$C$70 -> 0.07550077
A42: MERCEDES BENZ | B42: 61 | C42: 92 | D42: =+C42/B42-1 -> 0.50819672 | E42: =+C42/$C$70 -> 0.070878274
A43: JAC | B43: 3 | C43: 50 | D43: =+C43/B43-1 -> 15.666667 | E43: =+C43/$C$70 -> 0.038520801
A44: HINO | B44: 58 | C44: 48 | D44: =+C44/B44-1 -> -0.17241379 | E44: =+C44/$C$70 -> 0.036979969
A45: SINOTRUK | B45: 80 | C45: 42 | D45: =+C45/B45-1 -> -0.475 | E45: =+C45/$C$70 -> 0.032357473
A46: VOLKSWAGEN | B46: 17 | C46: 42 | D46: =+C46/B46-1 -> 1.4705882 | E46: =+C46/$C$70 -> 0.032357473
A47: FAW | B47: 0 | C47: 38 | D47: =+C47/B47-1 -> #DIV/0! | E47: =+C47/$C$70 -> 0.029275809
A48: IVECO | B48: 13 | C48: 35 | D48: =+C48/B48-1 -> 1.6923077 | E48: =+C48/$C$70 -> 0.026964561
... A69: VOLARE | B69: 1 | C69: 0 | D69: =+C69/B69-1 -> -1 | E69: =+C69/$C$70 -> 0
A70: Total | B70: =SUM(B37:B69) -> 939 | C70: =SUM(C37:C69) -> 1298 | D70: =+C70/B70-1 -> 0.38232162 | E70: =SUM(E37:E69) -> 1

Sheet 18
A1: Cuadro 18: Importación de camiones por empresa y marca, 2025 | R1: *No se disponen datos de los importadores
A2: Empresa | B2: Marcas | C2: Ene | D2: Feb | E2: Mar | F2: Abr | G2: May | H2: Jun | I2: Jul | J2: Ago | K2: Sep | L2: Oct | M2: Nov | N2: Dic | O2: Total | P2: % | R2: Ranking
A3: VOLPY SA | B3: Agrale | O3: =SUM(C3:N3) -> 0 | P3: =+O3/$O$34 -> #DIV/0! | R3: Empresa | S3: Marcas | T3: Cantidad | U3: %
A4: Tugua Tupi Guaraní S.A. Import. Export | B4: AIDA DINGDANBAO | O4: =SUM(C4:N4) -> 0 | P4: =+O4/$O$34 -> #DIV/0! | U4: =+T4/$T$35 -> #DIV/0!
A5: DAX S.A. | B5: AIMIX | O5: =SUM(C5:N5) -> 0 | P5: =+O5/$O$34 -> #DIV/0! | U5: =+T5/$T$35 -> #DIV/0!
A6: GANDYS S.A | B6: BARMON | O6: =SUM(C6:N6) -> 0 | P6: =+O6/$O$34 -> #DIV/0! | U6: =+T6/$T$35 -> #DIV/0!
A7: GOROSTIAGA AUTOMOVILES SA | B7: CHANGAN | O7: =SUM(C7:N7) -> 0 | P7: =+O7/$O$34 -> #DIV/0! | U7: =+T7/$T$35 -> #DIV/0!
A8: GOTZE INGENIERIA S A | B8: CLW | O8: =SUM(C8:N8) -> 0 | P8: =+O8/$O$34 -> #DIV/0! | U8: =+T8/$T$35 -> #DIV/0!
A9: Chacomer Automotores SA | B9: DFSK | O9: =SUM(C9:N9) -> 0 | P9: =+O9/$O$34 -> #DIV/0! | U9: =+T9/$T$35 -> #DIV/0!
A10: MERCOTEC S.A.E | B10: FOTON | O10: =SUM(C10:N10) -> 0 | P10: =+O10/$O$34 -> #DIV/0! | U10: =+T10/$T$35 -> #DIV/0!
A11: INGENIERIA DE TOPOGRAFIA Y CAMINOS SA (T & C SA) | B11: HENGWANG | O11: =SUM(C11:N11) -> 0 | P11: =+O11/$O$34 -> #DIV/0! | U11: =+T11/$T$35 -> #DIV/0!
A12: Auto Market S.A. | B12: HINO | O12: =SUM(C12:N12) -> 0 | P12: =+O12/$O$34 -> #DIV/0! | U12: =+T12/$T$35 -> #DIV/0!
A13: Automotor S.A. | B13: HYUNDAI | O13: =SUM(C13:N13) -> 0 | P13: =+O13/$O$34 -> #DIV/0! | U13: =+T13/$T$35 -> #DIV/0!
A14: Automotor S.A. | B14: ISUZU | O14: =SUM(C14:N14) -> 0 | P14: =+O14/$O$34 -> #DIV/0! | U14: =+T14/$T$35 -> #DIV/0!
A15: RODOMAQ SOCIEDAD ANONIMA | B15: IVECO | O15: =SUM(C15:N15) -> 0 | P15: =+O15/$O$34 -> #DIV/0! | U15: =+T15/$T$35 -> #DIV/0!
... A33: DAX S.A. | B33: ZOOMLION | O33: =SUM(C33:N33) -> 0 | P33: =+O33/$O$34 -> #DIV/0! | U33: =+T33/$T$35 -> #DIV/0!
A34: Total | C34: =SUM(C3:C33) -> 0 | D34: =SUM(D3:D33) -> 0 | E34: =SUM(E3:E33) -> 0 | F34: =SUM(F3:F33) -> 0 | G34: =SUM(G3:G33) -> 0 | H34: =SUM(H3:H33) -> 0 | I34: =SUM(I3:I33) -> 0 | J34: =SUM(J3:J33) -> 0 | ... P34: =SUM(P3:P33) -> #DIV/0! | U34: =+T34/$T$35 -> #DIV/0!
A35: Fuente: CADAM | K35: VOLVO | L35: 1 | M35: VW | N35: 19 | R35: Total | T35: =SUM(T4:T34) -> 0 | U35: =SUM(U4:U34) -> #DIV/0!
K36: ZHONGTONG | L36: 0
A38: Cuadro 18 B: Importación de camiones, empresas asociadas a CADAM y no asociadas, 2025
C39: Ene | D39: Feb | E39: Mar | F39: Abr | G39: May | H39: Jun | I39: Jul | J39: Ago | K39: Sep | L39: Oct | M39: Nov | N39: Dic | O39: Total | P39: %
A40: CADAM | C40: =+C10+C12+C14+C15+C19+C22+C29+C32 -> 0 | D40: =+D12+D13+D14+D15+D21+D22+D32 -> 0 | E40: =+E10+E12+E15+E18+E19+E21+E22 -> 0 | F40: =+F12+F13+F14+F15+F16+F18+F19+F21+F22+F24+F31+F32 -> 0 | G40: =+G9+G10+G12+G13+G15+G19+G21+G22+G24+G32 -> 0 | H40: =+H13+H14+H15+H18+H19+H21+H22+H24+H27+H32+H10+H12+H29+H31 -> 0 | I40: =+I10+I12+I13+I14+I21+I22+I24+I31+I32 -> 0 | J40: =+J10+J12+J13+J14+J18+J19+J21+J22+J29+J32 -> 0 | K40: =+K12+K13+K21+K22+K24+K29+K31+K32 -> 0 | L40: =+L10+L12+L13+L14+L15+L18+L19+L21+L220+L22+L24+L29+L31+L32 -> 0 | M40: =+M12+M13+M15+M18+M19+M21+M29+M31 -> 0 | N40: =+N9+N12+N13+N14+N15+N17+N18+N19+N21+N22+N31+N32 -> 0 | O40: =SUM(C40:N40) -> 0 | P40: =+O40/O42% -> #DIV/0!
A41: NO CADAM | C41: =+C34-C40 -> 0 | D41: =+D34-D40 -> 0 | E41: =+E34-E40 -> 0 | F41: =+F34-F40 -> 0 | G41: =+G34-G40 -> 0 | H41: =+H34-H40 -> 0 | I41: =+I34-I40 -> 0 | J41: =+J34-J40 -> 0 | K41: 0 | L41: =+L34-L40 -> 0 | M41: =+M34-M40 -> 0 | N41: =+N34-N40 -> 0 | O41: =SUM(C41:N41) -> 0 | P41: =+O41/O42% -> #DIV/0!
A42: Total | C42: =SUM(C40:C41) -> 0 | D42: =SUM(D40:D41) -> 0 | E42: =SUM(E40:E41) -> 0 | F42: =SUM(F40:F41) -> 0 | G42: =SUM(G40:G41) -> 0 | H42: =SUM(H40:H41) -> 0 | I42: =SUM(I40:I41) -> 0 | J42: =SUM(J40:J41) -> 0 | ... P42: =SUM(P40:P41) -> #DIV/0!
A43: Fuente: CADAM

Sheet 19
A1: Cuadro 19: Importación de camiones por modelo y tipo, 2026 | R1: 45047
A2: Marca | B2: Modelo | C2: Tipo | D2: Ene | E2: Feb | F2: Mar | G2: Abr | H2: May | I2: Jun | J2: Jul | K2: Ago | L2: Sep | M2: Oct | N2: Nov | O2: Dic | P2: Total | Q2: % | R2: Max | S2: Min | V2: Marca | W2: Modelo | X2: Tipo | Y2: Junio | Z2: En % | AA2: Tipo camión | AB2: Total | AC2: % | AD2: Especificacion
A3: AGRALE | B3: VOLARE WL | C3: ómnibus | D3: 0 | E3: 0 | F3: 0 | G3: 0 | H3: 0 | I3: 0 | P3: =SUM(D3:O3) -> 0 | Q3: =+P3/$P$321 -> 0 | R3: - | S3: - | U3: Kia K2700 | V3: KIA | W3: K2700 | X3: Chico | Y3: 297 | Z3: =+Y3/$Y$96 -> 0.22881356 | AA3: Chico | AB3: 534 | AC3: =+AB3/$AB$7% -> 41.140216 | AD3: hasta 5 ton.
A4: AGRALE | B4: A8700 | C4: grande | D4: 0 | E4: 0 | F4: 0 | G4: 0 | H4: 0 | I4: 0 | P4: =SUM(D4:O4) -> 0 | Q4: =+P4/$P$321 -> 0 | R4: - | S4: - | U4: Mitsubishi Canter | V4: MITSUBISHI | W4: CANTER | X4: Mediano | Y4: 66 | Z4: =+Y4/$Y$96 -> 0.050847458 | AA4: mediano | AB4: 496 | AC4: =+AB4/$AB$7% -> 38.212635 | AD4: de 5 a 11 ton
A5: AIDA DINGDANBAO | B5: STSQ12D | C5: grande | D5: 0 | E5: 0 | F5: 0 | G5: 0 | H5: 0 | I5: 0 | P5: =SUM(D5:O5) -> 0 | Q5: =+P5/$P$321 -> 0 | R5: - | S5: - | U5: Hyundai h100 | V5: HYUNDAI | W5: H100 | X5: Chico | Y5: 63 | Z5: =+Y5/$Y$96 -> 0.04853621 | AA5: Grande | AB5: 220 | AC5: =+AB5/$AB$7% -> 16.949153 | AD5: de 12 a 16 ton
A6: AIMIX | B6: AS3.5 | C6: grande | D6: 0 | E6: 0 | F6: 0 | G6: 0 | H6: 0 | I6: 0 | P6: =SUM(D6:O6) -> 0 | Q6: =+P6/$P$321 -> 0 | U6: Isuzu QMR77 | V6: ISUZU | W6: QMR77 | X6: mediano | Y6: 63 | Z6: =+Y6/$Y$96 -> 0.04853621 | AA6: Bus | AB6: 48 | AC6: =+AB6/$AB$7% -> 3.6979969
A7: BARMON | B7: LTGDS23.F | C7: Omnibus | D7: 0 | E7: 0 | F7: 0 | G7: 0 | H7: 0 | I7: 0 | P7: =SUM(D7:O7) -> 0 | Q7: =+P7/$P$321 -> 0 | U7: Mitsubishi Fuso | V7: MITSUBISHI | W7: Fuso | X7: Mediano | Y7: 42 | Z7: =+Y7/$Y$96 -> 0.032357473 | AA7: Total | AB7: =SUM(AB3:AB6) -> 1298 | AC7: =SUM(AC3:AC6) -> 100
A8: CHANGAN | B8: MD201 | C8: chico | D8: 0 | E8: 0 | F8: 0 | G8: 0 | H8: 0 | I8: 9 | P8: =SUM(D8:O8) -> 9 | Q8: =+P8/$P$321 -> 0.0069337442 | U8: Isuzu NQR71 | V8: ISUZU | W8: NQR71 | X8: mediano | Y8: 39 | Z8: =+Y8/$Y$96 -> 0.030046225
A9: CHANGAN | B9: MS201 | C9: chico | D9: 0 | E9: 0 | F9: 0 | G9: 0 | H9: 0 | I9: 0 | P9: =SUM(D9:O9) -> 0 | Q9: =+P9/$P$321 -> 0 | U9: Sinotruk Howo | V9: SINOTRUK | W9: Howo | X9: grande | Y9: 38 | Z9: =+Y9/$Y$96 -> 0.029275809
A10: CHUFENG | B10: HQG5080TQZBEVQC | C10: grande | D10: 0 | E10: 0 | F10: 0 | G10: 0 | H10: 2 | I10: 2 | P10: =SUM(D10:O10) -> 4 | Q10: =+P10/$P$321 -> 0.0030816641 | U10: Foton BJ1128 | V10: FOTON | W10: BJ1128 | X10: Mediano | Y10: 35 | Z10: =+Y10/$Y$96 -> 0.026964561
A11: CLW | B11: CLW5200CLGT3 | C11: grande | D11: 0 | E11: 0 | F11: 0 | G11: 0 | H11: 0 | I11: 0 | P11: =SUM(D11:O11) -> 0 | Q11: =+P11/$P$321 -> 0 | U11: Foton BJ1030 | V11: FOTON | W11: BJ1030 | X11: Chico | Y11: 32 | Z11: =+Y11/$Y$96 -> 0.024653313
A12: CLW | B12: CLW5250DFCT3 | C12: grande | D12: 0 | E12: 0 | F12: 0 | G12: 3 | H12: 0 | I12: 0 | P12: =SUM(D12:O12) -> 3 | Q12: =+P12/$P$321 -> 0.0023112481 | U12: Foton BJ1088 | V12: FOTON | W12: BJ1088 | X12: Chico | Y12: 30 | Z12: =+Y12/$Y$96 -> 0.023112481
A13: CNHTC | B13: ZZ3257V3847B1 | C13: grande | D13: 0 | E13: 0 | F13: 0 | G13: 0 | H13: 0 | I13: 0 | P13: =SUM(D13:O13) -> 0 | Q13: =+P13/$P$321 -> 0 | U13: Isuzu QLR77L | V13: ISUZU | W13: QLR77L | X13: mediano | Y13: 28 | Z13: =+Y13/$Y$96 -> 0.021571649
A14: DAF | B14: FTSXF480D | C14: mediano | D14: 0 | E14: 0 | F14: 0 | G14: 0 | H14: 0 | I14: 0 | P14: =SUM(D14:O14) -> 0 | Q14: =+P14/$P$321 -> 0 | U14: Hyundai EX6 | V14: HYUNDAI | W14: EX6 | X14: Mediano | Y14: 27 | Z14: =+Y14/$Y$96 -> 0.020801233
A15: DASWELL | B15: YCD4J22T-125 | C15: grande | D15: 0 | E15: 0 | F15: 0 | G15: 0 | H15: 0 | I15: 0 | P15: =SUM(D15:O15) -> 0 | Q15: =+P15/$P$321 -> 0 | U15: Isuzu NPR71L | V15: ISUZU | W15: NPR71L | X15: Mediano | Y15: 25 | Z15: =+Y15/$Y$96 -> 0.019260401
A16: DFSK | B16: Mini truck | C16: chico | D16: 0 | E16: 0 | F16: 0 | G16: 0 | H16: 0 | I16: 10 | P16: =SUM(D16:O16) -> 10 | Q16: =+P16/$P$321 -> 0.0077041602 | R16: - | S16: - | V16: M.BENZ | W16: 1418/48 | X16: grande | Y16: 23 | Z16: =+Y16/$Y$96 -> 0.017719569
A17: DFSK | B17: K07S | C17: Chico | D17: 0 | E17: 0 | F17: 0 | G17: 0 | H17: 0 | I17: 0 | P17: =SUM(D17:O17) -> 0 | Q17: =+P17/$P$321 -> 0 | R17: - | S17: - | V17: HINO | W17: FC9 | X17: Mediano | Y17: 22 | Z17: =+Y17/$Y$96 -> 0.016949153
A18: DFSK | B18: K01S | C18: Chico | D18: 0 | E18: 0 | F18: 0 | G18: 0 | H18: 0 | I18: 0 | P18: =SUM(D18:O18) -> 0 | Q18: =+P18/$P$321 -> 0 | R18: - | S18: - | V18: VW | W18: 17230 | X18: grande | Y18: 20 | Z18: =+Y18/$Y$96 -> 0.01540832
A19: DONGFENG | B19: EQ5310 | C19: Chico | D19: 0 | E19: 0 | F19: 0 | G19: 0 | H19: 0 | I19: 0 | P19: =SUM(D19:O19) -> 0 | Q19: =+P19/$P$321 -> 0 | R19: - | S19: - | V19: HYUNDAI | W19: County | X19: Bus | Y19: 19 | Z19: =+Y19/$Y$96 -> 0.014637904
A20: DONGFENG | B20: EQ1040TT2DJ | C20: Chico | D20: 0 | E20: 0 | F20: 0 | G20: 0 | H20: 0 | I20: 0 | P20: =SUM(D20:O20) -> 0 | Q20: =+P20/$P$321 -> 0 | V20: M.BENZ | W20: Accelo 916/39 | X20: grande | Y20: 18 | Z20: =+Y20/$Y$96 -> 0.013867488
A21: FARIZON | B21: F1E | C21: chico | D21: 0 | E21: 0 | F21: 9 | G21: 0 | H21: 0 | I21: 0 | P21: =SUM(D21:O21) -> 9 | Q21: =+P21/$P$321 -> 0.0069337442 | V21: HYUNDAI | W21: GT8 | X21: Mediano | Y21: 17 | Z21: =+Y21/$Y$96 -> 0.013097072
A22: FARIZON | B22: H9E-8T | C22: grande | D22: 0 | E22: 0 | F22: 10 | G22: 0 | H22: 0 | I22: 0 | P22: =SUM(D22:O22) -> 10 | Q22: =+P22/$P$321 -> 0.0077041602 | V22: M.BENZ | W22: ATEGO 1726/48 4X2 | X22: grande | Y22: 17 | Z22: =+Y22/$Y$96 -> 0.013097072
A23: FAW | B23: Tiger 3.4 | C23: chico | D23: 0 | E23: 0 | F23: 0 | G23: 12 | H23: 0 | I23: 0 | P23: =SUM(D23:O23) -> 12 | Q23: =+P23/$P$321 -> 0.0092449923 | V23: IVECO | W23: SWAY AS440 | X23: Grande | Y23: 15 | Z23: =+Y23/$Y$96 -> 0.01155624
A24: FAW | B24: Tiger 3.8 | C24: chico | D24: 0 | E24: 0 | F24: 0 | G24: 8 | H24: 0 | I24: 0 | P24: =SUM(D24:O24) -> 8 | Q24: =+P24/$P$321 -> 0.0061633282 | V24: JAC | W24: X200 CABINA SIMPLE | X24: Chico | Y24: 15 | Z24: =+Y24/$Y$96 -> 0.01155624
A25: FAW | B25: Tiger 5.9 | C25: Mediano | D25: 0 | E25: 0 | F25: 0 | G25: 8 | H25: 0 | I25: 0 | P25: =SUM(D25:O25) -> 8 | Q25: =+P25/$P$321 -> 0.0061633282 | V25: M.BENZ | W25: OF1723 59 | X25: Ómnibus | Y25: 13 | Z25: =+Y25/$Y$96 -> 0.010015408
A26: FAW | B26: Tiger 6.7 | C26: Mediano | D26: 0 | E26: 0 | F26: 0 | G26: 4 | H26: 0 | I26: 6 | P26: =SUM(D26:O26) -> 10 | Q26: =+P26/$P$321 -> 0.0077041602 | V26: FAW | W26: Tiger 3.4 | X26: chico | Y26: 12 | Z26: =+Y26/$Y$96 -> 0.0092449923
A27: FORD | B27: F4000 | C27: Mediano | D27: 0 | E27: 0 | F27: 0 | G27: 0 | H27: 0 | I27: 0 | P27: =SUM(D27:O27) -> 0 | Q27: =+P27/$P$321 -> 0 | R27: - | S27: - | V27: TATA | W27: Super Ace | X27: Chico | Y27: 12 | Z27: =+Y27/$Y$96 -> 0.0092449923
A28: FORD | B28: F650 | C28: grande | D28: 0 | E28: 0 | F28: 0 | G28: 0 | H28: 0 | I28: 0 | P28: =SUM(D28:O28) -> 0 | Q28: =+P28/$P$321 -> 0 | R28: - | S28: - | V28: HINO | W28: XZU720L | X28: Mediano | Y28: 11 | Z28: =+Y28/$Y$96 -> 0.0084745763
A29: FORLAND | B29: BJ1030V6JB5DA | C29: Chico | D29: 0 | E29: 0 | F29: 0 | G29: 0 | H29: 0 | I29: 0 | P29: =SUM(D29:O29) -> 0 | Q29: =+P29/$P$321 -> 0 | R29: - | S29: - | V29: DFSK | W29: Mini truck | X29: chico | Y29: 10 | Z29: =+Y29/$Y$96 -> 0.0077041602
A30: FORLAND | B30: BJ1065VDJD6F1 | C30: Chico | D30: 0 | E30: 0 | F30: 0 | G30: 0 | H30: 0 | I30: 0 | P30: =SUM(D30:O30) -> 0 | Q30: =+P30/$P$321 -> 0 | R30: - | S30: - | V30: FARIZON | W30: H9E-8T | X30: grande | Y30: 10 | Z30: =+Y30/$Y$96 -> 0.0077041602
A31: FOTON | B31: Aumark | C31: Chico | D31: 0 | E31: 0 | F31: 0 | G31: 0 | H31: 0 | I31: 0 | P31: =SUM(D31:O31) -> 0 | Q31: =+P31/$P$321 -> 0 | R31: - | S31: - | V31: FAW | W31: Tiger 6.7 | X31: Mediano | Y31: 10 | Z31: =+Y31/$Y$96 -> 0.0077041602
A32: FOTON | B32: Auman | C32: grande | D32: 0 | E32: 1 | F32: 0 | G32: 0 | H32: 0 | I32: 0 | P32: =SUM(D32:O32) -> 1 | Q32: =+P32/$P$321 -> 0.00077041602 | V32: HYUNDAI | W32: GT11 | X32: Mediano | Y32: 10 | Z32: =+Y32/$Y$96 -> 0.0077041602
A33: FOTON | B33: Camion | C33: Chico | D33: 0 | E33: 0 | F33: 0 | G33: 0 | H33: 0 | I33: 0 | P33: =SUM(D33:O33) -> 0 | Q33: =+P33/$P$321 -> 0 | R33: - | S33: - | V33: VW | W33: 11170 | X33: Grande | Y33: 10 | Z33: =+Y33/$Y$96 -> 0.0077041602
A34: FOTON | B34: BJ1128 | C34: Mediano | D34: 15 | E34: 0 | F34: 20 | G34: 0 | H34: 0 | I34: 0 | P34: =SUM(D34:O34) -> 35 | Q34: =+P34/$P$321 -> 0.026964561 | R34: - | S34: - | V34: CHANGAN | W34: MD201 | X34: chico | Y34: 9 | Z34: =+Y34/$Y$96 -> 0.0069337442
A35: FOTON | B35: BJ1030 | C35: Chico | D35: 0 | E35: 0 | F35: 0 | G35: 32 | H35: 0 | I35: 0 | P35: =SUM(D35:O35) -> 32 | Q35: =+P35/$P$321 -> 0.024653313 | R35: 8061.9 | S35: 6529 | U35: Iveco TECTOR 17 210 | V35: FARIZON | W35: F1E | X35: chico | Y35: 9 | Z35: =+Y35/$Y$96 -> 0.0069337442
A36: FOTON | B36: Bj1040 | C36: Chico | D36: 0 | E36: 0 | F36: 0 | G36: 0 | H36: 0 | I36: 0 | P36: =SUM(D36:O36) -> 0 | Q36: =+P36/$P$321 -> 0 | R36: - | S36: - | U36: HINO XZU600L | V36: M.BENZ | W36: Atego 2433/54 | X36: grande | Y36: 9 | Z36: =+Y36/$Y$96 -> 0.0069337442
A37: FOTON | B37: Bj1044 | C37: Chico | D37: 0 | E37: 0 | F37: 0 | G37: 0 | H37: 0 | I37: 0 | P37: =SUM(D37:O37) -> 0 | Q37: =+P37/$P$321 -> 0 | R37: 10684.84 | S37: 10684.84 | U37: Shacman SX3255DT384C | V37: FAW | W37: Tiger 3.8 | X37: chico | Y37: 8 | Z37: =+Y37/$Y$96 -> 0.0061633282
A38: FOTON | B38: BJ1065 | C38: Chico | D38: 0 | E38: 0 | F38: 0 | G38: 0 | H38: 0 | I38: 0 | P38: =SUM(D38:O38) -> 0 | Q38: =+P38/$P$321 -> 0 | R38: - | S38: - | U38: HYUNDAI EX | V38: FAW | W38: Tiger 5.9 | X38: Mediano | Y38: 8 | Z38: =+Y38/$Y$96 -> 0.0061633282
A39: FOTON | B39: BJ1088 | C39: Chico | D39: 0 | E39: 0 | F39: 0 | G39: 0 | H39: 30 | I39: 0 | P39: =SUM(D39:O39) -> 30 | Q39: =+P39/$P$321 -> 0.023112481 | R39: - | S39: - | U39: HINO FC | V39: HINO | W39: LY230L | X39: Mediano | Y39: 8 | Z39: =+Y39/$Y$96 -> 0.0061633282
A40: FOTON | B40: BJ2037 | C40: Chico | D40: 0 | E40: 0 | F40: 0 | G40: 0 | H40: 0 | I40: 0 | P40: =SUM(D40:O40) -> 0 | Q40: =+P40/$P$321 -> 0 | R40: - | S40: - | U40: ISUZU NPR71L | V40: HYUNDAI | W40: GT9 | X40: Mediano | Y40: 8 | Z40: =+Y40/$Y$96 -> 0.0061633282
A41: FOTON | B41: BJ1128 | C41: Chico | D41: 0 | E41: 0 | F41: 0 | G41: 0 | H41: 0 | I41: 0 | P41: =SUM(D41:O41) -> 0 | Q41: =+P41/$P$321 -> 0 | R41: - | S41: - | U41: Vw 6160 | V41: HYUNDAI | W41: GT11 | X41: Mediano | Y41: 8 | Z41: =+Y41/$Y$96 -> 0.0061633282
A42: FOTON | B42: BJ1166 | C42: Chico | D42: 0 | E42: 0 | F42: 0 | G42: 0 | H42: 0 | I42: 0 | P42: =SUM(D42:O42) -> 0 | Q42: =+P42/$P$321 -> 0 | U42: M.BENZ 915E | V42: JMC | W42: 5,6 TON. | X42: mediano | Y42: 8 | Z42: =+Y42/$Y$96 -> 0.0061633282
A43: FOTON | B43: BJ4189 | C43: grande | D43: 0 | E43: 0 | F43: 0 | G43: 0 | H43: 0 | I43: 0 | P43: =SUM(D43:O43) -> 0 | Q43: =+P43/$P$321 -> 0 | U43: M.BENZ 915E | V43: M.BENZ | W43: ACCELO 1416/46 6X2 | X43: grande | Y43: 8 | Z43: =+Y43/$Y$96 -> 0.0061633282
A44: Grove | B44: GMK6300 | C44: grande | D44: 0 | E44: 0 | F44: 0 | G44: 0 | H44: 0 | I44: 0 | P44: =SUM(D44:O44) -> 0 | Q44: =+P44/$P$321 -> 0 | R44: - | S44: - | V44: HINO | W44: WU720 | X44: Mediano | Y44: 7 | Z44: =+Y44/$Y$96 -> 0.0053929122
A45: HENGWANG | B45: HW3000L | C45: grande | D45: 0 | E45: 0 | F45: 0 | G45: 0 | H45: 0 | I45: 0 | P45: =SUM(D45:O45) -> 0 | Q45: =+P45/$P$321 -> 0 | U45: M.BENZ 915E | V45: HYUNDAI | W45: EX8 | X45: Mediano | Y45: 7 | Z45: =+Y45/$Y$96 -> 0.0053929122
A46: HENGWANG | B46: HW5000L | C46: grande | D46: 0 | E46: 0 | F46: 0 | G46: 0 | H46: 0 | I46: 0 | P46: =SUM(D46:O46) -> 0 | Q46: =+P46/$P$321 -> 0 | U46: M.BENZ 915E | V46: Scania | W46: K410C | X46: grande | Y46: 7 | Z46: =+Y46/$Y$96 -> 0.0053929122
A47: HENGTOP | B47: HT-6T | C47: grande | D47: 0 | E47: 0 | F47: 0 | G47: 0 | H47: 0 | I47: 1 | P47: =SUM(D47:O47) -> 1 | Q47: =+P47/$P$321 -> 0.00077041602 | V47: ISUZU | W47: PHR54 | X47: mediano | Y47: 6 | Z47: =+Y47/$Y$96 -> 0.0046224961
A48: HIGER | B48: KLQ6126 ELECT | C48: Omnibus | D48: 0 | E48: 0 | F48: 0 | G48: 0 | H48: 0 | I48: 0 | P48: =SUM(D48:O48) -> 0 | Q48: =+P48/$P$321 -> 0 | U48: M.BENZ 915E | V48: IVECO | W48: Gran Midi | X48: Omnibus | Y48: 6 | Z48: =+Y48/$Y$96 -> 0.0046224961
A49: HINO | B49: XZU600L | C49: Mediano | D49: 0 | E49: 0 | F49: 0 | G49: 0 | H49: 0 | I49: 0 | P49: =SUM(D49:O49) -> 0 | Q49: =+P49/$P$321 -> 0 | R49: - | S49: - | U49: M.BENZ 915E | V49: JAC | W49: LD250 CARGO BOX 2.5T | X49: Chico | Y49: 6 | Z49: =+Y49/$Y$96 -> 0.0046224961
A50: HINO | B50: XZU710L | C50: Mediano | D50: 0 | E50: 0 | F50: 0 | G50: 0 | H50: 0 | I50: 0 | P50: =SUM(D50:O50) -> 0 | Q50: =+P50/$P$321 -> 0 | R50: - | S50: - | U50: M.BENZ 915E | V50: JMC | W50: 2 TON DC | X50: chico | Y50: 6 | Z50: =+Y50/$Y$96 -> 0.0046224961
A51: HINO | B51: XZU720L | C51: Mediano | D51: 0 | E51: 2 | F51: 4 | G51: 0 | H51: 5 | I51: 0 | P51: =SUM(D51:O51) -> 11 | Q51: =+P51/$P$321 -> 0.0084745763 | R51: - | S51: - | U51: M.BENZ 915E | V51: TATA | W51: LPT709 | X51: Mediano | Y51: 6 | Z51: =+Y51/$Y$96 -> 0.0046224961
A52: HINO | B52: LY230L | C52: Mediano | D52: 4 | E52: 2 | F52: 1 | G52: 0 | H52: 1 | I52: 0 | P52: =SUM(D52:O52) -> 8 | Q52: =+P52/$P$321 -> 0.0061633282 | U52: M.BENZ 915E | V52: TATA | W52: SFC 407/31 | X52: Mediano | Y52: 6 | Z52: =+Y52/$Y$96 -> 0.0046224961
A53: HINO | B53: FC9 | C53: Mediano | D53: 13 | E53: 4 | F53: 5 | G53: 0 | H53: 0 | I53: 0 | P53: =SUM(D53:O53) -> 22 | Q53: =+P53/$P$321 -> 0.016949153 | R53: - | S53: - | U53: M.BENZ 915E | V53: ISUZU | W53: FRR90SL | X53: chico | Y53: 5 | Z53: =+Y53/$Y$96 -> 0.0038520801
A54: HINO | B54: WU720 | C54: Mediano | D54: 7 | E54: 0 | F54: 0 | G54: 0 | H54: 0 | I54: 0 | P54: =SUM(D54:O54) -> 7 | Q54: =+P54/$P$321 -> 0.0053929122 | R54: - | S54: - | U54: M.BENZ 915E | V54: JAC | W54: LE420 CARGO BOX 5.5T | X54: Mediano | Y54: 5 | Z54: =+Y54/$Y$96 -> 0.0038520801
A55: HUBEI | B55: CAMION | C55: grande | D55: 0 | E55: 0 | F55: 0 | G55: 0 | H55: 0 | I55: 0 | P55: =SUM(D55:O55) -> 0 | Q55: =+P55/$P$321 -> 0 | U55: M.BENZ 915E | V55: JAC | W55: LE760 CARGO BOX 4.5T | X55: Chico | Y55: 5 | Z55: =+Y55/$Y$96 -> 0.0038520801
A56: HYUNDAI | B56: EX6 | C56: Mediano | D56: 0 | E56: 2 | F56: 0 | G56: 2 | H56: 0 | I56: 23 | P56: =SUM(D56:O56) -> 27 | Q56: =+P56/$P$321 -> 0.020801233 | V56: CHUFENG | W56: HQG5080TQZBEVQC | X56: grande | Y56: 4 | Z56: =+Y56/$Y$96 -> 0.0030816641
